Workbook

Sheet Items
A1: ItemID | B1: LastName | C1: FirstName | D1: FullName | E1: Title | F1: College | G1: Department | H1: Email | I1: ItemType | J1: ItemTitle | K1: Year | L1: Venue / Funder | M1: Authors / Investigators | N1: Role | O1: Amount (USD) | P1: AwardID / PatentNo | Q1: DOI | R1: URL | S1: Sources | T1: SourceCount | U1: Confidence | V1: ScholarCitations | W1: CitationAsListed | X1: Abstract | Y1: AbstractSource | Z1: FullTextURL | AA1: FullTextType | AB1: OpenAccessStatus | AC1: School | AD1: Citations (OpenAlex) | AE1: AI-related | AF1: AI evidence | AG1: Check | AH1: Correction notes | AI1: Reviewed by
A2: AAS-0001 | B2: Botchway | C2: Karl | D2: Karl Botchway | E2: Associate Professor | F2: NYC College of Technology | G2: African American Studies | H2: karl.botchway07@citytech.cuny.edu | I2: Paper (venue type unclear) | J2: Botchway is a member of the African Studies Association, American Political Science Association, and The Academy of Political Science | S2: Dept bio | T2: 1 | U2: Medium (self-reported in faculty bio) | W2: Dr. Botchway is a member of the African Studies Association, American Political Science Association, and The Academy of Political Science. | AC2: School of Arts & Sciences | AE2: No
A3: AAS-0002 | B3: Botchway | C3: Karl | D3: Karl Botchway | E3: Associate Professor | F3: NYC College of Technology | G3: African American Studies | H3: karl.botchway07@citytech.cuny.edu | I3: Journal article | J3: Are Development Planners Afraid of History and Contextualization? Notes on Reading a Development Report on Northern Ghana | K3: 2001 | L3: Canadian Journal of African Studies / Revue canadienne des études africaines | M3: Karl Botchway | Q3: 10.1080/00083968.2001.10751216 | R3: https://doi.org/10.1080/00083968.2001.10751216 | S3: OpenAlex; Dept bio | T3: 2 | U3: High (City Tech affiliation on paper); 2 sources | W3: Are Development Planners Afraid of History and Contextualization? Notes on Reading a Development Report on Northern Ghana, Canadian Journal of African Studies, Volume 35, #1, 2001 | X3: Lorsqu’elles présentent leurs arguments en faveur du développement, estce que les agences de développement internationales analysent les sociétés qu’elles s’efforcent de développer comme des organismes engagées dans un processus historique plus large ou les voient-elles comme des sociétés isolées avec seulement quelques contacts sporadiques avec le monde extérieur? Cet article, analysant le cas d’un projet de développement rural dans la région nord du Ghana, conjointement financé par le Ghana et le Canada, affirme que les questions concernant le développement de cette région avaient été présentées comme si la pauvreté de la région était uniquement la conséquence des caractéristiques bio-physiques de la région et d’une piètre application des principes économiques. Cet article remet en question une telle emphase et déclare que le cas du projet de développement dans le Ghana du nord n’a pas été replacé dans son contexte et n’a pas suffisamment tenu compte de son histoire pour explorer les causes politiques, économiques et structurelles à long terme de la pauvreté dans cette région. Ce faisant, les questions contestées sur les causes socio-politiques et structurelles de la pauvreté deviennent dépolitisées. | Y3: OpenAlex | Z3: https://doi.org/10.2307/486346 | AA3: Not found | AB3: closed | AC3: School of Arts & Sciences | AD3: 4 | AE3: No
A4: AAS-0003 | B4: Botchway | C4: Karl | D4: Karl Botchway | E4: Associate Professor | F4: NYC College of Technology | G4: African American Studies | H4: karl.botchway07@citytech.cuny.edu | I4: Journal article | J4: Paradox of Empowerment: Reflections on a Case Study from Northern Ghana | K4: 2001 | L4: World Development | M4: Karl Botchway | Q4: 10.1016/s0305-750x(00)00084-x | R4: https://doi.org/10.1016/s0305-750x(00)00084-x | S4: OpenAlex; Dept bio | T4: 2 | U4: High (City Tech affiliation on paper); 2 sources | W4: Paradox of Empowerment: Reflections on a Case Study from Northern Ghana, World Development Vol. 29, #1, 2001 | AA4: Not found | AB4: closed | AC4: School of Arts & Sciences | AD4: 155 | AE4: No
A5: AAS-0004 | B5: Botchway | C5: Karl | D5: Karl Botchway | E5: Associate Professor | F5: NYC College of Technology | G5: African American Studies | H5: karl.botchway07@citytech.cuny.edu | I5: Paper (venue type unclear) | J5: Understanding "Development" Interventions in Northern Ghana, Edwin Mellen Press, Lewiston, NY, 2004 | K5: 2004 | S5: Dept bio | T5: 1 | U5: Medium (self-reported in faculty bio) | W5: Understanding "Development" Interventions in Northern Ghana, Edwin Mellen Press, Lewiston, NY, 2004 | AC5: School of Arts & Sciences | AE5: No
A6: AAS-0005 | B6: Biswas | C6: Debarati | D6: Debarati Biswas | E6: Assistant Professor | F6: NYC College of Technology | G6: African American Studies | H6: debarati.biswas57@citytech.cuny.edu | I6: Journal article | J6: Beyond the Parasitical Logic in Octavia Butler's Fledgling (2005) | K6: 2005 | M6: Chapter in Edited Book: “Beyond the Parasitical Logic in Octavia Butler's Fledgling | S6: Dept bio | T6: 1 | U6: Medium (self-reported in faculty bio) | W6: Chapter in Edited Book: “Beyond the Parasitical Logic in Octavia Butler's Fledgling (2005).” Parasitical Logic in Culture and Society. Ed. By Peter Hitchcock. Bloomsbury Publishing, 2026. Journals: Articles in Refereed Journals: Unbearable Being(s). Special Issue, WSQ: Women’s Studies Quarterly, vol. 52, numbers 3&4. Fall/Winter, 2024. Co-guest editor with Laura Westengard. “Rehearsals for Living Within the Unbearable: Tracking Possibilities of Love and Solidarity in Black Art and Literature.” Special Issue, WSQ: Women's Studies Quarterly 52, no. 3 (2024): 283-296. “Rituals of Survival in Single Room Occupancy Hotels,” Social Text, 158, vol. 42. issue 1, March 2024. Co-authored with Kirin Wachter Grene. Other Publications: “New College of Florida: The Conservative Christian Takeover by Ron DeSantis, Chris Rufo.” Teen Vogue: Politics, March 2023. Co-authored with Erik Wallenberg. “How to Subvert the Capitalist White-Supremacist University.” Public Books, May 2020. | AC6: School of Arts & Sciences | AE6: No
A7: AAS-0006 | B7: Botchway | C7: Karl | D7: Karl Botchway | E7: Associate Professor | F7: NYC College of Technology | G7: African American Studies | H7: karl.botchway07@citytech.cuny.edu | I7: Paper (venue type unclear) | J7: The Politics and Apolitics of Development: The Case of Development Project in Northern Ghana, in Kwadwo Konadu-Agyemang and Kwamina Panford (eds.) Africa's Development in the Twenty-first Century, Ashgate Publishing Company, Burlington, VT, 2006 | K7: 2006 | S7: Dept bio | T7: 1 | U7: Medium (self-reported in faculty bio) | W7: The Politics and Apolitics of Development: The Case of Development Project in Northern Ghana, in Kwadwo Konadu-Agyemang and Kwamina Panford (eds.) Africa's Development in the Twenty-first Century, Ashgate Publishing Company, Burlington, VT, 2006 | AC7: School of Arts & Sciences | AE7: No
A8: AAS-0007 | B8: Botchway | C8: Karl | D8: Karl Botchway | E8: Associate Professor | F8: NYC College of Technology | G8: African American Studies | H8: karl.botchway07@citytech.cuny.edu | I8: Journal article | J8: Challenging the Orthodoxy: African Development in the Age of Openness | K8: 2007 | L8: African and Asian Studies | M8: Jamee K. Moudud; Karl Botchway | Q8: 10.1163/156921007x236981 | R8: https://doi.org/10.1163/156921007x236981 | S8: OpenAlex; Dept bio | T8: 2 | U8: High (City Tech affiliation on paper); 2 sources | W8: Challenging the Orthodoxy: African Development in the Age of Openness, African and Asian Studies, Volume 6, #4, 2007. (With Jamee Moudud) | X8: Abstract Does trade openness necessarily lead to income convergence between countries in the North and South and hence facilitates social development? This paper challenges this claim with regards to African development in the age of neo-liberalism. The paper argues that a one-sided reading of the history of an early phase of globalization by advocates of neo-liberalism seems to have turned trade openness into a mantra for African development. Furthermore the paper challenges the rhetoric of competitiveness that underpins the rationale for neo-liberalism by critiquing the neoclassical model of competition. The neo-liberal policy position, as the paper suggests is problematic at an empirical level also. In a test for convergence for eleven sub-Saharan African countries described as good adjusters by advocates of trade openness, the paper shows that a straightforward openness per se guarantees nothing as far their growth rates are concerned. Rather this paper suggests that the role of the “developmental state” needs to be brought back in order to facilitate the international competitiveness of African countries. It will be argued that such a role for the developmental state rests on a very different conceptualization of the nature of capitalist competition and growth. In the final instance, then, we suggest the need for building a theory of the developmental state that rests on non-neoclassical macro- and micro-foundations. | Y8: OpenAlex | AA8: Not found | AB8: closed | AC8: School of Arts & Sciences | AD8: 4 | AE8: No
A9: AAS-0010 | B9: Botchway | C9: Karl | D9: Karl Botchway | E9: Associate Professor | F9: NYC College of Technology | G9: African American Studies | H9: karl.botchway07@citytech.cuny.edu | I9: Journal article | J9: The Search for a New Developmental State | K9: 2008 | L9: International Journal of Political Economy | M9: Jamee K. Moudud; Karl Botchway | Q9: 10.2753/ijp0891-1916370301 | R9: https://doi.org/10.2753/ijp0891-1916370301 | S9: OpenAlex; Dept bio | T9: 2 | U9: High (City Tech affiliation on paper); 2 sources | W9: The Search for a New Developmental State, International Journal of Political Economy, vol. 37, no. 3, Fall 2008. (With Jamee Moudud) | X9: (2008). The Search for a New Developmental State. International Journal of Political Economy: Vol. 37, No. 3, pp. 5-26. | Y9: OpenAlex | AA9: Not found | AB9: closed | AC9: School of Arts & Sciences | AD9: 6 | AE9: No
A10: AAS-0013 | B10: Botchway | C10: Karl | D10: Karl Botchway | E10: Associate Professor | F10: NYC College of Technology | G10: African American Studies | H10: karl.botchway07@citytech.cuny.edu | I10: Paper (venue type unclear) | J10: Neo-Liberalism and the Developmental State: Considerations for the New Partnership For Africa’s Development, in Benjamin F. Bobo and Hermann Sintim-Aboagye, Neo-Liberalism, Interventionism and the Developmental State, Africa World Press, Trenton, NJ, 2012 | K10: 2012 | S10: Dept bio | T10: 1 | U10: Medium (self-reported in faculty bio) | W10: Neo-Liberalism and the Developmental State: Considerations for the New Partnership For Africa’s Development, in Benjamin F. Bobo and Hermann Sintim-Aboagye, Neo-Liberalism, Interventionism and the Developmental State, Africa World Press, Trenton, NJ, 2012. (With Jamee Moudud) | AC10: School of Arts & Sciences | AE10: No
A11: AAS-0023 | B11: Ferdinand | C11: Renata | D11: Renata Ferdinand | E11: Chair | F11: NYC College of Technology | G11: African American Studies | H11: Renata.Ferdinand92@citytech.cuny.edu | I11: Journal article | J11: Writing Home | K11: 2014 | L11: Space and Culture | M11: Renata Harden Ferdinand | Q11: 10.1177/1206331213510445 | R11: https://doi.org/10.1177/1206331213510445 | S11: OpenAlex | T11: 1 | U11: High (City Tech affiliation on paper) | X11: Africa as an ancestral home is a prominent theme among African Americans. Many have sojourned to Africa in the hopes of establishing a cultural or spiritual connection with the continent. This essay investigates the ways in which African Americans encounter African culture and space. Specifically, this is an auto-ethnographic essay that details the author’s diasporic identity transformation as a result of visiting the West African nation of Burkina Faso. Enabled by educational courses and through a living arrangement with a host family, the author establishes how Burkina Faso became a surrogate home. | Y11: OpenAlex | AA11: Not found | AB11: closed | AC11: School of Arts & Sciences | AD11: 7 | AE11: No
A12: AAS-0026 | B12: Ferdinand | C12: Renata | D12: Renata Ferdinand | E12: Chair | F12: NYC College of Technology | G12: African American Studies | H12: Renata.Ferdinand92@citytech.cuny.edu | I12: Journal article | J12: It’s like a black woman’s Charlie Brown moment: An autoethnography of being diagnosed with lupus | K12: 2016 | L12: Journal of Health Psychology | M12: Renata Harden Ferdinand | Q12: 10.1177/1359105316664128 | R12: https://doi.org/10.1177/1359105316664128 | S12: OpenAlex | T12: 1 | U12: High (City Tech affiliation on paper) | X12: This essay uses autoethnography to relate the experience of being diagnosed with lupus. By using my personal experiences and a discussion of illness and Black women's health, I critically examine larger critical race issues of race, gender, and the social barriers to health care. Specifically, the essay focuses on the ways in which race impacts my experiences with the healthcare system, from my own insecurities of being stereotyped to the ways that doctors interact with me. The essay is framed by popular quotes from Charlie Brown because they help mediate the very personal experiences I am recounting. | Y12: OpenAlex | AA12: Not found | AB12: closed | AC12: School of Arts & Sciences | AD12: 5 | AE12: No
A13: AAS-0028 | B13: Ferdinand | C13: Renata | D13: Renata Ferdinand | E13: Chair | F13: NYC College of Technology | G13: African American Studies | H13: Renata.Ferdinand92@citytech.cuny.edu | I13: Journal article | J13: Remember, Me: An Interlocking Narrative of Black Women’s Past and Present | K13: 2017 | L13: Culture Studies &#x2194 Critical Methodologies | M13: Renata Harden Ferdinand | Q13: 10.1177/1532708617744575 | R13: https://doi.org/10.1177/1532708617744575 | S13: OpenAlex | T13: 1 | U13: High (City Tech affiliation on paper) | X13: This is a postcolonial autoethnography that explores the historical and contemporary plight of African American women. Specifically, it uses narrative and performative writing to demonstrate how both groups operate within similar systems of domination, leading to their existence as a disenfranchised, liminal group. By bridging the past with the present, the author draws a parallel between the lives of contemporary Black women and their historical predecessors, thereby showing the connection between seemingly disparate historical events. Furthermore, this essay examines the author’s particular location as a diasporic subject, exploring how she exists in an illusion of freedom, and with a disjointed subjectivity. Summarily, this essay examines larger issues of race, gender, and the identity politics of the diasporic subject, all in an effort to show how the past is recapitulated into the present. It offers a more nuanced way of thinking about the past, present, and the future. | Y13: OpenAlex | AA13: Not found | AB13: closed | AC13: School of Arts & Sciences | AD13: 7 | AE13: No
A14: AAS-0032 | B14: Evangelista | C14: Javiela | D14: Javiela Evangelista | E14: Associate Professor | F14: NYC College of Technology | G14: African American Studies | H14: javiela.evangelista75@citytech.cuny.edu | I14: Open educational resource | J14: The Heritage of Imperialism, AFR 2402 ID, Course Outline | K14: 2018 | L14: Open Educational Resources | M14: Evangelista, Javiela | R14: https://academicworks.cuny.edu/ny_oers/64 | S14: CUNY Academic Works | T14: 1 | U14: High (in CUNY Academic Works) | X14: This course offers an examination of the thought, structure, operation and results of imperialism in human history generally, and in the 19th/21st centuries in particular. We will use readings and films to examine European/American imperialism in the non-white areas of the world: the role of the Industrial Revolution; the imposition of Western European institutions on indigenous peoples of Africa, Asia, North/South America; colonialism; attempts by these people to reestablish autonomous sociological and cultural systems. | Y14: CUNY Academic Works | Z14: https://academicworks.cuny.edu/context/ny_oers/article/1073/viewcontent/auto_convert.pdf | AA14: PDF in CUNY Academic Works | AC14: School of Arts & Sciences | AE14: No
A15: AAS-0033 | B15: Effinger-Crichlow | C15: Marta | D15: Marta Effinger-Crichlow | E15: Professor | F15: NYC College of Technology | G15: African American Studies | H15: marta.effinger-crichlow45@citytech.cuny.edu | I15: Book chapter | J15: A Pedagogical Search for Home and Care | K15: 2019 | L15: University of Minnesota Press eBooks | M15: Marta Effinger-Crichlow | Q15: 10.5749/j.ctvg251hk.43 | R15: https://doi.org/10.5749/j.ctvg251hk.43 | S15: OpenAlex; CUNY Academic Works | T15: 2 | U15: High (City Tech affiliation on paper); 2 sources | Z15: https://academicworks.cuny.edu/context/ny_pubs/article/1485/viewcontent/effinger.pdf | AA15: Not found | AB15: closed | AC15: School of Arts & Sciences | AD15: 0 | AE15: No
A16: AAS-0036 | B16: Evangelista | C16: Javiela | D16: Javiela Evangelista | E16: Associate Professor | F16: NYC College of Technology | G16: African American Studies | H16: javiela.evangelista75@citytech.cuny.edu | I16: Book chapter | J16: Deconstructing the Heritage of Imperialism Toward Life-Long Learning: High-Impact Practices that Further Student Self-Actualization and Social Justice Analyses | K16: 2020 | L16: Springer eBooks | M16: Javiela Evangelista | Q16: 10.1007/978-3-030-56302-8_6 | R16: https://doi.org/10.1007/978-3-030-56302-8_6 | S16: OpenAlex | T16: 1 | U16: High (City Tech affiliation on paper) | AA16: Not found | AB16: closed | AC16: School of Arts & Sciences | AD16: 1 | AE16: No
A17: AAS-0047 | B17: Ferdinand | C17: Renata | D17: Renata Ferdinand | E17: Chair | F17: NYC College of Technology | G17: African American Studies | H17: Renata.Ferdinand92@citytech.cuny.edu | I17: Journal article | J17: Black Women, Black Girls, and the Covid-19 Pandemic: An Autoethnography of a Health Disparity | K17: 2022 | L17: Culture Studies &#x2194 Critical Methodologies | M17: Renata Harden Ferdinand; Rajah Emahn Ferdinand | Q17: 10.1177/15327086221087666 | R17: https://doi.org/10.1177/15327086221087666 | S17: OpenAlex | T17: 1 | U17: High (City Tech affiliation on paper) | X17: This is an autoethnographic essay that explores how the Covid-19 pandemic affect(ed) Black women and girls. Through storytelling and narrative and performative writing, it paints a clearer picture of the lives lost due to the coronavirus by highlighting specific tragedies that occurred, and by examining the larger societal context that allowed such tragedies to unfold. In addition, it offers an intimate look at the emotional processes that occur when one is diagnosed with the virus. | Y17: OpenAlex | AA17: Not found | AB17: closed | AC17: School of Arts & Sciences | AD17: 1 | AE17: No
A18: AAS-0048 | B18: Ferdinand | C18: Renata | D18: Renata Ferdinand | E18: Chair | F18: NYC College of Technology | G18: African American Studies | H18: Renata.Ferdinand92@citytech.cuny.edu | I18: Journal article | J18: Teaching Black Girlhood Studies with Black Motherhood Studies | K18: 2022 | L18: Girlhood Studies | M18: Renata Harden Ferdinand | Q18: 10.3167/ghs.2022.150306 | R18: https://doi.org/10.3167/ghs.2022.150306 | S18: OpenAlex | T18: 1 | U18: High (City Tech affiliation on paper) | X18: What is the relationship between Black Girlhood Studies and Black Motherhood Studies? In this article I answer this question by considering the ways in which these subjects can be explored together or in relation to each other. Using autoethnography, I describe the process of teaching Black Girlhood Studies with Black Motherhood Studies. Specifically, through narrative and performative writing, I draw upon my own personal experience of using research and scholarship associated with Black Girlhood Studies to inform and provide a foundation for the exploration of Black Motherhood Studies in an effort to promote a fuller, more complete and nuanced understanding of both social positions. | Y18: OpenAlex | AA18: Not found | AB18: closed | AC18: School of Arts & Sciences | AD18: 2 | AE18: No
A19: AAS-0050 | B19: Evangelista | C19: Javiela | D19: Javiela Evangelista | E19: Associate Professor | F19: NYC College of Technology | G19: African American Studies | H19: javiela.evangelista75@citytech.cuny.edu | I19: Conference presentation | J19: Implicit Bias Among Health Professionals | K19: 2023 | L19: Publications and Research | M19: Toussaint, Kimora H.; Evangelista, Javiela | R19: https://academicworks.cuny.edu/ny_pubs/1141 | S19: CUNY Academic Works | T19: 1 | U19: High (in CUNY Academic Works) | X19: Racism and implicit bias are prevalent in healthcare, which may affect patient well-being. One way implicit bias is most evident is in language. Negative descriptors, such as âsicklerââa term used for those diagnosed with Sickle Cell Disease (SCD), influence how health providers view their patients and determine pain medication prescriptions (Goddu et al.). Patient experience, such as prior use of opioids or using words that imply substance abuse, may block patients from accessing prescriptions and proper care. Black, Indigenous, and People of Color (BIPOC) are disproportionately affected by such negative descriptors (Sun et al., 2022). Among other adverse impacts, treating patient pain accounts for mental health or sleep issues and increases the number of unnecessary visits to the hospital (Keister et al., 2016). How patients are described in their Electronic Medical Records (EMRs) reveals prejudice in health practices, which may prevent adequate care and impact interactions with future health providers. Prejudices and biases are also presented in non-verbal communication, such as glances or facial expressions. This poster will include an analysis of peer-reviewed articles on data collection experiments and language use in Electronic Medical Records. In the end, methods for health professionals to acknowledge and address their unconscious biases, including health equity education, will be presented (Cooper et al., Healy et al.). | Y19: CUNY Academic Works | Z19: https://academicworks.cuny.edu/context/ny_pubs/article/2170/viewcontent/Implicit_Bias_Among_Health_Professionals.pdf | AA19: PDF in CUNY Academic Works | AC19: School of Arts & Sciences | AE19: No
A20: ARCH-0003 | B20: Anzalone | C20: Phillip | D20: Phillip Anzalone | E20: Associate Professor | F20: NYC College of Technology | G20: Architectural Technology | H20: PAnzalone@citytech.cuny.edu | I20: Journal article | J20: Trusset: Parallel Development of Software and Construction Systems for Space-Truss Structures | K20: 2004 | L20: International Journal of Architectural Computing | M20: Cory Clarke; Phillip Anzalone | Q20: 10.1260/1478077041518700 | R20: https://doi.org/10.1260/1478077041518700 | S20: OpenAlex; CUNY Academic Works | T20: 2 | U20: High (City Tech affiliation on paper); 2 sources | X20: This paper documents our current progress on the parallel development of a building system and corresponding agent-based software design tools; together the two produce a seamless pipeline from design to fabrication and assembly. The building system is a clad differential space-truss designed for fabrication entirely with computer numerically controlled (CNC) linear cutting devices such as CNC laser cutters or two-axis mills. The software component is a set of agent-based design tools for developing surfaces and envelopes formally suitable to be built using our space-truss system. | Y20: OpenAlex | Z20: https://academicworks.cuny.edu/context/ny_pubs/article/1192/viewcontent/ijac20032206.content.pdf | AA20: Not found | AB20: closed | AC20: School of Technology & Design | AD20: 2 | AE20: No
A21: ARCH-0010 | B21: Anzalone | C21: Phillip | D21: Phillip Anzalone | E21: Associate Professor | F21: NYC College of Technology | G21: Architectural Technology | H21: PAnzalone@citytech.cuny.edu | I21: Conference paper | J21: Non-Uniform Assemblage: Mass Customization in Digital Fabrication | K21: 2008 | L21: ScholarWorks@UMassAmherst (University of Massachusetts Amherst) | M21: Phillip Anzalone; Joseph Vidich; Joshua Draper | R21: https://openalex.org/W1558420933 | S21: OpenAlex; CUNY Academic Works | T21: 2 | U21: High (City Tech affiliation on paper); 2 sources | X21: This paper focuses on the development of parametric detailing, mass customization in CNC fabrication and its computational and handcrafted realizations in actualized built work.The projects studied are examples of student and faculty applied research work at Columbia University's Graduate School of Architecture that engage parametric design strategies to integrate digital fabrication processes with manual assembly procedures, including prefabricated components and assemblies.The presented case studies include the design, fabrication and assembly of two full-scale pavilion projects. | Y21: OpenAlex | Z21: https://scholarworks.umass.edu/wood/2008/sept27/8 | AA21: Open-access PDF (via OpenAlex) | AB21: green | AC21: School of Technology & Design | AD21: 3 | AE21: No
A22: ARCH-0016 | B22: Anzalone | C22: Phillip | D22: Phillip Anzalone | E22: Associate Professor | F22: NYC College of Technology | G22: Architectural Technology | H22: PAnzalone@citytech.cuny.edu | I22: Journal article | J22: Framing Space | K22: 2010 | L22: Publications and Research | M22: Anzalone, Phillip; Bayard, Stephanie | R22: https://academicworks.cuny.edu/ny_pubs/976 | S22: CUNY Academic Works | T22: 1 | U22: High (in CUNY Academic Works) | Z22: https://academicworks.cuny.edu/context/ny_pubs/article/2004/viewcontent/ACSA.AM.98.54.pdf | AA22: PDF in CUNY Academic Works | AC22: School of Technology & Design | AE22: No
A23: ARCH-0019 | B23: Vaidya | C23: Sanjive | D23: Sanjive Vaidya | E23: Associate Professor | F23: NYC College of Technology | G23: Architectural Technology | H23: SVaidya@citytech.cuny.edu | I23: Grant | J23: 2011-2015 CO-PI for NSF‐ ATE Grant: FuseLab: Director of Sustainability and Building Performance | K23: 2011 | N23: Co-PI | S23: Dept bio | T23: 1 | U23: Medium (self-reported in faculty bio) | W23: 2011-2015 CO-PI for NSF‐ ATE Grant: FuseLab: Director of Sustainability and Building Performance | AC23: School of Technology & Design | AE23: No
A24: ARCH-0020 | B24: Vaidya | C24: Sanjive | D24: Sanjive Vaidya | E24: Associate Professor | F24: NYC College of Technology | G24: Architectural Technology | H24: SVaidya@citytech.cuny.edu | I24: Grant | J24: 2011-2015 Design_Serv : Mentoring Program Director | K24: 2011 | S24: Dept bio | T24: 1 | U24: Medium (self-reported in faculty bio) | W24: 2011-2015 Design_Serv : Mentoring Program Director | AC24: School of Technology & Design | AE24: No
A25: ARCH-0021 | B25: Smith | C25: Shelley | D25: Shelley Smith | E25: Professor | F25: NYC College of Technology | G25: Architectural Technology | H25: SSmith@citytech.cuny.edu | I25: Grant | J25: Fuse Lab: Collaborative Education for Tomorrow's Technology in Architecture, Engineering, and Construction | K25: 2011 | L25: NSF: Advanced Tech Education Prog | M25: Shelley Smith; Huseyin Yuce; Gerarda M Shields; Anne Leonhardt; Marie Segares | N25: PI | O25: 877322 | P25: 1104254 | R25: https://www.nsf.gov/awardsearch/showAward?AWD_ID=1104254 | S25: NSF | T25: 1 | U25: High (NSF award to City Tech) | X25: New York City College of Technology (City Tech) in collaboration with Polytechnic High School of Engineering, Architecture and Technology (City Poly) and industry partners are implementing an initiative titled Fuse Lab in an effort to transform the AEC (architecture, engineering and construction) curriculum and develop faculty expertise. This initiative provides a model for other undergraduate AEC programs around the country. In order to produce students who can take advantage of and continuously adapt to the fields' rapidly evolving computational, construction and sustainable technologies, Fuse lab is 1) developing and implementing an articulated career pathway (3+2+2) that serves a diverse population of students and leads to the associate and baccalaureate degree while offering students multiple exit points that were integrated with industry certification; 2) creating curriculum units and faculty development opportunities that reflect the technology integration and interdisciplinary team work that have transformed industry practice; and 3) situating these activities in a larger advanced technology loop by creating sustainable mechanisms for industry participation across the career pathway and by joining existing feedback loops with ATE centers and related projects. The broader impact of the project includes addressing future needs of AEC technicians, increasing participation of underrepresented populations and producing a new AEC curriculum that can serve as a national model. | Y25: NSF | AC25: School of Technology & Design | AE25: No
A26: ARCH-0022 | B26: Leonhardt | C26: Anne | D26: Anne Leonhardt | E26: Associate Professor | F26: NYC College of Technology | G26: Architectural Technology | H26: ALeonhardt@citytech.cuny.edu | I26: Grant | J26: Fuse Lab: Collaborative Education for Tomorrow's Technology in Architecture, Engineering, and Construction | K26: 2011 | L26: NSF: Advanced Tech Education Prog | M26: Shelley Smith; Huseyin Yuce; Gerarda M Shields; Anne Leonhardt; Marie Segares | N26: Co-PI | O26: 877322 | P26: 1104254 | R26: https://www.nsf.gov/awardsearch/showAward?AWD_ID=1104254 | S26: NSF | T26: 1 | U26: High (NSF award to City Tech) | X26: New York City College of Technology (City Tech) in collaboration with Polytechnic High School of Engineering, Architecture and Technology (City Poly) and industry partners are implementing an initiative titled Fuse Lab in an effort to transform the AEC (architecture, engineering and construction) curriculum and develop faculty expertise. This initiative provides a model for other undergraduate AEC programs around the country. In order to produce students who can take advantage of and continuously adapt to the fields' rapidly evolving computational, construction and sustainable technologies, Fuse lab is 1) developing and implementing an articulated career pathway (3+2+2) that serves a diverse population of students and leads to the associate and baccalaureate degree while offering students multiple exit points that were integrated with industry certification; 2) creating curriculum units and faculty development opportunities that reflect the technology integration and interdisciplinary team work that have transformed industry practice; and 3) situating these activities in a larger advanced technology loop by creating sustainable mechanisms for industry participation across the career pathway and by joining existing feedback loops with ATE centers and related projects. The broader impact of the project includes addressing future needs of AEC technicians, increasing participation of underrepresented populations and producing a new AEC curriculum that can serve as a national model. | Y26: NSF | AC26: School of Technology & Design | AE26: No
A27: ARCH-0023 | B27: King | C27: Paul | D27: Paul King | E27: Professor | F27: NYC College of Technology | G27: Architectural Technology | H27: PKing@citytech.cuny.edu | I27: Journal article | J27: Technology and Teaching Philosophy | K27: 2011 | L27: Journal of Educational Technology Systems | M27: Paul C. King | Q27: 10.2190/et.40.2.f | R27: https://doi.org/10.2190/et.40.2.f | S27: OpenAlex | T27: 1 | U27: High (City Tech affiliation on paper) | X27: This article discusses the challenges faced when integrating new technologies into the classroom. Viewing the experiences of teaching a first year learning community through the lens of the principles of the Reflective Teaching Portfolio, the author looks to answer the question: How should Technology relate to our Teaching Philosophy? While a proponent of testing and integrating new technologies into the classroom, the author also recognizes that we learn more from our mistakes than from our successes and that if a tool does not fit with our Teaching Philosophy, then we should not use it. This article provides an honest assessment of recent experiences integrating online learning technologies into the classroom and makes suggestions on how to develop a successful approach. | Y27: OpenAlex | AA27: Not found | AB27: closed | AC27: School of Technology & Design | AD27: 5 | AE27: No
A28: ARCH-0024 | B28: Leonhardt | C28: Anne | D28: Anne Leonhardt | E28: Associate Professor | F28: NYC College of Technology | G28: Architectural Technology | H28: ALeonhardt@citytech.cuny.edu | I28: Grant | J28: Center for Performative Design and Engineering Technology: Pioneering Performative Processes in Design and Engineering Technology Education | K28: 2012 | L28: NSF: S-STEM-Schlr Sci Tech Eng&Math, TUES-Type 1 Project | M28: Anne Leonhardt; John McCullough; Adam Wilson; Iem Heng (Former); Anne Leonhardt (Former) | N28: PI | O28: 199820 | P28: 1141234 | R28: https://www.nsf.gov/awardsearch/showAward?AWD_ID=1141234 | S28: NSF | T28: 1 | U28: High (NSF award to City Tech) | X28: The School of Technology and Design at New York City College of Technology proposes to create a new Center for Performative Design and Engineering Technology that will pioneer performative design education. The project takes as its inspiration the broad focus on laboratory-based learning that brings technological education to a higher level of integration and broader faculty engagement across an entire division. The Center will become the focus of interdisciplinary project-based learning for faculty and students from its nine constituent departments where they will conduct research projects using state-of-the-art technologies in cross-cutting applications that mirror industry practice. The project will produce a laboratory design to support interdisciplinary research by configuring equipment and instrumentation for optimal collaborative use. A faculty team will create a web-based tutorial system for asynchronous learning to accompany interdisciplinary applications of cutting-edge technology. They will also design a new interdisciplinary capstone course and four cross-disciplinary projects for baccalaureate-level students. This project will provide a model for other institutions with similar programs to emulate. By bringing project-based interdisciplinary team collaborations to the fore, the project will contribute to an on-going paradigm shift in the way engineering design is taught. The project will also broaden participation since New York City College of Technology serves a high percentage of underrepresented minority students and is one of the nation's top producers of underrepresented minority associate degree graduates in STEM fields. | Y28: NSF | AC28: School of Technology & Design | AE28: No
A29: ARCH-0027 | B29: Smith | C29: Shelley | D29: Shelley Smith | E29: Professor | F29: NYC College of Technology | G29: Architectural Technology | H29: SSmith@citytech.cuny.edu | I29: Preprint | J29: Bounding the distinguishing number of infinite graphs | K29: 2013 | L29: arXiv (Cornell University) | M29: Simon M. Smith; Mark E. Watkins | Q29: 10.48550/arxiv.1302.4409 | R29: https://doi.org/10.48550/arxiv.1302.4409 | S29: OpenAlex | T29: 1 | U29: High (City Tech affiliation on paper) | X29: A group of permutations G of a set V is k-distinguishable if there exists a partition of V into k parts such that only the identity permutation in G fixes setwise all of the cells of the partition. The least cardinal number k such that (G,V) is k-distinguishable is its distinguishing number. In particular, a graph X is k-distinguishable if its automorphism group Aut(X) has distinguishing number at most k in its action on the vertices of X. Various results in the literature demonstrate that when an infinite graph fails to have some property, then often some finite subgraph is similarly deficient. In this paper we show that whenever an infinite connected graph X is not k-distinguishable (for a given cardinal k), then it contains a ball B of finite radius whose distinguishing number is at least k. Moreover, this lower bound cannot be sharpened, since for any integer k greater than 3 there exists an infinite, locally finite, connected graph X that is not k-distinguishable but in which every ball of finite radius is k-distinguishable. In the second half of this paper we show that a large distinguishing number for an imprimitive graph X is traceable to a high distinguishing number either of a block of imprimitivity or of the induced action of Aut(X) on the corresponding system of imprimitivity. The distinguishing numbers of infinite primitive graphs have been examined in detail in a previous paper by the authors together with Tom W. Tucker. | Y29: OpenAlex | Z29: https://arxiv.org/pdf/1302.4409 | AA29: Open-access PDF (via OpenAlex) | AB29: green | AC29: School of Technology & Design | AD29: 1 | AE29: No
A30: ARCH-0029 | B30: King | C30: Paul | D30: Paul King | E30: Professor | F30: NYC College of Technology | G30: Architectural Technology | H30: PKing@citytech.cuny.edu | I30: Book chapter | J30: Integrated Projects and the Development of Interdisciplinary Problem-Solving Strategies | K30: 2013 | L30: IGI Global eBooks | M30: Paul C. King | Q30: 10.4018/978-1-4666-4502-8.ch079 | R30: https://doi.org/10.4018/978-1-4666-4502-8.ch079 | S30: OpenAlex | T30: 1 | U30: High (City Tech affiliation on paper) | X30: Interdisciplinary problem solving and research skills require early preparation in two categories: critical thinking and communication. This chapter reviews the two-year process of interdisciplinary curriculum development, shaped by collaboration between the New York City Department of Education, the New York City College of Technology of the City University of New York, and City Polytechnic High School of Engineering, Architecture, and Technology. The resulting course, “Inter-Academy Integrated Projects” (IP), emphasizes multidisciplinary problem solving that includes creativity, observation, research, visual and discursive communication, and reflection. The collaborative lessons make use of project-based methodology and emphasize social responsibility. Core skills are combined across the two trimesters of IP. This endeavor will be contrasted and compared to the work of the Partnership for the 21st Century Skills by examining the use of high-impact learning practices, feedback from students and teachers, and the issues surrounding the implementation of any new curriculum. | Y30: OpenAlex | AA30: Not found | AB30: closed | AC30: School of Technology & Design | AD30: 0 | AE30: No
A31: ARCH-0030 | B31: Vaidya | C31: Sanjive | D31: Sanjive Vaidya | E31: Associate Professor | F31: NYC College of Technology | G31: Architectural Technology | H31: SVaidya@citytech.cuny.edu | I31: Grant | J31: 2014 Intersections Symposium Organizer: Conversant Technologies for Building Collaboration | K31: 2014 | S31: Dept bio | T31: 1 | U31: Medium (self-reported in faculty bio) | W31: 2014 Intersections Symposium Organizer: Conversant Technologies for Building Collaboration | AC31: School of Technology & Design | AE31: No
A32: ARCH-0034 | B32: Smith | C32: Shelley | D32: Shelley Smith | E32: Professor | F32: NYC College of Technology | G32: Architectural Technology | H32: SSmith@citytech.cuny.edu | I32: Journal article | J32: Bounding the Distinguishing Number of Infinite Graphs and Permutation Groups | K32: 2014 | L32: The Electronic Journal of Combinatorics | M32: Simon M. Smith; Mark E. Watkins | Q32: 10.37236/3046 | R32: https://doi.org/10.37236/3046 | S32: OpenAlex | T32: 1 | U32: High (City Tech affiliation on paper) | X32: A group of permutations $G$ of a set $V$ is $k$-distinguishable if there exists a partition of $V$ into $k$ cells such that only the identity permutation in $G$ fixes setwise all of the cells of the partition. The least cardinal number $k$ such that $(G,V)$ is $k$-distinguishable is its distinguishing number $D(G,V)$. In particular, a graph $\Gamma$ is $k$-distinguishable if its automorphism group $\rm{Aut}(\Gamma)$ satisfies $D(\rm{Aut}(\Gamma),V\Gamma)\leq k$.Various results in the literature demonstrate that when an infinite graph fails to have some property, then often some finite subgraph is similarly deficient. In this paper we show that whenever an infinite connected graph $\Gamma$ is not $k$-distinguishable (for a given cardinal $k$), then it contains a ball of finite radius whose distinguishing number is at least $k$. Moreover, this lower bound cannot be sharpened, since for any integer $k \geq 3$ there exists an infinite, locally finite, connected graph $\Gamma$ that is not $k$-distinguishable but in which every ball of finite radius is $k$-distinguishable.In the second half of this paper we show that a large distinguishing number for an imprimitive group $G$ is traceable to a high distinguishing number either of a block of imprimitivity or of the induced action by $G$ on the corresponding system of imprimitivity. An immediate application is to automorphism groups of infinite imprimitive graphs. These results are companion to the study of the distinguishing number of infinite primitive groups and graphs in a previous paper by the authors together with T. W. Tucker. | Y32: OpenAlex | Z32: https://www.combinatorics.org/ojs/index.php/eljc/article/download/v21i3p40/pdf | AA32: Open-access PDF (via OpenAlex) | AB32: diamond | AC32: School of Technology & Design | AD32: 3 | AE32: No
A33: ARCH-0038 | B33: Smith | C33: Shelley | D33: Shelley Smith | E33: Professor | F33: NYC College of Technology | G33: Architectural Technology | H33: SSmith@citytech.cuny.edu | I33: Journal article | J33: Infinite motion and 2-distinguishability of graphs and groups | K33: 2014 | L33: Journal of Algebraic Combinatorics | M33: Wilfried Imrich; Simon M. Smith; Thomas W. Tucker; Mark E. Watkins | Q33: 10.1007/s10801-014-0529-2 | R33: https://doi.org/10.1007/s10801-014-0529-2 | S33: OpenAlex | T33: 1 | U33: High (City Tech affiliation on paper) | X33: A group A acting faithfully on a set X is 2-distinguishable if there is a 2-coloring of X that is not preserved by any nonidentity element of A, equivalently, if there is a proper subset of X with trivial setwise stabilizer. The motion of an element a in A is the number of points of X that are moved by a, and the motion of the group A is the minimal motion of its nonidentity elements. For finite A, the Motion Lemma says that if the motion of A is large enough (specifically at least 2 log_2 |A|), then the action is 2-distinguishable. For many situations where X has a combinatorial or algebraic structure, the Motion Lemma implies the action of Aut(X) on X is 2-distinguishable in all but finitely many instances. We prove an infinitary version of the Motion Lemma for countably infinite permutation groups, which states that infinite motion is large enough to guarantee 2-distinguishability. From this we deduce a number of results, including the fact that every locally finite, connected graph whose automorphism group is countably infinite is 2-distinguishable. One cannot extend the Motion Lemma to uncountable permutation groups, but nonetheless we prove that 2-distinguishable permutation groups with infinite motion are dense in the class of groups with infinite motion. We conjecture an extension of the Motion Lemma which we expect holds for a restricted class of uncountable permutation groups, and we conclude with a list of open questions. The consequences of our results are drawn for orbit equivalence of infinite permutation groups. | Y33: OpenAlex | Z33: https://link.springer.com/content/pdf/10.1007%2Fs10801-014-0529-2.pdf | AA33: Open-access PDF (via OpenAlex) | AB33: bronze | AC33: School of Technology & Design | AD33: 24 | AE33: No
A34: ARCH-0039 | B34: Chin | C34: Ting | D34: Ting Chin | E34: Chair | F34: NYC College of Technology | G34: Architectural Technology | H34: TChin@citytech.cuny.edu | I34: Paper (venue type unclear) | J34: TECHNE Issue 01 | K34: 2014 | L34: TECHNE | M34: Ting Chin; Jason Montgomery | R34: https://openalex.org/W2916146426 | S34: OpenAlex; CUNY Academic Works | T34: 2 | U34: High (City Tech affiliation on paper); 2 sources | X34: The first issue of TECHNE, an annual publication of student work from the Department of Architecture at the New York City College of Technology. Edited by faculty members Ting Chin and Jason Montgomery, this issue includes contributions from Dean Kevin Hom, Shelley E. Smith, Ting Chin, Michael Duddy, Wendel Edwards, Claudia Hernandez-Feiks, Tim Maldonado, Harold Morales, Anthony Clemente, Patricia Paredes, Gareth Enahoro, Janil Castillo, Lia Dikigoropoulou, Andrea Garrido, Mario Alulema, Tasnuva Ahmed, Jasmine Cato, Marco Dwyer, Elvis Williams, Jean Louis Steevenson, James Rigley, Laura Calle, Moshin Alam, Carlos Mo Wu, Alondra Ramos, Tomasz Piasecki, Ekaterina Sanko, Diego Vega, Tim Maldonado, Alexander Aptekar, Jason Montgomery, Sergio Zapata, Daniel Otto, Michelle Matthews, Aaron Hollander, Shenier Torres, Nataly Bautista, Keith Alfaro, Vladislav Valentinov, Farhana Rahman, Brendan Sigvardsson Cooney, Paul King, Joseph Vidich, Patrick Delorey, Charles Walker, Omar Teles, Ariel Ortiz, Yael Malaev, Khadeeja Din, Chantal Manning, Brian Lall, Loyra Nunez, Eric Ramirez, Esteban Beita, Margarita Salas, William Valdez, Amira Joelson, Agustin Maldonado, Vesselin Milev, Raymond Jimenez, Danny Mieles, Vlad Dunda, Vera Orlova, Sauda Belkaus, Charles Able, Severino Alfonso, Zachary Downey, Anne Leonhardt, Anatoly Plotkin, Kwong Liu, Maksim Drapey, Maciej Stelmach, Ariel Mejia, Andriy Boychuk, Rafael Aquino,Mahshid Kandi, Kento Kawai, Evgenia Melnikova, Irina Nechaeva, Trung Nguyen, Jonathan Rincon, Rawle Smith, and Erick Ramirez. Table of Contents INTRODUCTIONS A Word From The Dean: Kevin Hom, Dean of the School of Technology and Design Introducing The Department: Shelley E. Smith, Associate Professor, Chair of the Department of Architectural Technology TECHNÄ: Ting Chin, Assistant Professor REFLECTIONS Anticipation: Michael Duddy, Assistant Professor What is Architecture?: Lia Dikigoropoulou, Assistant Professor Experiencing Architecture: Andrea Garrido An Architectural Pilgrimage: France Mario Alulema A Change of Heart: Tasnuva Ahmed Remembering Prof. Berensmann: Tim Maldonado, Professor PEDAGOGIES Teaching Architecture: Alexander Aptekar, Assistant Professor; Wendel Edwards, Associate Professor; Claudia Hernandez, Substitute Professor; Paul King, Associate Professor; Tim Maldonado, Professor PERSPECTIVES Learning Architecture: Janil Castillo, Anthony Clemente, Gareth Enahoro, Harold Morales, Patricia Paredes VISUAL STUDIES + FOUNDATIONS DESIGN SEQUENCE Process+ Workflow in Architectural Education: Jason Montgomery, Assistant Professor | Y34: CUNY Academic Works | Z34: https://academicworks.cuny.edu/context/ny_techne/article/1000/viewcontent/TECHNE_2014_CUNY2.pdf | AA34: Not found | AB34: closed | AC34: School of Technology & Design | AD34: 0 | AE34: No
A35: ARCH-0040 | B35: Vaidya | C35: Sanjive | D35: Sanjive Vaidya | E35: Associate Professor | F35: NYC College of Technology | G35: Architectural Technology | H35: SVaidya@citytech.cuny.edu | I35: Grant | J35: 2015 Intersections Symposium Organizer: Digital Intelligence: Conversations on Sensing and Simulation | K35: 2015 | S35: Dept bio | T35: 1 | U35: Medium (self-reported in faculty bio) | W35: 2015 Intersections Symposium Organizer: Digital Intelligence: Conversations on Sensing and Simulation | AC35: School of Technology & Design | AE35: No
A36: ARCH-0041 | B36: Smith | C36: Shelley | D36: Shelley Smith | E36: Professor | F36: NYC College of Technology | G36: Architectural Technology | H36: SSmith@citytech.cuny.edu | I36: Journal article | J36: A classification of primitive permutation groups with finite stabilizers | K36: 2015 | L36: Journal of Algebra | M36: Simon M. Smith | Q36: 10.1016/j.jalgebra.2015.01.023 | R36: https://doi.org/10.1016/j.jalgebra.2015.01.023 | S36: OpenAlex | T36: 1 | U36: High (City Tech affiliation on paper) | Z36: https://www.sciencedirect.com/science/article/pii/S0021869315000629/pdf | AA36: Open-access PDF (via OpenAlex) | AB36: bronze | AC36: School of Technology & Design | AD36: 8 | AE36: No
A37: ARCH-0042 | B37: Smith | C37: Shelley | D37: Shelley Smith | E37: Professor | F37: NYC College of Technology | G37: Architectural Technology | H37: SSmith@citytech.cuny.edu | I37: Journal article | J37: Cary Carson and Carl Lounsbury, eds. The Chesapeake House: Architectural Investigations by Colonial Williamsburg. Chapel Hill: University of North Carolina Press, 2013. xi+488 pp.; 150 color plates and 200 halftones, notes, contributors, index. $60.00. | K37: 2015 | L37: Winterthur Portfolio | M37: Shelley E. Smith | Q37: 10.1086/680459 | R37: https://doi.org/10.1086/680459 | S37: OpenAlex | T37: 1 | U37: High (City Tech affiliation on paper) | AA37: Not found | AB37: closed | AC37: School of Technology & Design | AD37: 0 | AE37: No
A38: ARCH-0045 | B38: Bouratoglou | C38: Jill | D38: Jill Bouratoglou | E38: Associate Professor | F38: NYC College of Technology | G38: Architectural Technology | H38: JBouratoglou@citytech.cuny.edu | I38: Journal article | J38: Global Interaction into the Traditional Design Studios through Blogs | K38: 2015 | L38: Athens Journal of Architecture | M38: Jill Bouratoglou; Lia Dikigoropoulou | Q38: 10.30958/aja.1-2-4 | R38: https://doi.org/10.30958/aja.1-2-4 | S38: OpenAlex | T38: 1 | U38: High (City Tech affiliation on paper) | X38:  Provide students with new and unique | Y38: OpenAlex | Z38: https://doi.org/10.30958/aja.1-2-4 | AA38: Open-access PDF (via OpenAlex) | AB38: diamond | AC38: School of Technology & Design | AD38: 1 | AE38: No
A39: ARCH-0046 | B39: Dikigoropoulou | C39: Lia | D39: Lia Dikigoropoulou | E39: Associate Professor | F39: NYC College of Technology | G39: Architectural Technology | H39: LDikigoropoulou@citytech.cuny.edu | I39: Journal article | J39: Global Interaction into the Traditional Design Studios through Blogs | K39: 2015 | L39: Athens Journal of Architecture | M39: Jill Bouratoglou; Lia Dikigoropoulou | Q39: 10.30958/aja.1-2-4 | R39: https://doi.org/10.30958/aja.1-2-4 | S39: OpenAlex | T39: 1 | U39: High (City Tech affiliation on paper) | X39:  Provide students with new and unique | Y39: OpenAlex | Z39: https://doi.org/10.30958/aja.1-2-4 | AA39: Open-access PDF (via OpenAlex) | AB39: diamond | AC39: School of Technology & Design | AD39: 1 | AE39: No
A40: ARCH-0049 | B40: Dikigoropoulou | C40: Lia | D40: Lia Dikigoropoulou | E40: Associate Professor | F40: NYC College of Technology | G40: Architectural Technology | H40: LDikigoropoulou@citytech.cuny.edu | I40: Conference paper | J40: Study Abroad - Belize - Architectural Technology Students Design and Build | K40: 2015 | L40: CUNY Academic Works (City University of New York) | M40: Lia Dikigoropoulou | R40: https://openalex.org/W2618761520 | S40: OpenAlex; CUNY Academic Works | T40: 2 | U40: High (City Tech affiliation on paper); 2 sources | Z40: https://academicworks.cuny.edu/context/ufs_conf/article/1002/viewcontent/Global_Ed_Conf_Poster_DIKIGOROPOULOU_Belize.pdf | AA40: Not found | AB40: closed | AC40: School of Technology & Design | AD40: 0 | AE40: No
A41: ARCH-0050 | B41: Chin | C41: Ting | D41: Ting Chin | E41: Chair | F41: NYC College of Technology | G41: Architectural Technology | H41: TChin@citytech.cuny.edu | I41: Paper (venue type unclear) | J41: TECHNE Issue 02 | K41: 2015 | L41: TECHNE | M41: Chin, Ting; Duddy, Michael; Montgomery, Jason | R41: https://academicworks.cuny.edu/ny_techne/2 | S41: CUNY Academic Works | T41: 1 | U41: High (in CUNY Academic Works) | X41: The second issue of TECHNE, an annual publication of student work from the Department of Architecture at the New York City College of Technology. Edited by faculty members Ting Chin, Michael Duddy, and Jason Montgomery, this issue includes contributions from Danny Batista, Jason Sai Hung, Heidi Cherubin, Michelle Yang, Laura Calle, Carlos Jacome, Carolina Walters, Hito Rodriguez, Carlin Baez, Brendan Sigvardsson Cooney, Mimu Sakuma, Anton Sukaj, Marie Baretsky, Tatiana Zheludkova, Moises Reyes, Brendan Edwards, Desiree Andrade, Felipe Arellano, Shadeen Dixon, Tam Huiying, Melissa Benitez, Carlos Jacome, Kilton Shehu, Daniel Mego, Marie Baretsky, Jin Chen, Heraldi Sadmojo, Luiza De Souza, Kate Sanko, Bertol Dragani, Charles Happel, Rithol Clytus, Maria Genao, Bertoli Dragani, Jason Ng, Michelle Matthews, Anastasiia Shaiukova, Enny Filpo, Vladislav Valentinov, Raymond Jimenez, Catherine Brito, Andrea Garrido, Genaro Cobar, Batista Rodriguez, and Nicole Ordonez. Table of Contents: INTRODUCTIONS Introduction Ting Chin, Assistant Professor--p. 7 Abstraction and Architecture Jason Montgomery, Assistant Professor--p. 801 DIAGRAMMING--p. 16 02 ITERATION--p. 30 03 MODELING/ MASSING--p. 42 04 REPRESENTATION--p. 54 05 DESIGN CONCEPT--p. 98 06 THE CITY--p. 124On the Abstract and the Real in the Urban Architecture Design Studio Amira Joelson, Associate Adjunct Professor--p. 128 Reflection on the City and Urban Design Bertol Dragani, Third Year Student--p. 131 07 DIGITAL DESIGN--p. 152 | Y41: CUNY Academic Works | Z41: https://academicworks.cuny.edu/context/ny_techne/article/1001/viewcontent/TECHNE_2015_CUNY.pdf | AA41: PDF in CUNY Academic Works | AC41: School of Technology & Design | AE41: No
A42: ARCH-0051 | B42: Duddy | C42: Michael | D42: Michael Duddy | E42: Associate Professor | F42: NYC College of Technology | G42: Architectural Technology | H42: MDuddy@citytech.cuny.edu | I42: Paper (venue type unclear) | J42: TECHNE Issue 02 | K42: 2015 | L42: TECHNE | M42: Chin, Ting; Duddy, Michael; Montgomery, Jason | R42: https://academicworks.cuny.edu/ny_techne/2 | S42: CUNY Academic Works | T42: 1 | U42: High (in CUNY Academic Works) | X42: The second issue of TECHNE, an annual publication of student work from the Department of Architecture at the New York City College of Technology. Edited by faculty members Ting Chin, Michael Duddy, and Jason Montgomery, this issue includes contributions from Danny Batista, Jason Sai Hung, Heidi Cherubin, Michelle Yang, Laura Calle, Carlos Jacome, Carolina Walters, Hito Rodriguez, Carlin Baez, Brendan Sigvardsson Cooney, Mimu Sakuma, Anton Sukaj, Marie Baretsky, Tatiana Zheludkova, Moises Reyes, Brendan Edwards, Desiree Andrade, Felipe Arellano, Shadeen Dixon, Tam Huiying, Melissa Benitez, Carlos Jacome, Kilton Shehu, Daniel Mego, Marie Baretsky, Jin Chen, Heraldi Sadmojo, Luiza De Souza, Kate Sanko, Bertol Dragani, Charles Happel, Rithol Clytus, Maria Genao, Bertoli Dragani, Jason Ng, Michelle Matthews, Anastasiia Shaiukova, Enny Filpo, Vladislav Valentinov, Raymond Jimenez, Catherine Brito, Andrea Garrido, Genaro Cobar, Batista Rodriguez, and Nicole Ordonez. Table of Contents: INTRODUCTIONS Introduction Ting Chin, Assistant Professor--p. 7 Abstraction and Architecture Jason Montgomery, Assistant Professor--p. 801 DIAGRAMMING--p. 16 02 ITERATION--p. 30 03 MODELING/ MASSING--p. 42 04 REPRESENTATION--p. 54 05 DESIGN CONCEPT--p. 98 06 THE CITY--p. 124On the Abstract and the Real in the Urban Architecture Design Studio Amira Joelson, Associate Adjunct Professor--p. 128 Reflection on the City and Urban Design Bertol Dragani, Third Year Student--p. 131 07 DIGITAL DESIGN--p. 152 | Y42: CUNY Academic Works | Z42: https://academicworks.cuny.edu/context/ny_techne/article/1001/viewcontent/TECHNE_2015_CUNY.pdf | AA42: PDF in CUNY Academic Works | AC42: School of Technology & Design | AE42: No
A43: ARCH-0053 | B43: Chin | C43: Ting | D43: Ting Chin | E43: Chair | F43: NYC College of Technology | G43: Architectural Technology | H43: TChin@citytech.cuny.edu | I43: Paper (venue type unclear) | J43: ANALOG:DIGITAL, The Digital Spine: A 1 x 1 Strategy for Integrating Digital Tools in Foundation Design Studios | K43: 2016 | L43: Publications and Research | M43: Claudia E Hernandez Feiks; Ting Chin | R43: https://openalex.org/W2619788226 | S43: OpenAlex; CUNY Academic Works | T43: 2 | U43: High (City Tech affiliation on paper); 2 sources | X43: Architectural education today needs to foster the inherent conceptual and creative thought processes the profession demands but also knowledge of all of the tools that allow architects to create and produce their work. Over the last 25 years the number of digital tools used in the practice of architecture has increased exponentially. Incorporating these digital tools, together with analog ones still being taught in most undergraduate programs today, is overstretching already overloaded architectural curricula. This leaves us to consider how we maintain the quality of teaching as the quantity of content increases and the amount of time with students remains the same. Additionally the inclusion of these tools has not only impacted the content of curricula but has also propelled us to reexamine the classroom environment and transform the way we teach and communicate with students. | Y43: CUNY Academic Works | Z43: https://academicworks.cuny.edu/context/ny_pubs/article/1144/viewcontent/Analog_digital.pdf | AA43: Not found | AB43: closed | AC43: School of Technology & Design | AD43: 0 | AE43: No
A44: ARCH-0054 | B44: Hernandez-Feiks | C44: Claudia | D44: Claudia Hernandez-Feiks | E44: Associate Professor/B.Arch Co-director | F44: NYC College of Technology | G44: Architectural Technology | H44: CHernandez@citytech.cuny.edu | I44: Paper (venue type unclear) | J44: ANALOG:DIGITAL, The Digital Spine: A 1 x 1 Strategy for Integrating Digital Tools in Foundation Design Studios | K44: 2016 | L44: Publications and Research | M44: Claudia E Hernandez Feiks; Ting Chin | R44: https://openalex.org/W2619788226 | S44: OpenAlex; CUNY Academic Works | T44: 2 | U44: High (City Tech affiliation on paper); 2 sources | X44: Architectural education today needs to foster the inherent conceptual and creative thought processes the profession demands but also knowledge of all of the tools that allow architects to create and produce their work. Over the last 25 years the number of digital tools used in the practice of architecture has increased exponentially. Incorporating these digital tools, together with analog ones still being taught in most undergraduate programs today, is overstretching already overloaded architectural curricula. This leaves us to consider how we maintain the quality of teaching as the quantity of content increases and the amount of time with students remains the same. Additionally the inclusion of these tools has not only impacted the content of curricula but has also propelled us to reexamine the classroom environment and transform the way we teach and communicate with students. | Y44: CUNY Academic Works | Z44: https://academicworks.cuny.edu/context/ny_pubs/article/1144/viewcontent/Analog_digital.pdf | AA44: Not found | AB44: closed | AC44: School of Technology & Design | AD44: 0 | AE44: No
A45: ARCH-0059 | B45: Anzalone | C45: Phillip | D45: Phillip Anzalone | E45: Associate Professor | F45: NYC College of Technology | G45: Architectural Technology | H45: PAnzalone@citytech.cuny.edu | I45: Journal article | J45: Locating Architectural Production | K45: 2016 | L45: Publications and Research | M45: Anzalone, Phillip; Bayard, Stephanie | R45: https://academicworks.cuny.edu/ny_pubs/974 | S45: CUNY Academic Works | T45: 1 | U45: High (in CUNY Academic Works) | Z45: https://academicworks.cuny.edu/context/ny_pubs/article/2002/viewcontent/ACSA.AM.104.11.pdf | AA45: PDF in CUNY Academic Works | AC45: School of Technology & Design | AE45: No
A46: ARCH-0065 | B46: Chin | C46: Ting | D46: Ting Chin | E46: Chair | F46: NYC College of Technology | G46: Architectural Technology | H46: TChin@citytech.cuny.edu | I46: Paper (venue type unclear) | J46: TECHNE Issue 03 | K46: 2016 | L46: TECHNE | M46: Ting Chin; Michael C. Duddy; Jason Montgomery | R46: https://openalex.org/W2596382232 | S46: OpenAlex; CUNY Academic Works | T46: 2 | U46: High (City Tech affiliation on paper); 2 sources | X46: The third issue of TECHNE, an annual publication of student work from the Department of Architecture at the New York City College of Technology. Edited by faculty members Ting Chin, Michael Duddy, and Jason Montgomery, this issue includes contributions from Ramsey Dabby, Ramis Rawnak, Ken Grace, Carlos Villella, Shi Long Yang, Percia Gomez, Jill Bouratoglou, Lia Dikigoropoulou, Francisco Morales, Farhana Rahman, Jianfeng Yao, Ana Perez, Peter Zaharatos, Jenne Li, Janil Castillo, Glenny Desena, Elizabeth Parks, Eileen Gray, Mohamed Yakoob, Mario Estrada, Isaias Garcia, Erjan Kadrakunov, Farhana Rahmancenter, Alfonso Severino, Loukia Tsafoulia, Mimu Sakuma, Asli N. Oney, Tatiana Zh, Esteban Beita, Tim Maldonado, Sittha Siriprakaisak, Diana Basily, Enny Filpo, Brigitta H. Purnamasari, Alina De Jesus, Ori Dona, Hadiza Djibring, Horacio Moller, Yuhui Ouyang, Manu Shukurzoda, Kris Alcaide, Norma Chiicaiza, Popi Bequm, Diego Ortega, Jason Ng, Walkiria Cabrera, Eliza Barragan, Jennifer Valerio, Joshua Mendieta, Pablo Zuluaga Morelo, Hamal Hashem, Pak hui, Adis Saracevic, Christian Plaza, Mohammad Alsharif, Maksim Drapey, Sher Boota, Noemi Rovirosa, Richida Lankoande, Claudia Hernandez, Melissa Benitez, Alan Xicohtencatl, Lee-Anne Valdez, Areli Amado, Patryk Michaluk, Marcos Villa, Emani Ennover, Alodra Peralata, Victor Centeno, and Naryomi-Storm Porter. Table of Contents: INTRODUCTION TING CHIN, MICHAEL DUDDY, JASON MONTGOMERY p. 4-5 THOUGHTS ON âPROCESSâ RAMSEY DABBY p. 6-7 NOTES ON THE CONCEPTUALIZING PROCESS IN ARCHITECTURE KEN GRACE p. 8-17 ADVANCED DESIGN METHODOLOGY JILL BOURATOGLOU, LIA DIKIGOROPOULOU p. 18-25 THE PROCESS OF MAKING ELIZABETH PARKS p. 26-29 PROCâ¢ESS ALFONSO SEVERINO, LOUKIA TSAFOULIA p. 30-37 URBAN DESIGN STUDIO: THE DESIGN PROCESS TIM MALDONADO, ESTEBAN BEITA p. 38-47 MAKING CITIES MICHAEL DUDDY, JASON MONTGOMERY p. 48-67 ANALOG:DIGITAL TING CHIN, CLAUDIA HERNANDEZ p. 68-83 | Y46: CUNY Academic Works | Z46: https://academicworks.cuny.edu/context/ny_techne/article/1002/viewcontent/TECHNE_2016_CUNY.pdf | AA46: Not found | AB46: closed | AC46: School of Technology & Design | AD46: 0 | AE46: No
A47: ARCH-0066 | B47: Duddy | C47: Michael | D47: Michael Duddy | E47: Associate Professor | F47: NYC College of Technology | G47: Architectural Technology | H47: MDuddy@citytech.cuny.edu | I47: Paper (venue type unclear) | J47: TECHNE Issue 03 | K47: 2016 | L47: TECHNE | M47: Ting Chin; Michael C. Duddy; Jason Montgomery | R47: https://openalex.org/W2596382232 | S47: OpenAlex; CUNY Academic Works | T47: 2 | U47: High (City Tech affiliation on paper); 2 sources | X47: The third issue of TECHNE, an annual publication of student work from the Department of Architecture at the New York City College of Technology. Edited by faculty members Ting Chin, Michael Duddy, and Jason Montgomery, this issue includes contributions from Ramsey Dabby, Ramis Rawnak, Ken Grace, Carlos Villella, Shi Long Yang, Percia Gomez, Jill Bouratoglou, Lia Dikigoropoulou, Francisco Morales, Farhana Rahman, Jianfeng Yao, Ana Perez, Peter Zaharatos, Jenne Li, Janil Castillo, Glenny Desena, Elizabeth Parks, Eileen Gray, Mohamed Yakoob, Mario Estrada, Isaias Garcia, Erjan Kadrakunov, Farhana Rahmancenter, Alfonso Severino, Loukia Tsafoulia, Mimu Sakuma, Asli N. Oney, Tatiana Zh, Esteban Beita, Tim Maldonado, Sittha Siriprakaisak, Diana Basily, Enny Filpo, Brigitta H. Purnamasari, Alina De Jesus, Ori Dona, Hadiza Djibring, Horacio Moller, Yuhui Ouyang, Manu Shukurzoda, Kris Alcaide, Norma Chiicaiza, Popi Bequm, Diego Ortega, Jason Ng, Walkiria Cabrera, Eliza Barragan, Jennifer Valerio, Joshua Mendieta, Pablo Zuluaga Morelo, Hamal Hashem, Pak hui, Adis Saracevic, Christian Plaza, Mohammad Alsharif, Maksim Drapey, Sher Boota, Noemi Rovirosa, Richida Lankoande, Claudia Hernandez, Melissa Benitez, Alan Xicohtencatl, Lee-Anne Valdez, Areli Amado, Patryk Michaluk, Marcos Villa, Emani Ennover, Alodra Peralata, Victor Centeno, and Naryomi-Storm Porter. Table of Contents: INTRODUCTION TING CHIN, MICHAEL DUDDY, JASON MONTGOMERY p. 4-5 THOUGHTS ON âPROCESSâ RAMSEY DABBY p. 6-7 NOTES ON THE CONCEPTUALIZING PROCESS IN ARCHITECTURE KEN GRACE p. 8-17 ADVANCED DESIGN METHODOLOGY JILL BOURATOGLOU, LIA DIKIGOROPOULOU p. 18-25 THE PROCESS OF MAKING ELIZABETH PARKS p. 26-29 PROCâ¢ESS ALFONSO SEVERINO, LOUKIA TSAFOULIA p. 30-37 URBAN DESIGN STUDIO: THE DESIGN PROCESS TIM MALDONADO, ESTEBAN BEITA p. 38-47 MAKING CITIES MICHAEL DUDDY, JASON MONTGOMERY p. 48-67 ANALOG:DIGITAL TING CHIN, CLAUDIA HERNANDEZ p. 68-83 | Y47: CUNY Academic Works | Z47: https://academicworks.cuny.edu/context/ny_techne/article/1002/viewcontent/TECHNE_2016_CUNY.pdf | AA47: Not found | AB47: closed | AC47: School of Technology & Design | AD47: 0 | AE47: No
A48: ARCH-0067 | B48: Vaidya | C48: Sanjive | D48: Sanjive Vaidya | E48: Associate Professor | F48: NYC College of Technology | G48: Architectural Technology | H48: SVaidya@citytech.cuny.edu | I48: Grant | J48: 2017 WDI Grant Sponsor/Advisor: Pathways to Leadership for Women in Design and Construction | K48: 2017 | S48: Dept bio | T48: 1 | U48: Medium (self-reported in faculty bio) | W48: 2017 WDI Grant Sponsor/Advisor: Pathways to Leadership for Women in Design and Construction | AC48: School of Technology & Design | AE48: No
A49: ARCH-0070 | B49: Duddy | C49: Michael | D49: Michael Duddy | E49: Associate Professor | F49: NYC College of Technology | G49: Architectural Technology | H49: MDuddy@citytech.cuny.edu | I49: Open educational resource | J49: Introduction to Architecture, ARCH 1101, Course Outline | K49: 2017 | L49: Open Educational Resources | M49: Duddy, Michael | R49: https://academicworks.cuny.edu/ny_oers/58 | S49: CUNY Academic Works | T49: 1 | U49: High (in CUNY Academic Works) | X49: The Introduction to Architecture provides a foundation for students entering the BArch / BTech program to develop a âvisual literacyâ of the built environment. Using New York City as a living laboratory, students explore concepts of design, composition, and construction in the context of the city through their direct experience of buildings. By practicing the basic skills of drafting, sketching, and reading about buildings, and with the opportunity to present their understandings to others through written assignments and verbal presentations, students will develop methods of representing and presenting architecture verbally and graphically. | Y49: CUNY Academic Works | Z49: https://academicworks.cuny.edu/context/ny_oers/article/1070/viewcontent/auto_convert.pdf | AA49: PDF in CUNY Academic Works | AC49: School of Technology & Design | AE49: No
A50: ARCH-0072 | B50: Anzalone | C50: Phillip | D50: Phillip Anzalone | E50: Associate Professor | F50: NYC College of Technology | G50: Architectural Technology | H50: PAnzalone@citytech.cuny.edu | I50: Conference paper | J50: Rapidly Deployed and Assembled Tensegrity System: An Augmented Design Approach | K50: 2017 | L50: ACADIA quarterly | M50: Phillip Anzalone; Stephanie Bayard; Ralph Spencer Steenblik | Q50: 10.52842/conf.acadia.2017.092 | R50: https://doi.org/10.52842/conf.acadia.2017.092 | S50: OpenAlex; CUNY Academic Works | T50: 2 | U50: High (City Tech affiliation on paper); 2 sources | X50: The Rapidly Deployable and Assembled Tensegrity (RDAT) project enables the efficient automated design and deployment of differential-geometry tensegrity structures through computation-driven design-to-installation workflow. RDAT employs the integration of parametric and solid-modeling methods with production by streamlining computer numerically controlled manufacturing through novel detailing and production techniques to develop an efficient manufacturing and assembly system. The RDAT project emerges from the Authors' research in academia and professional practice focusing on computationally produced full-scale performative building systems and their innovative uses in the building and construction industry. | Y50: OpenAlex | Z50: https://academicworks.cuny.edu/ny_pubs/690 | AA50: Open-access PDF (via OpenAlex) | AB50: green | AC50: School of Technology & Design | AD50: 3 | AE50: No
A51: ARCH-0073 | B51: Chin | C51: Ting | D51: Ting Chin | E51: Chair | F51: NYC College of Technology | G51: Architectural Technology | H51: TChin@citytech.cuny.edu | I51: Paper (venue type unclear) | J51: TECHNE Issue 04 | K51: 2017 | L51: TECHNE | M51: Ting Chin; Michael C. Duddy; Jason Montgomery | R51: https://openalex.org/W2915673810 | S51: OpenAlex; CUNY Academic Works | T51: 2 | U51: High (City Tech affiliation on paper); 2 sources | X51: Introduction: Etymologically the word architect is derived from the Greek word arkhitekton meaning âchief builderâ (arkhi-, chief + tekton, builder). Originally, architects were primarily builders or artisans. Since that time architects have moved increasingly further away from the act of building. However, recent technological advances in such fields as digital fabrication, custom prototyping, and materials science are drawing architects back to the craft of making. This issue of TECHNE focuses on the relevance of building, making, and fabricating in architectural pedagogy and practice, and presents essays, conceptual proposals, and projects that address this topic. We consider why it is important to provide students with opportunities to engage in building and making and reflect on what students gain from these experiences. What are the lessons learned from student projects that have embraced a design:build approach? How can we provide more of these opportunities to students? This issue features the extraordinary work of our students and faculty on the Solar Decathlon. The project exemplifies the epitome of a hands-on experiential learning opportunity in designing to build. It is through projects like this that students are afforded the opportunity to learn soft skills, such as communicating, collaborating, scheduling, and managing, together with hard skills such as drawing construction details and using tools on a job site. Both students and faculty discover that, unlike in a traditional classroom, each learn more than they could have expected. We also discuss the impact new digital fabrication tools have on the way we conceive, practice, and, most importantly, teach architecture. With the onset of these tools, architecture is being conceived differently both in its conceptual approach and its multitude of possible job descriptions. These tools have enabled students and practitioners to engage more directly with the act of expeditiously making and have inspired projects that are seemingly less constrained by the confines of a traditional architecture practice. These explorations and inspirations expand the field of architecture, and what it makes, and exponentially increases the number of potential trajectories that we can embark upon. Are these tools and processes redefining the role of an architect? Should we use what we learn from these contemporary processes to inform traditional practices and pedagogies or are they something entirely new? Student contributions: Ashley Amador, Rosemarie Castillo, Darwin Diaz, Meilledjine Francois, Percia Gomez, Asli Oney, Ana Perez, Carolina Rianchos, Steven Zimmerman Table of contents:Introduction: Ting Chin, Michael Duddy, Jason Montgomery p. 1Precise | Concise: Sanjive Vaidya p. 3Iris Pavilion: Mentor: Professor Joseph Vidich Assistants: Michael DiCarlo & Anner More Students: Shadeen Dixon Allon Morgan Heraldi Sadmojo Mimu Sakuma Claudia Tupayachi p. 5ARCH4890 Computation & Fabrication: Professor Hart Marlow p.15 Terra Table: Henry Aguilar p. 33Solar Decathlon: Solar Decathlon Team p. 41Energy Modeling Report: Professor Jihun Kim p. 69Stratusquo: Anner More & Franklin Rojas p. 89Adaptive & Autonomous Tensegrity System: Anner More & Franklin Rojas Student Team: Mimu Sakuma Allon Morgan Heraldi Sadmojo Anastasiia Shaiukova p. 99 Opposite Reactions: Anastasiia Shaiukova p. 105Projecting Architecture in the Digital Era: Professor Severino Alfonso, Students: Espinoza Edinboro Leitch Choudhury p. 111 Design Build Experiences of a Practicing City Tech Faculty Member: Professor Mars Podvorica p. 123 | Y51: CUNY Academic Works | Z51: https://academicworks.cuny.edu/context/ny_techne/article/1003/viewcontent/CUNY_Academic_Works_Spreads.pdf | AA51: Not found | AB51: closed | AC51: School of Technology & Design | AD51: 0 | AE51: No
A52: ARCH-0074 | B52: Duddy | C52: Michael | D52: Michael Duddy | E52: Associate Professor | F52: NYC College of Technology | G52: Architectural Technology | H52: MDuddy@citytech.cuny.edu | I52: Paper (venue type unclear) | J52: TECHNE Issue 04 | K52: 2017 | L52: TECHNE | M52: Ting Chin; Michael C. Duddy; Jason Montgomery | R52: https://openalex.org/W2915673810 | S52: OpenAlex; CUNY Academic Works | T52: 2 | U52: High (City Tech affiliation on paper); 2 sources | X52: Introduction: Etymologically the word architect is derived from the Greek word arkhitekton meaning âchief builderâ (arkhi-, chief + tekton, builder). Originally, architects were primarily builders or artisans. Since that time architects have moved increasingly further away from the act of building. However, recent technological advances in such fields as digital fabrication, custom prototyping, and materials science are drawing architects back to the craft of making. This issue of TECHNE focuses on the relevance of building, making, and fabricating in architectural pedagogy and practice, and presents essays, conceptual proposals, and projects that address this topic. We consider why it is important to provide students with opportunities to engage in building and making and reflect on what students gain from these experiences. What are the lessons learned from student projects that have embraced a design:build approach? How can we provide more of these opportunities to students? This issue features the extraordinary work of our students and faculty on the Solar Decathlon. The project exemplifies the epitome of a hands-on experiential learning opportunity in designing to build. It is through projects like this that students are afforded the opportunity to learn soft skills, such as communicating, collaborating, scheduling, and managing, together with hard skills such as drawing construction details and using tools on a job site. Both students and faculty discover that, unlike in a traditional classroom, each learn more than they could have expected. We also discuss the impact new digital fabrication tools have on the way we conceive, practice, and, most importantly, teach architecture. With the onset of these tools, architecture is being conceived differently both in its conceptual approach and its multitude of possible job descriptions. These tools have enabled students and practitioners to engage more directly with the act of expeditiously making and have inspired projects that are seemingly less constrained by the confines of a traditional architecture practice. These explorations and inspirations expand the field of architecture, and what it makes, and exponentially increases the number of potential trajectories that we can embark upon. Are these tools and processes redefining the role of an architect? Should we use what we learn from these contemporary processes to inform traditional practices and pedagogies or are they something entirely new? Student contributions: Ashley Amador, Rosemarie Castillo, Darwin Diaz, Meilledjine Francois, Percia Gomez, Asli Oney, Ana Perez, Carolina Rianchos, Steven Zimmerman Table of contents:Introduction: Ting Chin, Michael Duddy, Jason Montgomery p. 1Precise | Concise: Sanjive Vaidya p. 3Iris Pavilion: Mentor: Professor Joseph Vidich Assistants: Michael DiCarlo & Anner More Students: Shadeen Dixon Allon Morgan Heraldi Sadmojo Mimu Sakuma Claudia Tupayachi p. 5ARCH4890 Computation & Fabrication: Professor Hart Marlow p.15 Terra Table: Henry Aguilar p. 33Solar Decathlon: Solar Decathlon Team p. 41Energy Modeling Report: Professor Jihun Kim p. 69Stratusquo: Anner More & Franklin Rojas p. 89Adaptive & Autonomous Tensegrity System: Anner More & Franklin Rojas Student Team: Mimu Sakuma Allon Morgan Heraldi Sadmojo Anastasiia Shaiukova p. 99 Opposite Reactions: Anastasiia Shaiukova p. 105Projecting Architecture in the Digital Era: Professor Severino Alfonso, Students: Espinoza Edinboro Leitch Choudhury p. 111 Design Build Experiences of a Practicing City Tech Faculty Member: Professor Mars Podvorica p. 123 | Y52: CUNY Academic Works | Z52: https://academicworks.cuny.edu/context/ny_techne/article/1003/viewcontent/CUNY_Academic_Works_Spreads.pdf | AA52: Not found | AB52: closed | AC52: School of Technology & Design | AD52: 0 | AE52: No
A53: ARCH-0075 | B53: King | C53: Paul | D53: Paul King | E53: Professor | F53: NYC College of Technology | G53: Architectural Technology | H53: PKing@citytech.cuny.edu | I53: Book chapter | J53: The Solar Decathlon: Team DURA and Interdisciplinary Place-Based Learning | K53: 2017 | L53: Springer eBooks | M53: Paul C. King | Q53: 10.1007/978-3-319-66014-1_3 | R53: https://doi.org/10.1007/978-3-319-66014-1_3 | S53: OpenAlex | T53: 1 | U53: High (City Tech affiliation on paper) | AA53: Not found | AB53: closed | AC53: School of Technology & Design | AD53: 1 | AE53: No
A54: ARCH-0076 | B54: Kim | C54: Jihun | D54: Jihun Kim | E54: Associate Professor | F54: NYC College of Technology | G54: Architectural Technology | H54: JKim@citytech.cuny.edu | I54: Journal article | J54: Topography integration to wind downscaling | K54: 2017 | L54: Building and Environment | M54: Jihun Kim; Yun Kyu Yi; Ali M Malkawi | Q54: 10.1016/j.buildenv.2017.01.024 | R54: https://doi.org/10.1016/j.buildenv.2017.01.024 | S54: OpenAlex | T54: 1 | U54: High (City Tech affiliation on paper) | AA54: Not found | AB54: closed | AC54: School of Technology & Design | AD54: 9 | AE54: No
A55: ARCH-0077 | B55: Aptekar | C55: Alexander | D55: Alexander Aptekar | E55: Assistant Professor | F55: NYC College of Technology | G55: Architectural Technology | H55: AAptekar@citytech.cuny.edu | I55: Technical report | J55: UNL | K55: 2017 | M55: A. Aptekar; USDOE Office of Energy Efficiency and Renewable Energy (EERE) | Q55: 10.2172/1347232 | R55: https://doi.org/10.2172/1347232 | S55: OpenAlex | T55: 1 | U55: High (City Tech affiliation on paper) | X55: The final report on New York City College of Technology (City Tech) DURA (Diverse | Urban | Resilient | Adaptable) home project. City Tech has participated in the Solar Decathlon 2015 project as DURA. The DURA team consists of students, faculty, volunteers, Service Corps participants, Industry advisers, recent graduates and others. The DURA team researched, designed, and constructed a zero energy prototype house. This process was a valuable opportunity for City Tech as a project of such scale has not been completed before with the integration of so many departments and their students. | Y55: OpenAlex | Z55: https://www.osti.gov/servlets/purl/1347232 | AA55: Open-access PDF (via OpenAlex) | AB55: gold | AC55: School of Technology & Design | AD55: 0 | AE55: No
A56: ARCH-0080 | B56: Anzalone | C56: Phillip | D56: Phillip Anzalone | E56: Associate Professor | F56: NYC College of Technology | G56: Architectural Technology | H56: PAnzalone@citytech.cuny.edu | I56: Paper (venue type unclear) | J56: Imprecision in Materials + Production | K56: 2018 | L56: CUNY Academic Works (City University of New York) | M56: Phillip Anzalone; Marcella Del Signore; Andrew John Wit | R56: https://openalex.org/W3158815684 | S56: OpenAlex; CUNY Academic Works | T56: 2 | U56: High (City Tech affiliation on paper); 2 sources | Z56: https://academicworks.cuny.edu/context/ny_pubs/article/1710/viewcontent/acadia18_242.pdf | AA56: Not found | AB56: closed | AC56: School of Technology & Design | AD56: 5 | AE56: No
A57: ARCH-0082 | B57: Anzalone | C57: Phillip | D57: Phillip Anzalone | E57: Associate Professor | F57: NYC College of Technology | G57: Architectural Technology | H57: PAnzalone@citytech.cuny.edu | I57: Paper (venue type unclear) | J57: Notes on imprecision and infidelity | K57: 2018 | L57: CUNY Academic Works (City University of New York) | M57: Phillip Anzalone; Marcella Del Signore; Andrew John Wit | R57: https://openalex.org/W3181254131 | S57: OpenAlex; CUNY Academic Works | T57: 2 | U57: High (City Tech affiliation on paper); 2 sources | Z57: https://academicworks.cuny.edu/ny_pubs/692 | AA57: Open-access PDF (via OpenAlex) | AB57: green | AC57: School of Technology & Design | AD57: 3 | AE57: No
A58: ARCH-0083 | B58: Aptekar | C58: Alexander | D58: Alexander Aptekar | E58: Assistant Professor | F58: NYC College of Technology | G58: Architectural Technology | H58: AAptekar@citytech.cuny.edu | I58: Conference presentation | J58: Solar & Rain Catching Canopy "Urban Oasis 2" | K58: 2018 | L58: Publications and Research | M58: Ibitoye, Afolabi; Wilmot, Cheriyah; Aptekar, Alexander; Kosieradzki, Grzegorz; Sultanova, Kaiyrgul; Vallon, Jude | R58: https://academicworks.cuny.edu/ny_pubs/335 | S58: CUNY Academic Works | T58: 1 | U58: High (in CUNY Academic Works) | X58: The accumulation of water runoff during rain storms is a major problem in New York Cityâs combination water systems, forcing water treatment plants to release untreated excess water. To avoid overfilling of the sewer system by this grey water, pocket parks and gardens will be used to absorb the excess rainfall. We will be harnessing natureâs resources with current technologies such as: solar panels combined with rain catching canopies, to beautify the environment, educate the public about sustainability, stimulate growth to local businesses through increased foot traffic and bringing social awareness on environmental issues. The canopies are designed to collect the maximum amount of rainwater based on its surface area, maximize solar collection and retention. Our flawless design has analyzed expected rainfall and optimal solar angles for the solar panel placement on the canopy to provide sunshade for benches near existing flower beds or canopy placements, collect rainwater for irrigation, and harness solar radiation. To function as a rain catcher, nonporous tarp and a water pipe will be used to collect water for the planters and supplied into clay pots for osmotic irrigation of plants; while solar panels supplies energy to electrical outlets. Upon completion of the minimal viable product using mostly recycled wood and plywood materials, the density of the canopy shade proved to be top heavy thereby making the overall structure unstable, posing safety concern. To maintain tension at the bottom, the base column can either be bolted to the sides of the planter, ground or immersed in Earth with bolts secured by washers. The new design still use environmentally friendly materials made of canvas and worn on a prefabricated aluminum to maintain conformity and aesthetics of the previous wooden designs; it is lighter in weight, stand-alone and remains adaptive to any structure without pocket parks. | Y58: CUNY Academic Works | Z58: https://academicworks.cuny.edu/context/ny_pubs/article/1350/type/native/viewcontent/ESP_Fall_MMXVIII_Poster_rev.pptx | AA58: PDF in CUNY Academic Works | AC58: School of Technology & Design | AE58: No
A59: ARCH-0084 | B59: Aptekar | C59: Alexander | D59: Alexander Aptekar | E59: Assistant Professor | F59: NYC College of Technology | G59: Architectural Technology | H59: AAptekar@citytech.cuny.edu | I59: Conference presentation | J59: Solar & Rain Catching Canopy "Urban Oasis" 1.1 | K59: 2018 | L59: Publications and Research | M59: Ibitoye, Afolabi; Aptekar, Alexander | R59: https://academicworks.cuny.edu/ny_pubs/342 | S59: CUNY Academic Works | T59: 1 | U59: High (in CUNY Academic Works) | X59: Accumulation of water runoff during rain storms affects New York Cityâs combination water system, forcing water treatment plants to release untreated excess water. Rather than allow this grey water to overfill the sewer system, pocket parks and gardens can be used to absorb rainfall. By harnessing natureâs resources through todayâs technology we can also create solar and rain catching canopies to beautify, educate, and bring growth and social awareness to local businesses. In order to design the canopies to collect the maximum amount of rainwater and maximize solar collection, we analyzed expected rainfall and optimal solar angles. The canopies will provide shade for benches near existing flower beds, collect rainwater for irrigation, and collect solar energy. Rainwater that falls on the canopy will slope into PVC pipes and be distributed to clay pots which will efficiently distribute water, while solar panels will provide energy for public electrical outlets. The inclusion of a solar panel created the need for an energy storage component, especially in the absence of sunlight, which quantitatively measures the harnessed energy, and a solar charge controller for energy regulation to limit the rate at which electric current will be added or drawn from the battery and distribution. Upon completion of the first prototype using mostly wooden and plywood materials, the density of the canopy shade proved to be top heavy thereby making the overall structure singly unstable posing safety concern, this necessitated a proposed material change into aluminum and canvas with lighter weight as a possible standalone and/or adaptive structure to the existing pocket parks. Once refined, these canopies can provide shade, public electrical outlets, and help to mitigate New York Cityâs storm water runoff problem. | Y59: CUNY Academic Works | Z59: https://academicworks.cuny.edu/context/ny_pubs/article/1360/type/native/viewcontent/SummerMMXVIII_Poster.pptx | AA59: PDF in CUNY Academic Works | AC59: School of Technology & Design | AE59: No
A60: ARCH-0085 | B60: Aptekar | C60: Alexander | D60: Alexander Aptekar | E60: Assistant Professor | F60: NYC College of Technology | G60: Architectural Technology | H60: AAptekar@citytech.cuny.edu | I60: Conference presentation | J60: Solar and Rain Catching Canopy. Urban Oasis | K60: 2018 | L60: Publications and Research | M60: Ibitoye, Afolabi; Clark, Langston; Zimareva, Elena; Banks, Evan; Aptekar, Alexander | R60: https://academicworks.cuny.edu/ny_pubs/266 | S60: CUNY Academic Works | T60: 1 | U60: High (in CUNY Academic Works) | X60: The Urban Oasis is designed to work within existing âpocket parksâ in New York City as a combined rainwater collector, personal electronics charging station and resting designation for New Yorkers. Intended to not only lessen the demand on the city power grid by using renewable energy to charge devices, the urban oasis is also intended to mitigate grey water overfill in New Yorkâs combined sewer system and, in general, serve as a model for responsible environmental stewardship in urban areas. The important technical aspects of the canopy specifically analyzed were: a) how much rainwater could the canopy be expected to collect per operating season b) what the optimal solar panel angle based off of New Yorkâs specific geographical location was to maximize solar collection and c) how many full device charges could be expected per operating day. Information was gathered from various local and state organizations. The first prototype is constructed of locally sourced lumber and was assembled by hand using power and hand tools. Based off of historical rainfall data taken from National Oceanic and Atmospheric Administration (NOAA) as well as the design square footage of the canopy, expected total annual rainfall collection was calculated to be 311 gallons. Using sun angle calculations taken from existing solar charts and averaging optimal angles across each month, it was determined that a fixed angle of 60Â° would be optimal for solar collection. Based off of the specs of the specific solar panel being used and using research from existing sources of information on solar panels, the urban oasis is expected to produce 147 watt hours per day (which approximates as about 27 cellular phone charges per day.) The density of the material being used has necessitated design changes to aid in its structural stability. Additionally, New York City specific code is still being researched and experts are being consulted to determine the legal hurdles still to overcome and long term viability of the project existing in a public space. | Y60: CUNY Academic Works | Z60: https://academicworks.cuny.edu/context/ny_pubs/article/1273/type/native/viewcontent/Elena_Zimareva___Solar_and_Rain_Catching_Canopy_editsjvjrev.pptx | AA60: PDF in CUNY Academic Works | AC60: School of Technology & Design | AE60: No
A61: ARCH-0086 | B61: Chin | C61: Ting | D61: Ting Chin | E61: Chair | F61: NYC College of Technology | G61: Architectural Technology | H61: TChin@citytech.cuny.edu | I61: Conference paper | J61: Symbiotic Urbanism: Looking Beyond Sustainability | K61: 2018 | M61: Ting Chin | Q61: 10.35483/acsa.intl.2018.9 | R61: https://doi.org/10.35483/acsa.intl.2018.9 | S61: OpenAlex | T61: 1 | U61: High (City Tech affiliation on paper) | X61: Given the inherent ecological damage associated with post-industrial sites, their remediation offers an opportunity to apply the concept of symbiotic urbanism, a type of urban development that not only prevents ecological degradation, but also restores the natural environment while concurrently benefitting adjacent communities and economies, to their rehabilitation. Analogous to symbiotic urbanism, definitions of regenerative urban development and regenerative cities capture the notion of urban development that goes beyond preventing environmental damage to also encompass the replenishment of natural resources, but few case studies of how the entirety of the idea can be implemented exist. In contrast to commonly referenced examples of regenerative urban development this paper will discuss an application of symbiotic urbanism that offers a proposal for the comprehensive rehabilitation of a post-industrial site. The proposal uses the site’s industrial legacy as inspiration for entering a new era of production that engages in the research and development of innovative technologies that simultaneously remediate existing environmental degradation while stimulating new economies and opportunities and reconnecting communities to long-abandoned places. | Y61: OpenAlex | Z61: https://www.acsa-arch.org/proceedings/International Proceedings/ACSA.Intl.2018/ACSA.Intl.2018.9.pdf | AA61: Open-access PDF (via OpenAlex) | AB61: gold | AC61: School of Technology & Design | AD61: 2 | AE61: No
A62: ARCH-0087 | B62: Chin | C62: Ting | D62: Ting Chin | E62: Chair | F62: NYC College of Technology | G62: Architectural Technology | H62: TChin@citytech.cuny.edu | I62: Paper (venue type unclear) | J62: TECHNE Issue 05 | K62: 2018 | L62: TECHNE | M62: Ting Chin; Michael C. Duddy; Jason Montgomery | R62: https://openalex.org/W2956083882 | S62: OpenAlex; CUNY Academic Works | T62: 2 | U62: High (City Tech affiliation on paper); 2 sources | X62: INTRODUCTION: TING CHIN, MICHAEL DUDDY, AND JASON MONTGOMERY As the Department of Architectural Technology at the New York City College of Technology embarks on its path to achieve accreditation by the National Architecture Accrediting Board (NAAB) for a Bachelor of Architecture, this issue of TECHNE- decidedly focused on architectural education. Over the last two years through countless discussions within our department and college, and with architecture faculty from other universities and currently practicing architects, we have been questioning the value, purpose, and means of an architectural education. As educators in architecture we are responsible for exposing students to a multifaceted profession that can yield many trajectories. With the boundless array of opportunities in the digital realm currently upon us, the number of possible career paths a student can embark on are limitless. Traditionally a design education spans from presenting students with the theoretical foundations of the profession to imparting the practical skills necessary to enter the workforce. With so many new technologies to teach, and a limited amount number of hours in the classroom, how can we most effectively utilize our time with students? Would it be more worthwhile to require internships and a practice-based education, focus on conceptual and theoretical thought processes, or to develop soft skills, such as collaboration, resourcefulness, and problem-solving? For this issue we queried notable practitioners and educators to share what they consider to be fundamental to a design education and how they thought we could better prepare our students to navigate the profession. Contributors spanned from architects working, or who have worked, in world-renowned firms to sole-proprietors, and from educators, simultaneously teaching at many different schools, who are inherently exposed to a variety of educational agendas, to members of our own faculty. Approaches to architectural education and practice ranged from beliefs firmly rooted in history to those that encouraged embarking on new directions. The array of responses demonstrates the many facets of architecture and suggests that we approach the teaching and learning of it by understanding its contextual significance in history while guiding our students to make a mark on its future. TABLE OF CONTENTS INTRODUCTION. TING CHIN, MICHAEL DUDDY, JASON MONTGOMERY. 1 SERVICE > WORK. SANJIVE VAIDYA. 4 21ST CENTURY ARCHITECTURAL EDUCATION. ARIK WILSON. 5 PRACTISE PRACTICE: QUESTIONS OF DESIGN. CHRIS HILLYARD. 9 HOW TO BE HUMAN. JIEUN YANG. 16 THE PRACTICE OF ARCHITECTURE. WAYNE STRIKER. 21 THE UNQUANTIFIABLE VALUE OF STUDY ABROAD. ELISABETH MARTIN. 23 THE 21ST CENTURY INTERN. EDWARD SIEGEL. 27 THOUGHTS ON THE FUTURE OF ARCHITECTURAL EDUCATION. EIRINI TSACHRELIA. 32 THE YOUNG ARCHITECT IâD LIKE TO HAVE SITTING NEXT TO ME. STEPHEN T. CHRISMAN. 35 IN SEARCH OF AN ARCHITECTURAL ASSISTANT. PETER GREENBERG. 37 CURIOUS ALWAYS. TIM MCCARTHY. 41 DATA LITERACY AND PERFORMANCE SIMULATION. JIHUN KIM. 44 URBAN MICROCLIMATE ANALYSIS- EMERGING SCHOLARS. GABRIELA MARTINEZ, YUYING XIAN. 47 DURA. STA CLUB. 49 CONSTRAINTS. SEVERINO ALFONSO. 54 THE MITIGATOR- ARCH 4810. ASLI ONEY. 71 INTERVIEW WITH CLAUDIA HERNANDEZ. JAMAR DINALL. 79 PUBLIC LIBRARY- ARCH 2310. EVELYN RICHARDSON. 85 SCHOOL OF ARCHITECTURE- ARCH 2410. JAMAR DINALL. 89 SCHOOL OF ARCHITECTURE- ARCH2410. IVANA BATISTA. 93 RED HOOK MASTER PLAN- ARCH 4710. ADAM ELKHOULY, MARCELO LEDESMA, JAMES RIGLEY. 97 RED HOOK MASTER PLAN- ARCH 4710. ONICA LEITCH-EDINBORO. 101 BROOKLYN MIXED-USE HIGH RISE- ARCH 4710. SAADIQ ALLI. 103 BROOKLYN HIGH RISE- ARCH 4810. ALLON MORGAN. 107 MULTI-USE COMPLEX AND PARK- ARCH 4710. ALIMERV PROCTOR. 109 MOVEMENT TO SPACE- RED HOOK MASTER PLAN- ARCH 4710. JORGE TLATELPA, EMILY NORTHIA, CHRISTINE NICOLE JAYCO. 113 INTERVIEW WITH WENDELL EDWARDS. STEVEN ZIMMERMAN. 118 INTERVIEW WITH CESAR SALAZAR. DARWIN DIAZ. 123 INTERVIEW WITH TIM MALDONADO. GABRIELA MARTINEZ & YUYING XIAN. 125 STUDENT INTERVIEWS. TING LAU. 129 ALUMNI VOICES. CAITLIN MCMANUS '17. 135 MARSHA-ANN CADOUGAN '13. 136 | Y62: CUNY Academic Works | Z62: https://academicworks.cuny.edu/context/ny_techne/article/1004/viewcontent/TECHNE_ISSU_with_text_recog.pdf | AA62: Not found | AB62: closed | AC62: School of Technology & Design | AD62: 0 | AE62: No
A63: ARCH-0088 | B63: Duddy | C63: Michael | D63: Michael Duddy | E63: Associate Professor | F63: NYC College of Technology | G63: Architectural Technology | H63: MDuddy@citytech.cuny.edu | I63: Paper (venue type unclear) | J63: TECHNE Issue 05 | K63: 2018 | L63: TECHNE | M63: Ting Chin; Michael C. Duddy; Jason Montgomery | R63: https://openalex.org/W2956083882 | S63: OpenAlex; CUNY Academic Works | T63: 2 | U63: High (City Tech affiliation on paper); 2 sources | X63: INTRODUCTION: TING CHIN, MICHAEL DUDDY, AND JASON MONTGOMERY As the Department of Architectural Technology at the New York City College of Technology embarks on its path to achieve accreditation by the National Architecture Accrediting Board (NAAB) for a Bachelor of Architecture, this issue of TECHNE- decidedly focused on architectural education. Over the last two years through countless discussions within our department and college, and with architecture faculty from other universities and currently practicing architects, we have been questioning the value, purpose, and means of an architectural education. As educators in architecture we are responsible for exposing students to a multifaceted profession that can yield many trajectories. With the boundless array of opportunities in the digital realm currently upon us, the number of possible career paths a student can embark on are limitless. Traditionally a design education spans from presenting students with the theoretical foundations of the profession to imparting the practical skills necessary to enter the workforce. With so many new technologies to teach, and a limited amount number of hours in the classroom, how can we most effectively utilize our time with students? Would it be more worthwhile to require internships and a practice-based education, focus on conceptual and theoretical thought processes, or to develop soft skills, such as collaboration, resourcefulness, and problem-solving? For this issue we queried notable practitioners and educators to share what they consider to be fundamental to a design education and how they thought we could better prepare our students to navigate the profession. Contributors spanned from architects working, or who have worked, in world-renowned firms to sole-proprietors, and from educators, simultaneously teaching at many different schools, who are inherently exposed to a variety of educational agendas, to members of our own faculty. Approaches to architectural education and practice ranged from beliefs firmly rooted in history to those that encouraged embarking on new directions. The array of responses demonstrates the many facets of architecture and suggests that we approach the teaching and learning of it by understanding its contextual significance in history while guiding our students to make a mark on its future. TABLE OF CONTENTS INTRODUCTION. TING CHIN, MICHAEL DUDDY, JASON MONTGOMERY. 1 SERVICE > WORK. SANJIVE VAIDYA. 4 21ST CENTURY ARCHITECTURAL EDUCATION. ARIK WILSON. 5 PRACTISE PRACTICE: QUESTIONS OF DESIGN. CHRIS HILLYARD. 9 HOW TO BE HUMAN. JIEUN YANG. 16 THE PRACTICE OF ARCHITECTURE. WAYNE STRIKER. 21 THE UNQUANTIFIABLE VALUE OF STUDY ABROAD. ELISABETH MARTIN. 23 THE 21ST CENTURY INTERN. EDWARD SIEGEL. 27 THOUGHTS ON THE FUTURE OF ARCHITECTURAL EDUCATION. EIRINI TSACHRELIA. 32 THE YOUNG ARCHITECT IâD LIKE TO HAVE SITTING NEXT TO ME. STEPHEN T. CHRISMAN. 35 IN SEARCH OF AN ARCHITECTURAL ASSISTANT. PETER GREENBERG. 37 CURIOUS ALWAYS. TIM MCCARTHY. 41 DATA LITERACY AND PERFORMANCE SIMULATION. JIHUN KIM. 44 URBAN MICROCLIMATE ANALYSIS- EMERGING SCHOLARS. GABRIELA MARTINEZ, YUYING XIAN. 47 DURA. STA CLUB. 49 CONSTRAINTS. SEVERINO ALFONSO. 54 THE MITIGATOR- ARCH 4810. ASLI ONEY. 71 INTERVIEW WITH CLAUDIA HERNANDEZ. JAMAR DINALL. 79 PUBLIC LIBRARY- ARCH 2310. EVELYN RICHARDSON. 85 SCHOOL OF ARCHITECTURE- ARCH 2410. JAMAR DINALL. 89 SCHOOL OF ARCHITECTURE- ARCH2410. IVANA BATISTA. 93 RED HOOK MASTER PLAN- ARCH 4710. ADAM ELKHOULY, MARCELO LEDESMA, JAMES RIGLEY. 97 RED HOOK MASTER PLAN- ARCH 4710. ONICA LEITCH-EDINBORO. 101 BROOKLYN MIXED-USE HIGH RISE- ARCH 4710. SAADIQ ALLI. 103 BROOKLYN HIGH RISE- ARCH 4810. ALLON MORGAN. 107 MULTI-USE COMPLEX AND PARK- ARCH 4710. ALIMERV PROCTOR. 109 MOVEMENT TO SPACE- RED HOOK MASTER PLAN- ARCH 4710. JORGE TLATELPA, EMILY NORTHIA, CHRISTINE NICOLE JAYCO. 113 INTERVIEW WITH WENDELL EDWARDS. STEVEN ZIMMERMAN. 118 INTERVIEW WITH CESAR SALAZAR. DARWIN DIAZ. 123 INTERVIEW WITH TIM MALDONADO. GABRIELA MARTINEZ & YUYING XIAN. 125 STUDENT INTERVIEWS. TING LAU. 129 ALUMNI VOICES. CAITLIN MCMANUS '17. 135 MARSHA-ANN CADOUGAN '13. 136 | Y63: CUNY Academic Works | Z63: https://academicworks.cuny.edu/context/ny_techne/article/1004/viewcontent/TECHNE_ISSU_with_text_recog.pdf | AA63: Not found | AB63: closed | AC63: School of Technology & Design | AD63: 0 | AE63: No
A64: ARCH-0089 | B64: Duddy | C64: Michael | D64: Michael Duddy | E64: Associate Professor | F64: NYC College of Technology | G64: Architectural Technology | H64: MDuddy@citytech.cuny.edu | I64: Journal article | J64: The Ends of Reason: Towards an Understanding of the Architectonic | K64: 2018 | L64: Journal of Aesthetics and Phenomenology | M64: Michael C. Duddy | Q64: 10.1080/20539320.2018.1460111 | R64: https://doi.org/10.1080/20539320.2018.1460111 | S64: OpenAlex | T64: 1 | U64: High (City Tech affiliation on paper) | X64: In the Critique of Pure Reason, Kant defines the architectonic as the “art of constructing systems.” For him, architectonics is the systematic unity of knowledge according to a principle he identifies as the ends of reason. In the discipline of architecture, the concept of the architectonic has varied understandings: the unity of form of the appearance of the building that is given; or the order of the unity of form that systematizes the appearance as it is grasped; or the principle of the order of the unity of form that is understood. This paper argues that the architectonic in architecture is described by a principle of order of the unity of form, and that this principle is tantamount to Kant’s principle of the ends of reason. This thesis is investigated by relating Kant’s concept of the architectonic to the concept of concinnitas proposed by the fifteenth-century architect and humanist, Leon Battista Alberti. Concinnitas is understood here as the conceptual complement to Kant’s principle of the ends of reason which underlies his architectonic: both are doctrines of the unity of the whole, and both are initiated as an a priori judgment of the immanent “ends of reason” that is inherent to an idea and assures the “systematic unity” of that idea is given as the perfection of the concept which in Alberti’s case is the building’s form. Both interpretations are grounded on formal perfection where the perfection of Kant’s systematic unity of reason finds its complement in Alberti’s unity of form. | Y64: OpenAlex | AA64: Not found | AB64: closed | AC64: School of Technology & Design | AD64: 2 | AE64: No
A65: ARCH-0091 | B65: Smith | C65: Shelley | D65: Shelley Smith | E65: Professor | F65: NYC College of Technology | G65: Architectural Technology | H65: SSmith@citytech.cuny.edu | I65: Journal article | J65: Arabinose substitution effect on xylan rigidity and self-aggregation | K65: 2019 | L65: Publications and Research | M65: Shrestha, Utsab; Smith, Sydney; Pingali, Sai Venkatesh; Yang, Hui; Zahran, Mai; Breunig, Llyod; Wilson, Liza; Cosgrove, Daniel; O'Neill, Hugh; Petridis, Loukas | R65: https://academicworks.cuny.edu/ny_pubs/411 | S65: CUNY Academic Works | T65: 1 | U65: High (in CUNY Academic Works) | X65: Substituted xylans play an important role in the structure and mechanics of the primary cell wall of plants. Arabinoxylans (AX) consist of a xylose backbone substituted with arabinose, while glucuronoarabinoxylans (GAX) also contain glucuronic acid substitutions and ferulic acid esters on some of the arabinoses. We provide a molecular-level description on the dependence of xylan conformational, selfaggregation properties and binding to cellulose on the degree of arabinose substitution. Molecular dynamics simulations reveal fully solubilized xylans with a low degree of arabinose substitution (lsAX) to be stiffer than their highly substituted (hsAX) counterparts. Small-angle neutron scattering experiments indicate that both wild-type hsAX and debranched lsAX form macromolecular networks that are penetrated by water. In those networks, lsAX are more folded and entangled than hsAX chains. Increased conformational entropy upon network formation for hsAX contributes to AX loss of solubility upon debranching. Furthermore, simulations show the intermolecular contacts to cellulose are not affected by arabinose substitution (within the margin of error). Ferulic acid is the GAX moiety found here to bind to cellulose most strongly, suggesting it may play an anchoring role to strengthen GAX-cellulose interactions. The above results suggest highly substituted GAX acts as a spacer, keeping cellulose microfibrils apart, whereas low substitution GAX is more localized in plant cell walls and promotes cellulose bundling. | Y65: CUNY Academic Works | Z65: https://academicworks.cuny.edu/context/ny_pubs/article/1430/viewcontent/cellulose_ms_revised.pdf | AA65: PDF in CUNY Academic Works | AC65: School of Technology & Design | AE65: No
A66: ARCH-0093 | B66: Vaidya | C66: Sanjive | D66: Sanjive Vaidya | E66: Associate Professor | F66: NYC College of Technology | G66: Architectural Technology | H66: SVaidya@citytech.cuny.edu | I66: Grant | J66: Deans Roundtable.” Panel discussion with 15 East Coast Schools of Architecture and Planning, AIA: Center for Architecture New York, 2019, 2020 & 2021 | K66: 2019 | S66: Dept bio | T66: 1 | U66: Medium (self-reported in faculty bio) | W66: Vaidya, Sanjive. “Deans Roundtable.” Panel discussion with 15 East Coast Schools of Architecture and Planning, AIA: Center for Architecture New York, 2019, 2020 & 2021. | AC66: School of Technology & Design | AE66: No
A67: ARCH-0094 | B67: Anzalone | C67: Phillip | D67: Phillip Anzalone | E67: Associate Professor | F67: NYC College of Technology | G67: Architectural Technology | H67: PAnzalone@citytech.cuny.edu | I67: Conference paper | J67: Experimental Applications of Virtual Reality in Design Education | K67: 2019 | L67: ACADIA quarterly | M67: Amber Bartosh; Phillip Anzalone | Q67: 10.52842/conf.acadia.2019.458 | R67: https://doi.org/10.52842/conf.acadia.2019.458 | S67: OpenAlex; CUNY Academic Works | T67: 2 | U67: High (City Tech affiliation on paper); 2 sources | X67: By introducing rapid reproduction, algorithms, and complex formal configurations, the digital era of architecture began a revolution. Architects incorporated the computational capacity of the computer into the design process both as a tool and as a critical component of the theories and practice of architecture as a whole. As we move into what has been coined “the second digital turn,” a period in which digital integration is considered ubiquitous, how can we consider, prepare, and propel towards the next technological innovation to significantly inform design thinking, representation, and manifestation? What tools are available to investigate this speculative design future and how can they be implemented? If the integration of technology in architecture is now a given, perhaps the next digital design era is not just digital but virtual. As new technologies emerge the potential for integrating the virtual design world with our physical senses affords novel possibilities for interactive design, simulation, analysis and construction. Hybrid reality technologies including virtual reality (VR) and augmented reality (AR), embody the potential to supersede conventional representation methodologies such as drawing, rendering, physical modeling, and animation. As they become increasingly pervasive, they will transform how we communicate ideas and data as spatial concepts. Further, they will reform the construct of the built environment when applied to both materiality and fabrication. This paper will describe the incorporation of VR as a tool in various classroom and laboratory settings, recognize the educational outcomes of this incorporation, and identify the potential relationship of these technologies to future academic exploration and application to practice. | Y67: OpenAlex | Z67: https://academicworks.cuny.edu/ny_pubs/693 | AA67: Open-access PDF (via OpenAlex) | AB67: green | AC67: School of Technology & Design | AD67: 15 | AE67: No
A68: ARCH-0096 | B68: Chin | C68: Ting | D68: Ting Chin | E68: Chair | F68: NYC College of Technology | G68: Architectural Technology | H68: TChin@citytech.cuny.edu | I68: Book chapter | J68: Industrial Ecologies: Manufacturing the Post-industrial Landscape | K68: 2019 | L68: Advances in Science, Technology & Innovation/Advances in science, technology & innovation | M68: Ting Chin | Q68: 10.1007/978-3-030-17308-1_7 | R68: https://doi.org/10.1007/978-3-030-17308-1_7 | S68: OpenAlex | T68: 1 | U68: High (City Tech affiliation on paper) | AA68: Not found | AB68: closed | AC68: School of Technology & Design | AD68: 5 | AE68: No
A69: ARCH-0097 | B69: Duddy | C69: Michael | D69: Michael Duddy | E69: Associate Professor | F69: NYC College of Technology | G69: Architectural Technology | H69: MDuddy@citytech.cuny.edu | I69: Journal article | J69: Logical Accidents and the Problem of the Inside Corner | K69: 2019 | L69: Nexus Network Journal | M69: Michael C. Duddy | Q69: 10.1007/s00004-019-00435-6 | R69: https://doi.org/10.1007/s00004-019-00435-6 | S69: OpenAlex | T69: 1 | U69: High (City Tech affiliation on paper) | AA69: Not found | AB69: closed | AC69: School of Technology & Design | AD69: 0 | AE69: No
A70: ARCH-0098 | B70: Chin | C70: Ting | D70: Ting Chin | E70: Chair | F70: NYC College of Technology | G70: Architectural Technology | H70: TChin@citytech.cuny.edu | I70: Book chapter | J70: Mapping Urban Performance Culture: A Common Ground for Architecture and Theater | K70: 2019 | L70: Springer eBooks | M70: Ting Chin; Christopher Swift | Q70: 10.1007/978-3-030-32471-1_6 | R70: https://doi.org/10.1007/978-3-030-32471-1_6 | S70: OpenAlex; CUNY Academic Works | T70: 2 | U70: High (City Tech affiliation on paper); 2 sources | X70: Our co-taught course focuses on theater history, with an emphasis on performance architecture. Assignments are designed to illuminate the ways in which architectural design and technology inform performance practices and audience reception. The pivotal assignment for exploring interdisciplinarity is a three-week module on mapping historical theaters in New York City. Open-source Global Information Systems (GIS) software serves as a common mechanism for students to situate theatrical productions in the context of the built urban environment, deepening their understanding of the social, economic, and artistic forces that contributed to performance culture. Mapping is a shared pedagogy for analyzing and presenting research findings from different fields. Learning how to collect, analyze, and map data is also a general education skill that can be applied to disciplines across undergraduate curricula. | Y70: CUNY Academic Works | Z70: https://academicworks.cuny.edu/context/ny_pubs/article/1639/viewcontent/Chin_Swift_Mapping.pdf | AA70: Not found | AB70: closed | AC70: School of Technology & Design | AD70: 1 | AE70: No
A71: ARCH-0103 | B71: Vaidya | C71: Sanjive | D71: Sanjive Vaidya | E71: Associate Professor | F71: NYC College of Technology | G71: Architectural Technology | H71: SVaidya@citytech.cuny.edu | I71: Grant | J71: AIA Brooklyn: Making Change | K71: 2020 | S71: Dept bio | T71: 1 | U71: Medium (self-reported in faculty bio) | W71: Vaidya, Sanjive. “AIA Brooklyn: Making Change.” Department of Architectural Technology program presented at the American Institute of Architects Brooklyn Chapter, New York, June 24, 2020. | AC71: School of Technology & Design | AE71: No
A72: ARCH-0104 | B72: Vaidya | C72: Sanjive | D72: Sanjive Vaidya | E72: Associate Professor | F72: NYC College of Technology | G72: Architectural Technology | H72: SVaidya@citytech.cuny.edu | I72: Grant | J72: Architectural League Program Fosters 'Sense of Belonging' to Larger Design Community Among Local College Students | K72: 2020 | S72: Dept bio | T72: 1 | U72: Medium (self-reported in faculty bio) | W72: Sitz, Miriam. “Architectural League Program Fosters 'Sense of Belonging' to Larger Design Community Among Local College Students.” Architectural Record RSS, Architectural Record, 6 Aug. 2020. | AC72: School of Technology & Design | AE72: No
A73: ARCH-0105 | B73: Vaidya | C73: Sanjive | D73: Sanjive Vaidya | E73: Associate Professor | F73: NYC College of Technology | G73: Architectural Technology | H73: SVaidya@citytech.cuny.edu | I73: Grant | J73: Architecture Schools Are Becoming More Diverse, but the Profession Still Faces Challenges | K73: 2020 | S73: Dept bio | T73: 1 | U73: Medium (self-reported in faculty bio) | W73: Bohanon, Mariah and Steward, Mariah. “Architecture Schools Are Becoming More Diverse, but the Profession Still Faces Challenges.” Insight into Diversity, Oct. 2020, pp. 52-54. | AC73: School of Technology & Design | AE73: No
A74: ARCH-0110 | B74: Vaidya | C74: Sanjive | D74: Sanjive Vaidya | E74: Associate Professor | F74: NYC College of Technology | G74: Architectural Technology | H74: SVaidya@citytech.cuny.edu | I74: Grant | J74: Head of Class: Interview with Dean Harris and Chairman Vaidya | K74: 2020 | S74: Dept bio | T74: 1 | U74: Medium (self-reported in faculty bio) | W74: Duncan, Michelle and Sainvil, Talisha. “Head of Class: Interview with Dean Harris and Chairman Vaidya.” Pylon, Sept/Oct. 2020, pp. 101-108. | AC74: School of Technology & Design | AE74: No
A75: ARCH-0111 | B75: Kim | C75: Jihun | D75: Jihun Kim | E75: Associate Professor | F75: NYC College of Technology | G75: Architectural Technology | H75: JKim@citytech.cuny.edu | I75: Conference paper | J75: Integrating Analog Design Techniques and Building Performance Simulation – From Intuitiveness to Counter-Intuitiveness in Architectural Design Process | K75: 2020 | L75: Building Simulation Conference proceedings | M75: Jihun Kim | Q75: 10.26868/25222708.2019.210861 | R75: https://doi.org/10.26868/25222708.2019.210861 | S75: OpenAlex | T75: 1 | U75: High (City Tech affiliation on paper) | X75: The paper presents a pedagogical approach to teach building's environmental performance by using tangible architectural analysis techniques combined with complex computer simulations.The aim was to enhance the learning process for simulation-illiterate architectural students.Through interpreting and translating information from one mode of analysis to another, students prioritized what may have affected energy flow, therefore, they could strategize how to assess the given system, helping them to design high-performance buildings. | Y75: OpenAlex | AA75: Not found | AB75: closed | AC75: School of Technology & Design | AD75: 0 | AE75: No
A76: ARCH-0112 | B76: Vaidya | C76: Sanjive | D76: Sanjive Vaidya | E76: Associate Professor | F76: NYC College of Technology | G76: Architectural Technology | H76: SVaidya@citytech.cuny.edu | I76: Grant | J76: J. Max Bond Jr. Lecture | IMPATIENCE! | K76: 2020 | S76: Dept bio | T76: 1 | U76: Medium (self-reported in faculty bio) | W76: Spark, Muriel. “J. Max Bond Jr. Lecture | IMPATIENCE!” Interview by Maria Budtz Sorenson and Suzanne Mecs. The Center for Architecture, AIA New York, 09 Oct. 2020. | AC76: School of Technology & Design | AE76: No
A77: ARCH-0113 | B77: Vaidya | C77: Sanjive | D77: Sanjive Vaidya | E77: Associate Professor | F77: NYC College of Technology | G77: Architectural Technology | H77: SVaidya@citytech.cuny.edu | I77: Grant | J77: Lokko, Lesley., Sutton, Sharon., Rickenbacker, Shawn., Henry, Lisa C., Vaidya, Sanjive., Weisz, Claire | K77: 2020 | S77: Dept bio | T77: 1 | U77: Medium (self-reported in faculty bio) | W77: Lokko, Lesley., Sutton, Sharon., Rickenbacker, Shawn., Henry, Lisa C., Vaidya, Sanjive., Weisz, Claire. (2020, October 14). A Case for Public Design Education. [ Conference Presentation]. New York | AC77: School of Technology & Design | AE77: No
A78: ARCH-0116 | B78: Vaidya | C78: Sanjive | D78: Sanjive Vaidya | E78: Associate Professor | F78: NYC College of Technology | G78: Architectural Technology | H78: SVaidya@citytech.cuny.edu | I78: Grant | J78: Reimagine Town Hall Presentations about architecture and contemporary challenges, based on workshops with 2020 design graduates | K78: 2020 | S78: Dept bio | T78: 1 | U78: Medium (self-reported in faculty bio) | W78: Vaidya, Sanjive, and multiple participants. “Reimagine Town Hall Presentations about architecture and contemporary challenges, based on workshops with 2020 design graduates.” The Architectural League of New York, 7 Oct. 2020 | AC78: School of Technology & Design | AE78: No
A79: ARCH-0117 | B79: Vaidya | C79: Sanjive | D79: Sanjive Vaidya | E79: Associate Professor | F79: NYC College of Technology | G79: Architectural Technology | H79: SVaidya@citytech.cuny.edu | I79: Grant | J79: Students and Alumni Gather to Discuss Racism in Architecture Schools | K79: 2020 | S79: Dept bio | T79: 1 | U79: Medium (self-reported in faculty bio) | W79: Morley, Jack Balderrama. “Students and Alumni Gather to Discuss Racism in Architecture Schools.” The Architect's Newspaper, 3 Aug. 2020 | AC79: School of Technology & Design | AE79: No
A80: ARCH-0122 | B80: Vaidya | C80: Sanjive | D80: Sanjive Vaidya | E80: Associate Professor | F80: NYC College of Technology | G80: Architectural Technology | H80: SVaidya@citytech.cuny.edu | I80: Grant | J80: The New York Review of Architecture and The Architectural League of New York, New York | K80: 2020 | S80: Dept bio | T80: 1 | U80: Medium (self-reported in faculty bio) | W80: Vaidya, Sanjive and Sutton, Sharon (2020, July 30). New Grounds for Design Education. The New York Review of Architecture and The Architectural League of New York, New York. | AC80: School of Technology & Design | AE80: No
A81: ARCH-0129 | B81: Vaidya | C81: Sanjive | D81: Sanjive Vaidya | E81: Associate Professor | F81: NYC College of Technology | G81: Architectural Technology | H81: SVaidya@citytech.cuny.edu | I81: Grant | J81: Goldstein, Brian., Rickenbacker, Shawn., Vaidya, Sanjive., Davis, Steven., Phillips, Karen | K81: 2021 | S81: Dept bio | T81: 1 | U81: Medium (self-reported in faculty bio) | W81: Goldstein, Brian., Rickenbacker, Shawn., Vaidya, Sanjive., Davis, Steven., Phillips, Karen. (2021, October 14). J. Max Bond Jr. Lecture | The Man, The Legacy. [ Presentation & Panel Discussion | AC81: School of Technology & Design | AE81: No
A82: ARCH-0133 | B82: Vaidya | C82: Sanjive | D82: Sanjive Vaidya | E82: Associate Professor | F82: NYC College of Technology | G82: Architectural Technology | H82: SVaidya@citytech.cuny.edu | I82: Grant | J82: On Being Chair: Martyr or Hostage? | K82: 2021 | S82: Dept bio | T82: 1 | U82: Medium (self-reported in faculty bio) | W82: “On Being Chair: Martyr or Hostage?” CUNY Conference for Department Chairs, November 5, 2021. | AC82: School of Technology & Design | AE82: No
A83: ARCH-0136 | B83: Azaroff | C83: Illya | D83: Illya Azaroff | E83: Professor | F83: NYC College of Technology | G83: Architectural Technology | H83: IAzaroff@citytech.cuny.edu | I83: Journal article | J83: Rapid Research and Assessment on COVID-19 and Climate in New York City | K83: 2021 | L83: Journal of Extreme Events | M83: Nora I. Kyrkjebø; Adam S. Parris; Janice Barnes; Illya Azaroff; Deborah L. Balk; Ana Isabel Baptista; Christian V. Braneon; William R. Calabrese; Treston Codrington; Jessica Colon; Farzana Gandhi; Maureen George; Peter M. Groffman; Justin Gundlach; Rachel Hogan Carr; Nancy Holt; Radley Horton; Arthee Jahangir; Bobuchi Ken-Opurum; Kim Knowlton; Robin M. Leichenko; Nicole P. Maher; Peter John Marcotullio; Thomas Matte; Katherine A. McComas; S. Kyle McKay; Timon McPhearson; Richard H. Moss; Guy J. P. Nordenson; Thaddeus Pawlowski; Nicholas B. Rajkovich; Kevin A. Reed; Laurie Schoeman; John Shapiro; Danielle Spiegel-Feld; John Tchen; Joel E. Towers; Gernot Wagner | Q83: 10.1142/s234573762150010x | R83: https://doi.org/10.1142/s234573762150010x | S83: OpenAlex | T83: 1 | U83: High (City Tech affiliation on paper) | X83: In May 2020, the New York City (NYC) Mayor’s Office of Climate Resiliency (MOCR) began convening bi-weekly discussions, called the Rapid Research and Assessment (RRA) Series, between City staff and external experts in science, policy, design, engineering, communications, and planning. The goal was to rapidly develop authoritative, actionable information to help integrate resiliency into the City’s COVID response efforts. The situation in NYC is not uncommon. Extreme events often require government officials, practitioners, and citizens to call upon multiple forms of scientific and technical assistance from rapid data collection to expert elicitation, each spanning more or less involved engagement. We compare the RRA to similar rapid assessment efforts and reflect on the nature of the RRA and similar efforts to exchange and co-produce knowledge. The RRA took up topics on social cohesion, risk communication, resilient and healthy buildings, and engagement, in many cases strengthening confidence in what was already known but also refining the existing knowledge in ways that can be helpful as the pandemic unfolds. Researchers also learned from each other ways to be supportive of the City of New York and MOCR in the future. The RRA network will continue to deepen, continue to co-produce actionable climate knowledge, and continue to value organizational sensemaking as a usable climate service, particularly in highly uncertain times. Given the complex, rare, and, in many cases, unfamiliar context of COVID-19, we argue that organizational sensemaking is a usable climate service. | Y83: OpenAlex | AA83: Not found | AB83: closed | AC83: School of Technology & Design | AD83: 4 | AE83: No
A84: ARCH-0137 | B84: Azaroff | C84: Illya | D84: Illya Azaroff | E84: Professor | F84: NYC College of Technology | G84: Architectural Technology | H84: IAzaroff@citytech.cuny.edu | I84: Grant | J84: SCC-CIVIC-PG Track A - The Lily Pad Neighborhood Mobility Hub Planning and Feasibility Study | K84: 2021 | L84: NSF: S&CC: Smart & Connected Commun | M84: Illya Azaroff; Gerarda M Shields; Jinwon Kim | N84: PI | O84: 50000 | P84: 2047236 | R84: https://www.nsf.gov/awardsearch/showAward?AWD_ID=2047236 | S84: NSF | T84: 1 | U84: High (NSF award to City Tech) | X84: The project is to study the feasibility and create a conceptual plan for a resilient neighborhood-based mobility hub in the Rockaways Peninsula, New York City. The mobility hub provides a single point of connectivity where different travel options: walking, biking, transit, and shared mobility – come together. It addresses the long standing challenges between location of affordable housing and jobs by providing lower cost transportation choices, as well as bridging connections to high-speed transit and jobs. The mobility hub would also provide support for vulnerable residents by building resilient capacity to disasters. In times of crisis, the Hub would transform and support preparation, response, and recovery; providing key connections to critical emergency services. The Rockaways was selected because of its mobility, housing, and social equity issues. It provides an ideal community for evaluating mobility options to solve long standing issues between housing affordability and jobs as it leverages New York City Housing Authority (NYCHA)’s long term commitment to this community. The goals of this project are 1) through the use of community engagement and data gathering, create a feasible mobility program to connect the community, neighborhoods, isolated / vulnerable populations with affordable housing, jobs and critical services, 2) establish a functional plan and budget for implementing the mobility solutions pilot program. The project directly addresses challenges of the CIVIC Innovation Challenge Track A: Communities and Mobility: Offering Better Mobility Options to Solve the Spatial Mismatch Between Housing Affordability and Jobs. CIVIC is a collaboration between the NSF, the Vehicle Transportation Office of the Department of Energy, and the Science and Technology Directorate of the Department of Homeland Security. This award reflects NSF's statutory mission and has been deemed worthy of support through evaluation using the Foundation's intellectual merit and broader impacts review criteria. | Y84: NSF | AC84: School of Technology & Design | AE84: No
A85: ARCH-0138 | B85: Kim | C85: Jihun | D85: Jihun Kim | E85: Associate Professor | F85: NYC College of Technology | G85: Architectural Technology | H85: JKim@citytech.cuny.edu | I85: Grant | J85: SCC-CIVIC-PG Track A - The Lily Pad Neighborhood Mobility Hub Planning and Feasibility Study | K85: 2021 | L85: NSF: S&CC: Smart & Connected Commun | M85: Illya Azaroff; Gerarda M Shields; Jinwon Kim | N85: Co-PI | O85: 50000 | P85: 2047236 | R85: https://www.nsf.gov/awardsearch/showAward?AWD_ID=2047236 | S85: NSF | T85: 1 | U85: High (NSF award to City Tech) | X85: The project is to study the feasibility and create a conceptual plan for a resilient neighborhood-based mobility hub in the Rockaways Peninsula, New York City. The mobility hub provides a single point of connectivity where different travel options: walking, biking, transit, and shared mobility – come together. It addresses the long standing challenges between location of affordable housing and jobs by providing lower cost transportation choices, as well as bridging connections to high-speed transit and jobs. The mobility hub would also provide support for vulnerable residents by building resilient capacity to disasters. In times of crisis, the Hub would transform and support preparation, response, and recovery; providing key connections to critical emergency services. The Rockaways was selected because of its mobility, housing, and social equity issues. It provides an ideal community for evaluating mobility options to solve long standing issues between housing affordability and jobs as it leverages New York City Housing Authority (NYCHA)’s long term commitment to this community. The goals of this project are 1) through the use of community engagement and data gathering, create a feasible mobility program to connect the community, neighborhoods, isolated / vulnerable populations with affordable housing, jobs and critical services, 2) establish a functional plan and budget for implementing the mobility solutions pilot program. The project directly addresses challenges of the CIVIC Innovation Challenge Track A: Communities and Mobility: Offering Better Mobility Options to Solve the Spatial Mismatch Between Housing Affordability and Jobs. CIVIC is a collaboration between the NSF, the Vehicle Transportation Office of the Department of Energy, and the Science and Technology Directorate of the Department of Homeland Security. This award reflects NSF's statutory mission and has been deemed worthy of support through evaluation using the Foundation's intellectual merit and broader impacts review criteria. | Y85: NSF | AC85: School of Technology & Design | AE85: No
A86: ARCH-0143 | B86: Vaidya | C86: Sanjive | D86: Sanjive Vaidya | E86: Associate Professor | F86: NYC College of Technology | G86: Architectural Technology | H86: SVaidya@citytech.cuny.edu | I86: Grant | J86: The Case for a Public Design Education | K86: 2021 | M86: Vaidya, Sanjive | S86: Dept bio | T86: 1 | U86: Medium (self-reported in faculty bio) | W86: Vaidya, Sanjive. “The Case for a Public Design Education” Metropolis Magazine. 30 June 2021 | AC86: School of Technology & Design | AE86: No
A87: ARCH-0146 | B87: Kim | C87: Jihun | D87: Jihun Kim | E87: Associate Professor | F87: NYC College of Technology | G87: Architectural Technology | H87: JKim@citytech.cuny.edu | I87: Journal article | J87: A non-invasive artificial intelligence approach for the prediction of human blastocyst ploidy: a retrospective model development and validation study | K87: 2022 | L87: Publications and Research | M87: Barnes, Josue; Brendel, Matthew; Gao, Vianne R; Rajendran, Suraj; Kim, Junbum; Li, Qianzi; Malmsten, Jonas E; Sierra, Jose T; Zisimopoulos, Pantelis; Sigaras, Alexandros; Khosravi, Pegah; Meseguer, Marcos; Zhan, Qiansheng; Rosenwaks, Zev; Elemento, Olivier; Zaninovic, Nikica; Hajirasouliha, Iman | R87: https://academicworks.cuny.edu/ny_pubs/1180 | S87: CUNY Academic Works | T87: 1 | U87: High (in CUNY Academic Works) | X87: Summary Background One challenge in the field of in-vitro fertilisation is the selection of the most viable embryos for transfer. Morphological quality assessment and morphokinetic analysis both have the disadvantage of intra-observer and inter-observer variability. A third method, preimplantation genetic testing for aneuploidy (PGT-A), has limitations too, including its invasiveness and cost. We hypothesised that differences in aneuploid and euploid embryos that allow for model-based classification are reflected in morphology, morphokinetics, and associated clinical information. Methods In this retrospective study, we used machine-learning and deep-learning approaches to develop STORK-A, a non-invasive and automated method of embryo evaluation that uses artificial intelligence to predict embryo ploidy status. Our method used a dataset of 10â378 embryos that consisted of static images captured at 110 h after intracytoplasmic sperm injection, morphokinetic parameters, blastocyst morphological assessments, maternal age, and ploidy status. Independent and external datasets, Weill Cornell Medicine EmbryoScope+ (WCM-ES+; Weill Cornell Medicine Center of Reproductive Medicine, NY, USA) and IVI Valencia (IVI Valencia, Health Research Institute la Fe, Valencia, Spain) were used to test the generalisability of STORK-A and were compared measuring accuracy and area under the receiver operating characteristic curve (AUC). Findings Analysis and model development included the use of 10â378 embryos, all with PGT-A results, from 1385 patients (maternal age range 21â48 years; mean age 36Â·98 years [SD 4Â·62]). STORK-A predicted aneuploid versus euploid embryos with an accuracy of 69Â·3% (95% CI 66Â·9â71Â·5; AUC 0Â·761; positive predictive value [PPV] 76Â·1%; negative predictive value [NPV] 62Â·1%) when using images, maternal age, morphokinetics, and blastocyst score. A second classification task trained to predict complex aneuploidy versus euploidy and single aneuploidy produced an accuracy of 74Â·0% (95% CI 71Â·7â76Â·1; AUC 0Â·760; PPV 54Â·9%; NPV 87Â·6%) using an image, maternal age, morphokinetic parameters, and blastocyst grade. A third classification task trained to predict complex aneuploidy versus euploidy had an accuracy of 77Â·6% (95% CI 75Â·0â80Â·0; AUC 0Â·847; PPV 76Â·7%; NPV 78Â·0%). STORK-A reported accuracies of 63Â·4% (AUC 0Â·702) on the WCM-ES+ dataset and 65Â·7% (AUC 0Â·715) on the IVI Valencia dataset, when using an image, maternal age, and morphokinetic parameters, similar to the STORK-A test dataset accuracy of 67Â·8% (AUC 0Â·737), showing generalisability. Interpretation As a proof of concept, STORK-A shows an ability to predict embryo ploidy in a non-invasive manner and shows future potential as a standardised supplementation to traditional methods of embryo selection and prioritisation for implantation or recommendation for PGT-A. | Y87: CUNY Academic Works | Z87: https://academicworks.cuny.edu/context/ny_pubs/article/2208/viewcontent/1_s2.0_S2589750022002138_main.pdf | AA87: PDF in CUNY Academic Works | AC87: School of Technology & Design | AE87: Yes | AF87: title: artificial intelligence; abstract: machine-learning, deep-learning, artificial intelligence
A88: ARCH-0147 | B88: Hom | C88: Kevin | D88: Kevin Hom | E88: Professor | F88: NYC College of Technology | G88: Architectural Technology | H88: KHom@citytech.cuny.edu | I88: Paper (venue type unclear) | J88: Circular economy in the built environment | K88: 2022 | L88: Publications and Research | M88: Hom, Kevin | R88: https://academicworks.cuny.edu/ny_pubs/984 | S88: CUNY Academic Works | T88: 1 | U88: High (in CUNY Academic Works) | X88: The circular economy is as much an attitude as a program. The circular economy (CE) is an action plan which identifies a series of goals and associated outcomes. It is a comprehensive response to the impact of the industrial revolution and the linear economy model which was the economic basis of the industrial revolution. This manuscript discusses the philosophy and strategies of the circular economy and the role that the built environment has in implementing this philosophy. | Y88: CUNY Academic Works | Z88: https://academicworks.cuny.edu/context/ny_pubs/article/2008/viewcontent/hom.pdf | AA88: PDF in CUNY Academic Works | AC88: School of Technology & Design | AE88: No
A89: ARCH-0154 | B89: Duddy | C89: Michael | D89: Michael Duddy | E89: Associate Professor | F89: NYC College of Technology | G89: Architectural Technology | H89: MDuddy@citytech.cuny.edu | I89: Journal article | J89: TECHNE Issue 06 | K89: 2022 | L89: TECHNE | M89: Duddy, Michael; Matangira, Farai; Nazirova, Sanobar; Owolabi, Ololade Tolu; Diaz, Darwin | R89: https://academicworks.cuny.edu/ny_techne/6 | S89: CUNY Academic Works | T89: 1 | U89: High (in CUNY Academic Works) | X89: INTRODUCTION Sanjive Vaidya, RA, Department chair âMidnight on Feb. 5, 1952, a cross was burned in front of Stoughton Hall, where the 11 black members of the Harvard Class of 1955 livedâ¦ One of the 11 black students was the late J. Max Bond â55, who became one the nationâs leading black architects, stressing socially progressive themes and public service.â -Hartman, Chester. âCross burning in Harvard Yard?â The Harvard Crimson, 17 Sept 2014. Symbolizing structural and social barriers for minorities and people of color accessing higher education, this violent scene is heightened by its setting. The venerated campus represents a pinnacle of logic and reason. Faculty openly discouraged Max Bond from pursuing architecture because of the color of his skin. His experience at Harvard is alarming, but familiar. The barriers are now less overt, but remain economically polarizing and dispiriting. By completing his degree, Max Bond demonstrated the steel resolve and calm demeanor that propelled him to prominence while using his power to help others do the same. He advanced ideas on the intersection between architecture, public service and the pivotal role of public education. Access to higher education is fundamental to the discourse on equity and advancement. The American Institute of Architects (AIA) 2016 report on Diversity in the Profession of Architecture enumerates barriers to the pursuit of an architectural education. Beyond the high cost of architectural programs is the lack of role models of color. First and secondgeneration students choose more lucrative careers. Architectâs salaries are notoriously low. Underscoring this is a lack of awareness about the scope of architecture. The New York Building Congress forecast $56.4 billion of construction spending on the city in 2020. This is spread over many components of development and reconstruction. It points to the expanding use of digital design technologies, advanced materials and performance analytics to manage the increasing complexity of building in the city. Efforts to ensure that design and planning are aligned with resource conservation and energy management increase construction costs. Graduates from the Department of Architectural Technology often engage non-traditional design practices such as: digital fabrication and representation, preservation technologies, building performance analytics and project management. The newly reconfigured fouryear BTech curriculum harnesses their interests and talents. It is a strategy to bring students closer to the drivers of construction spending, accessing employment opportunities with sustainable compensation. Capitalizing on this robust technical curriculum, the new five-year BArch program provides a high quality, affordable professional degree pathway for students pursuing a role in the practice of building design and construction. While both degrees offer students an opportunity to pursue licensure, the BArch degree accelerates the timeline. It promises to be an industry disrupter, offering agency to a demographic frequently underserved and unrecognized for their leadership potential. The courage and tenacity of these students to overcome significant economic and social barriers is evidence of their ability to succeed. Educating the quantity and diversity of architectural students, City Tech is situated to play an important role in the revitalization and public well-being of New York City. It remains a reliable ally and positive catalyst for the disadvantaged and underrepresented. The process of design thinking coupled with personal experience of the cityâs deficiencies, make these students important contributors to discussions on infrastructure, disaster preparation and climate change. They can become effective advocates for their communities with firsthand experience of inadequate public accommodations for the aging and dying, support for the mentally ill and disabled, housing for the homeless and the formerly incarcerated. Their education is an act of self-defense. It is a defiant assertion of belonging, and pride in diversity. An effective design education links aesthetics with science, policy and human need. Vitruvian principles for the twenty-first century. Table of contents INTRODUCTION EDITORS 3 TABLE OF CONTENTS 4 MESSAGE FROM THE CHAIR SANJIVE VAIDYA 7 FACULTY WORK 8 EXPLORATION OF LIGHT THROUGH VIRTUAL REALITY ESTEBAN BEITA 11 FROM TANGIBILITY TO COMPLEXITY JIHUN KIM 19 COLLECTIVE COMPLEXION JIHUN KIM 27 INTERVIEW FREDERIC LEVRAT 39 COMMERCIAL TOWER AND FACADE DESIGN KATHERINE BUCHELLI 42 EDUCATION, DESIGN AND PRACTICE JASON A. MONTGOMERY 45 DESIGN 8 NET ZERO COMMERCIAL TOWER FACADE STUDIO JOHN NEARY / VICTORIA ERESKINA 55 MIXED REALITY IN FACADE EDUCATION PHILLIP ANZALONE 65 STRUCTURE FOR ARCHITECTS RAMSEY DABBY / ASHWANI BEDI 74 EXPRESSING ENERGY ROB ROTHBLATT 79 STUDENT WORK 87 BROOKLYN HEIGHTS PUBLIC LIBRARY ARCH DESIGN STUDIO 3 ABRIL RODRIGUEZ 89 BROOKLYN STACK HOUSES ARCH DESIGN STUDIO 5 ALBERT W. VARGAS 91 BROOKLYN URBAN VILLAGE PARK ARCH DESIGN STUDIO 5 FARAI MATANGIRA 93 SKYWALK ESPLANADE ARCH DESIGN STUDIO 7 JOSHUA CANDO 95 THE ANELIDA ARCH DESIGN STUDIO 6 JULIA PROKOP 97 NEW GOWANUS HOSTEL + FISH % OYSTER FARM ARCH DESIGN STUDIO 5 OLIVER HADI 99 COMMUNITY HOUSING DEVELOPMENT ARCH DESIGN STUDIO 6 OLOLADE T. OWOLABI 101 NYC HOUSING AUTHORITY: AVENUE ARCH DESIGN STUDIO 6 PAMELA LOPEZ 103 HOUSING PROJECT ARCH DESIGN STUDIO 6 RAFIA AMIN 105 NYCHA HOUSING PROJECT ARCH DESIGN STUDIO 6 TASFIA AMIR 107 GOWANUS CANAL HOSTEL ARCH DESIGN STUDIO 5 TIFFANY ZHANG 109 STUDENT WRITING: PRINCIPLES & THEORIES OF ARCHITECTURE 111 ARCHITECTURE CLUB 133 | Y89: CUNY Academic Works | Z89: https://academicworks.cuny.edu/context/ny_techne/article/1005/viewcontent/TECHNE_Master_Document.pdf | AA89: PDF in CUNY Academic Works | AC89: School of Technology & Design | AE89: No
A90: ARCH-0161 | B90: Kim | C90: Jihun | D90: Jihun Kim | E90: Associate Professor | F90: NYC College of Technology | G90: Architectural Technology | H90: JKim@citytech.cuny.edu | I90: Journal article | J90: Chinatown Unbound: Trans-Asian Urbanism in the Age of China | K90: 2023 | L90: Contemporary Sociology A Journal of Reviews | M90: Jinwon Kim | Q90: 10.1177/00943061231204791a | R90: https://doi.org/10.1177/00943061231204791a | S90: OpenAlex | T90: 1 | U90: High (City Tech affiliation on paper) | X90: shape mainstream news attention in terms of social movements?Overall, Amenta and Caren offer readers a comprehensive, solid analysis of the role of print media in movement politics.The book is a great read, not only for students of social movements, but also for activists, journalists, and historians. | Y90: OpenAlex | AA90: Not found | AB90: closed | AC90: School of Technology & Design | AD90: 0 | AE90: No
A91: ARCH-0163 | B91: Azaroff | C91: Illya | D91: Illya Azaroff | E91: Professor | F91: NYC College of Technology | G91: Architectural Technology | H91: IAzaroff@citytech.cuny.edu | I91: Conference paper | J91: Creating Equitable Access with the Lily Pad Neighborhood Mobility Hub | K91: 2023 | L91: ASCE Inspire | M91: Gerarda M. Shields; Illya Azaroff; Jinwon Kim | Q91: 10.1061/9780784485163.069 | R91: https://doi.org/10.1061/9780784485163.069 | S91: OpenAlex | T91: 1 | U91: High (City Tech affiliation on paper) | X91: The aftermath of Hurricane Sandy in 2012 accentuated the vulnerabilities of low-lying communities to extreme hydraulic events. However, Sandy also made it clear that these vulnerabilities were not equally experienced. Communities on the Rockaway Peninsula in Queens, New York, were particularly devastated by Hurricane Sandy with more than 1,000 structures destroyed and 10 ft of storm surge flooding the area and recovery continues to this day. The COVID-19 pandemic further exacerbated these vulnerabilities with significant impacts on employment. The Lily Pad is the study of a New York City Housing Authority (NYCHA) prototype mobility hub program to address these vulnerabilities. The mobility hub’s goal is to promote climate change impact readiness and inform government agency operations and maintenance such as NYCHA’s. This was an NSF planning grant. This paper will focus on the first goal of the planning grant which is, through the use of community engagement and data gathering, the creation of feasible pilot mobility programs to connect the community, neighborhoods, and vulnerable populations with affordable housing, jobs, and critical services. | Y91: OpenAlex | AA91: Not found | AB91: closed | AC91: School of Technology & Design | AD91: 1 | AE91: No
A92: ARCH-0164 | B92: Kim | C92: Jihun | D92: Jihun Kim | E92: Associate Professor | F92: NYC College of Technology | G92: Architectural Technology | H92: JKim@citytech.cuny.edu | I92: Conference paper | J92: Creating Equitable Access with the Lily Pad Neighborhood Mobility Hub | K92: 2023 | L92: ASCE Inspire | M92: Gerarda M. Shields; Illya Azaroff; Jinwon Kim | Q92: 10.1061/9780784485163.069 | R92: https://doi.org/10.1061/9780784485163.069 | S92: OpenAlex | T92: 1 | U92: High (City Tech affiliation on paper) | X92: The aftermath of Hurricane Sandy in 2012 accentuated the vulnerabilities of low-lying communities to extreme hydraulic events. However, Sandy also made it clear that these vulnerabilities were not equally experienced. Communities on the Rockaway Peninsula in Queens, New York, were particularly devastated by Hurricane Sandy with more than 1,000 structures destroyed and 10 ft of storm surge flooding the area and recovery continues to this day. The COVID-19 pandemic further exacerbated these vulnerabilities with significant impacts on employment. The Lily Pad is the study of a New York City Housing Authority (NYCHA) prototype mobility hub program to address these vulnerabilities. The mobility hub’s goal is to promote climate change impact readiness and inform government agency operations and maintenance such as NYCHA’s. This was an NSF planning grant. This paper will focus on the first goal of the planning grant which is, through the use of community engagement and data gathering, the creation of feasible pilot mobility programs to connect the community, neighborhoods, and vulnerable populations with affordable housing, jobs, and critical services. | Y92: OpenAlex | AA92: Not found | AB92: closed | AC92: School of Technology & Design | AD92: 1 | AE92: No
A93: ARCH-0177 | B93: Kim | C93: Jihun | D93: Jihun Kim | E93: Associate Professor | F93: NYC College of Technology | G93: Architectural Technology | H93: JKim@citytech.cuny.edu | I93: Paper (venue type unclear) | J93: The Impact of International Technology Education Standards on the Development of a National Curriculum: A Case Study in Korea | K93: 2023 | L93: Publications and Research | M93: Sung, Euisuk; Choi, Yuhuyn; Kim, Ji Suk; Lee, Eunsang; Lim, Yunjin | R93: https://academicworks.cuny.edu/ny_pubs/1083 | S93: CUNY Academic Works | T93: 1 | U93: High (in CUNY Academic Works) | X93: South Korea has mandated technology education as a general education subject since 1954. However, recent educational trends, such as the emergence of computer education; artificial intelligence; Science, Technology, Engineering, and Mathematics (STEM); and K-12 engineering education call for considerable change in Korean technology education. The authors translated and published Standards for Technological and Engineering Literacy (STEL) in Korean to introduce the new standards to Korean educators in response to these challenges. This case study will review the history of Korean technology education from its inception in the 1960s and discuss the potential impacts of STEL on the Korean technology education curriculum. Additionally, this case study will illustrate the process of publishing STEL in Korean, including the team-building process, challenges in translating the text, and peer review for quality control. Lastly, the authors will discuss the implications, visions, and challenges of Korean technology education with STEL translation. | Y93: CUNY Academic Works | Z93: https://academicworks.cuny.edu/context/ny_pubs/article/2110/viewcontent/13_Euisuk_040723__1_.pdf | AA93: PDF in CUNY Academic Works | AC93: School of Technology & Design | AE93: No
A94: ARCH-0183 | B94: Hom | C94: Kevin | D94: Kevin Hom | E94: Professor | F94: NYC College of Technology | G94: Architectural Technology | H94: KHom@citytech.cuny.edu | I94: Conference paper | J94: Circular Economy: The 4Rs reduce-reuse-recycle-recover | K94: 2024 | L94: IOP Conference Series Earth and Environmental Science | M94: Kevin Hom | Q94: 10.1088/1755-1315/1402/1/012042 | R94: https://doi.org/10.1088/1755-1315/1402/1/012042 | S94: OpenAlex; CUNY Academic Works | T94: 2 | U94: High (City Tech affiliation on paper); 2 sources | X94: Abstract This article summarizes the lecture presented at the Net Built 2024 conference. The lecture addresses the unsustainability of the current linear economy, characterized by the “take, make, dispose” model, in light of environmental challenges. The inefficiencies of this system lead to increased energy consumption, elevated CO2 emissions, and the exacerbation of climate change. It examines the current state of design and construction with respect to climate change and sustainable resource management. Additionally, the lecture introduces a methodology that integrates technologies and design philosophies capable of driving significant positive change. By advocating for a transformative approach to the expected lifetime of buildings and components, this presentation explores new paradigms grounded in the principles of the circular economy. To illustrate these strategies and their outcomes, the author provides a series of case studies. The presentation delves into open methods and strategies for managing building systems, focusing on lifecycle impact, durability, serviceability, and obsolescence. | Y94: OpenAlex | Z94: https://doi.org/10.1088/1755-1315/1402/1/012042 | AA94: Open-access page (via OpenAlex) | AB94: diamond | AC94: School of Technology & Design | AD94: 12 | AE94: No
A95: ARCH-0187 | B95: Hernandez-Feiks | C95: Claudia | D95: Claudia Hernandez-Feiks | E95: Associate Professor/B.Arch Co-director | F95: NYC College of Technology | G95: Architectural Technology | H95: CHernandez@citytech.cuny.edu | I95: Conference paper | J95: Metacognition as a Tool for Engineering Technology Students | K95: 2024 | L95: Publications and Research | M95: Melanie Villatoro; Chen Xu; Claudia E Hernandez Feiks; Navid Allahverdi; Serdar Ozlek | Q95: 10.18260/1-2--31457 | R95: https://doi.org/10.18260/1-2--31457 | S95: OpenAlex; CUNY Academic Works | T95: 2 | U95: High (City Tech affiliation on paper); 2 sources | X95: New York City College of Technology, “City Tech,” is the designated senior college of technology within the 24-unit City University of New York (CUNY). The college plays an important role nationally in the education of future scientists, engineers, technologists and mathematicians by offering a broad range of engineering technology majors. These majors have high enrollment annually; However, the one–year retention rates of freshman in the engineering technology associates degrees are typically 10-20% lower as compared to college wide one-year retention rates. One common reason for students changing majors or discontinuing their education after their first year is poor performance in classes. How can we, as faculty, support students and help them excel in their college coursework? According to Sandra McGuire, "If you teach students how to learn, and give simple, straightforward strategies to use, they can significantly increase their learning and performance." This study looks to examine whether McGuire's strategies can be replicated in engineering technology majors at City Tech. Specifically, this pilot phase looked at students majoring in Construction Management and Civil Engineering Technology (CMCE). Courses in CMCE were selected to receive the intervention and our results will look to identify correlations between grade performance and exposure to the intervention. | Y95: OpenAlex | Z95: https://academicworks.cuny.edu/context/ny_pubs/article/1899/viewcontent/18b4_ASEE_Fall2018.pdf | AA95: Not found | AB95: closed | AC95: School of Technology & Design | AD95: 0 | AE95: No
A96: ARCH-0188 | B96: Azaroff | C96: Illya | D96: Illya Azaroff | E96: Professor | F96: NYC College of Technology | G96: Architectural Technology | H96: IAzaroff@citytech.cuny.edu | I96: Journal article | J96: New York State Climate Impacts Assessment Chapter 04: Buildings | K96: 2024 | L96: Annals of the New York Academy of Sciences | M96: Nicholas B. Rajkovich; Carrie Brown; Illya Azaroff; Erik Backus; Shannon Clarke; Jared Enriquez; Bethany Greenaway; Meghan T. Holtan; Jamal Lewis; Ozgem Ornektekin; Laurie Schoeman; Amanda Stevens | Q96: 10.1111/nyas.15200 | R96: https://doi.org/10.1111/nyas.15200 | S96: OpenAlex | T96: 1 | U96: High (City Tech affiliation on paper) | X96: New York State has nearly 5.3 million buildings, and all of them are vulnerable in some way to the impacts of climate change. Understanding these impacts is critical, because risks to buildings not only threaten individual lives but also pose threats to community-level resilience. This chapter examines the impacts of climate change on buildings and, by extension, the people and communities they shelter and support. It also highlights building types and populations that are at particular risk and presents adaptation strategies to protect the state's existing and future building stock from climate impacts. | Y96: OpenAlex | Z96: https://onlinelibrary.wiley.com/doi/pdfdirect/10.1111/nyas.15200 | AA96: Open-access PDF (via OpenAlex) | AB96: hybrid | AC96: School of Technology & Design | AD96: 4 | AE96: No
A97: ARCH-0189 | B97: Azaroff | C97: Illya | D97: Illya Azaroff | E97: Professor | F97: NYC College of Technology | G97: Architectural Technology | H97: IAzaroff@citytech.cuny.edu | I97: Technical report | J97: New York State Climate Impacts Assessment: 04 Buildings | K97: 2024 | L97: Publications and Research | M97: Rajkovich, Nicholas B.; Brown, Carrie; Azaroff, Ilya; Backus, Erik; Clarke, Shannon; Enriquez, Jared; Greenaway, Bethany; Holtan, Meghan T.; Lewis, Jamal; Ornektekin, Ozgem; Schoeman, Laurie | R97: https://academicworks.cuny.edu/ny_pubs/1219 | S97: CUNY Academic Works | T97: 1 | U97: High (in CUNY Academic Works) | X97: New York State has nearly 5.3 million buildings, and all of them are vulnerable in some way to the impacts of climate change. Understanding these impacts is critical, because risks to buildings not only threaten individual lives but also pose threats to community-level resilience. This chapter examines the impacts of climate change on buildings and, by extension, the people and communities they shelter and support. It also highlights building types and populations that are at particular risk and presents adaptation strategies to protect the stateâs existing and future building stock from climate impacts. | Y97: CUNY Academic Works | Z97: https://academicworks.cuny.edu/context/ny_pubs/article/2248/viewcontent/Annals_of_the_New_York_Academy_of_Sciences___2024___Rajkovich___New_York_State_Climate_Impacts_Assessment_Chapter_04___1_.pdf | AA97: PDF in CUNY Academic Works | AC97: School of Technology & Design | AE97: No
A98: ARCH-0190 | B98: Aptekar | C98: Alexander | D98: Alexander Aptekar | E98: Assistant Professor | F98: NYC College of Technology | G98: Architectural Technology | H98: AAptekar@citytech.cuny.edu | I98: Conference presentation | J98: Optimizing Indoor Environment Quality | K98: 2024 | L98: Publications and Research | M98: Ahmmed, Anjum B.; Lopez, Christopher Gabriel; Garcia, Jennifer; Tapia, Marti; Antoine, Nick; Aptekar, Alexander | R98: https://academicworks.cuny.edu/ny_pubs/1223 | S98: CUNY Academic Works | T98: 1 | U98: High (in CUNY Academic Works) | X98: This research investigates an integrative approach to health in building design by focusing on material selection and its impact on indoor environmental quality (IEQ). Specifically, the study examines clay plaster through sensory evaluation methods to compare its effectiveness with conventional finishes in filtering out unpleasant odors from chemicals commonly used in indoor spaces. Key parameters such as material texture, and visual satisfaction will also be assessed. Randomly selected participants from across campus will evaluate the odor of clay plaster and paint applied to the laser-cut composite boards, reporting on each finish's ability to mask the burnt smell of charred edges and the strength of the finish. We expect that clay plaster will be perceived as the most pleasant option as it doesnât contain VOCs (harmful chemicals) and will more effectively conceal burnt odors compared to the traditional finishes. The results will provide valuable insights into the performance of various clay plaster formulations relative to conventional materials, informing future choices in sustainable building design. | Y98: CUNY Academic Works | Z98: https://academicworks.cuny.edu/context/ny_pubs/article/2252/viewcontent/INDOOR_AIR_QUAILITY_ESP_POSTER.pptx.pdf | AA98: PDF in CUNY Academic Works | AC98: School of Technology & Design | AE98: No
A99: ARCH-0197 | B99: M'Bouroukounda | C99: Elena | D99: Elena M'Bouroukounda | E99: Lecturer | F99: NYC College of Technology | G99: Architectural Technology | H99: embouroukounda@citytech.cuny.edu | I99: Journal article | J99: TECHNE 2022-2023 | K99: 2024 | L99: TECHNE | M99: MâBouroukounda, Elena; Yang, Jieun | R99: https://academicworks.cuny.edu/ny_techne/7 | S99: CUNY Academic Works | T99: 1 | U99: High (in CUNY Academic Works) | X99: In this relaunch of TECHNE, the editorial team sought to reset and reflect on the departmentâs trajectory and achievements through coursework from the 2022-2023 academic year. The publication also includes snippets of student life outside the classroom, including study abroad, student-run events, mentorships and pre-internships, and other department-wide organized events. This book is an archive of architectural stories, ideas, and experiments. We hope that TECHNE continues to capture the work of current students and recent graduates with the immediacy to meet the challenges and architectural discourse of the moment. | Y99: CUNY Academic Works | Z99: https://academicworks.cuny.edu/context/ny_techne/article/1006/viewcontent/TECHNE_2022_23_Digital_Issuu.pdf | AA99: PDF in CUNY Academic Works | AC99: School of Technology & Design | AE99: No
A100: ARCH-0198 | B100: Yang | C100: Jieun | D100: Jieun Yang | E100: Associate Professor/B.ARCH Co-Director | F100: NYC College of Technology | G100: Architectural Technology | H100: JYang@citytech.cuny.edu | I100: Journal article | J100: TECHNE 2022-2023 | K100: 2024 | L100: TECHNE | M100: MâBouroukounda, Elena; Yang, Jieun | R100: https://academicworks.cuny.edu/ny_techne/7 | S100: CUNY Academic Works | T100: 1 | U100: High (in CUNY Academic Works) | X100: In this relaunch of TECHNE, the editorial team sought to reset and reflect on the departmentâs trajectory and achievements through coursework from the 2022-2023 academic year. The publication also includes snippets of student life outside the classroom, including study abroad, student-run events, mentorships and pre-internships, and other department-wide organized events. This book is an archive of architectural stories, ideas, and experiments. We hope that TECHNE continues to capture the work of current students and recent graduates with the immediacy to meet the challenges and architectural discourse of the moment. | Y100: CUNY Academic Works | Z100: https://academicworks.cuny.edu/context/ny_techne/article/1006/viewcontent/TECHNE_2022_23_Digital_Issuu.pdf | AA100: PDF in CUNY Academic Works | AC100: School of Technology & Design | AE100: No
...

Sheet Faculty
A1: SNo | B1: LastName | C1: FirstName | D1: FullName | E1: Title | F1: College | G1: Department | H1: Email | I1: Office | J1: DirectoryProfile | K1: ORCID | L1: HasProfile | M1: TotalPubs | N1: Citations | O1: Hindex | P1: Iindex | Q1: ScholarProfile | R1: ScholarInterests | S1: ScholarCheckedOn | T1: ItemsCollected | U1: Journal article | V1: Conference paper | W1: Book | X1: Book chapter | Y1: Conference presentation | Z1: Technical report | AA1: Paper (venue type unclear) | AB1: Patent | AC1: Grant | AD1: WithDOI | AE1: FoundIn: Dept bio | AF1: FoundIn: Academic Works | AG1: FoundIn: ORCID | AH1: FoundIn: Crossref | AI1: FoundIn: NSF | AJ1: FoundIn: Google Scholar | AK1: Notes | AL1: School | AM1: Status | AN1: Preprint | AO1: Dataset | AP1: Dissertation | AQ1: Open educational resource | AR1: Other | AS1: FoundIn: OpenAlex | AT1: FoundIn: NIH | AU1: AI tier | AV1: AI items (confirmed) | AW1: Items to check
A2: 1 | B2: Almeida | C2: Nora | D2: Nora Almeida | E2: Associate Professor/Instruction, Reference | F2: NYC College of Technology | G2: Library | H2: NAlmeida@citytech.cuny.edu | I2: L-543D | J2: https://www.citytech.cuny.edu/faculty/nalmeida | L2: FALSE | T2: =COUNTIFS(Items!$H$2:$H$5547,$H2) | U2: =COUNTIFS(Items!$H$2:$H$5547,$H2,Items!$I$2:$I$5547,"Journal article") | V2: =COUNTIFS(Items!$H$2:$H$5547,$H2,Items!$I$2:$I$5547,"Conference paper") | W2: =COUNTIFS(Items!$H$2:$H$5547,$H2,Items!$I$2:$I$5547,"Book") | X2: =COUNTIFS(Items!$H$2:$H$5547,$H2,Items!$I$2:$I$5547,"Book chapter") | Y2: =COUNTIFS(Items!$H$2:$H$5547,$H2,Items!$I$2:$I$5547,"Conference presentation") | Z2: =COUNTIFS(Items!$H$2:$H$5547,$H2,Items!$I$2:$I$5547,"Technical report") | AA2: =COUNTIFS(Items!$H$2:$H$5547,$H2,Items!$I$2:$I$5547,"Paper (venue type unclear)") | AB2: =COUNTIFS(Items!$H$2:$H$5547,$H2,Items!$I$2:$I$5547,"Patent") | AC2: =COUNTIFS(Items!$H$2:$H$5547,$H2,Items!$I$2:$I$5547,"Grant") | AD2: =COUNTIFS(Items!$H$2:$H$5547,$H2,Items!$Q$2:$Q$5547,"<>") | AE2: =COUNTIFS(Items!$H$2:$H$5547,$H2,Items!$S$2:$S$5547,"*Dept bio*") | AF2: =COUNTIFS(Items!$H$2:$H$5547,$H2,Items!$S$2:$S$5547,"*CUNY Academic Works*") | AG2: =COUNTIFS(Items!$H$2:$H$5547,$H2,Items!$S$2:$S$5547,"*ORCID*") | AH2: =COUNTIFS(Items!$H$2:$H$5547,$H2,Items!$S$2:$S$5547,"*Crossref*") | AI2: =COUNTIFS(Items!$H$2:$H$5547,$H2,Items!$S$2:$S$5547,"*NSF*") | AJ2: =COUNTIFS(Items!$H$2:$H$5547,$H2,Items!$S$2:$S$5547,"*Google Scholar*") | AL2: Library | AM2: Full-time | AN2: =COUNTIFS(Items!$H$2:$H$5547,$H2,Items!$I$2:$I$5547,"Preprint") | AO2: =COUNTIFS(Items!$H$2:$H$5547,$H2,Items!$I$2:$I$5547,"Dataset") | AP2: =COUNTIFS(Items!$H$2:$H$5547,$H2,Items!$I$2:$I$5547,"Dissertation") | AQ2: =COUNTIFS(Items!$H$2:$H$5547,$H2,Items!$I$2:$I$5547,"Open educational resource") | AR2: =COUNTIFS(Items!$H$2:$H$5547,$H2,Items!$I$2:$I$5547,"Other") | AS2: =COUNTIFS(Items!$H$2:$H$5547,$H2,Items!$S$2:$S$5547,"*OpenAlex*") | AT2: =COUNTIFS(Items!$H$2:$H$5547,$H2,Items!$S$2:$S$5547,"*NIH*") | AV2: =COUNTIFS(Items!$H$2:$H$5547,$H2,Items!$AE$2:$AE$5547,"Yes") | AW2: 0
A3: 2 | B3: Berger | C3: Monica | D3: Monica Berger | E3: Professor/Instruction and Scholarly Communications Librarian | F3: NYC College of Technology | G3: Library | H3: MBerger@citytech.cuny.edu | I3: L-543A | J3: https://www.citytech.cuny.edu/faculty/mberger | L3: FALSE | T3: =COUNTIFS(Items!$H$2:$H$5547,$H3) | U3: =COUNTIFS(Items!$H$2:$H$5547,$H3,Items!$I$2:$I$5547,"Journal article") | V3: =COUNTIFS(Items!$H$2:$H$5547,$H3,Items!$I$2:$I$5547,"Conference paper") | W3: =COUNTIFS(Items!$H$2:$H$5547,$H3,Items!$I$2:$I$5547,"Book") | X3: =COUNTIFS(Items!$H$2:$H$5547,$H3,Items!$I$2:$I$5547,"Book chapter") | Y3: =COUNTIFS(Items!$H$2:$H$5547,$H3,Items!$I$2:$I$5547,"Conference presentation") | Z3: =COUNTIFS(Items!$H$2:$H$5547,$H3,Items!$I$2:$I$5547,"Technical report") | AA3: =COUNTIFS(Items!$H$2:$H$5547,$H3,Items!$I$2:$I$5547,"Paper (venue type unclear)") | AB3: =COUNTIFS(Items!$H$2:$H$5547,$H3,Items!$I$2:$I$5547,"Patent") | AC3: =COUNTIFS(Items!$H$2:$H$5547,$H3,Items!$I$2:$I$5547,"Grant") | AD3: =COUNTIFS(Items!$H$2:$H$5547,$H3,Items!$Q$2:$Q$5547,"<>") | AE3: =COUNTIFS(Items!$H$2:$H$5547,$H3,Items!$S$2:$S$5547,"*Dept bio*") | AF3: =COUNTIFS(Items!$H$2:$H$5547,$H3,Items!$S$2:$S$5547,"*CUNY Academic Works*") | AG3: =COUNTIFS(Items!$H$2:$H$5547,$H3,Items!$S$2:$S$5547,"*ORCID*") | AH3: =COUNTIFS(Items!$H$2:$H$5547,$H3,Items!$S$2:$S$5547,"*Crossref*") | AI3: =COUNTIFS(Items!$H$2:$H$5547,$H3,Items!$S$2:$S$5547,"*NSF*") | AJ3: =COUNTIFS(Items!$H$2:$H$5547,$H3,Items!$S$2:$S$5547,"*Google Scholar*") | AL3: Library | AM3: Full-time | AN3: =COUNTIFS(Items!$H$2:$H$5547,$H3,Items!$I$2:$I$5547,"Preprint") | AO3: =COUNTIFS(Items!$H$2:$H$5547,$H3,Items!$I$2:$I$5547,"Dataset") | AP3: =COUNTIFS(Items!$H$2:$H$5547,$H3,Items!$I$2:$I$5547,"Dissertation") | AQ3: =COUNTIFS(Items!$H$2:$H$5547,$H3,Items!$I$2:$I$5547,"Open educational resource") | AR3: =COUNTIFS(Items!$H$2:$H$5547,$H3,Items!$I$2:$I$5547,"Other") | AS3: =COUNTIFS(Items!$H$2:$H$5547,$H3,Items!$S$2:$S$5547,"*OpenAlex*") | AT3: =COUNTIFS(Items!$H$2:$H$5547,$H3,Items!$S$2:$S$5547,"*NIH*") | AU3: Some AI work | AV3: =COUNTIFS(Items!$H$2:$H$5547,$H3,Items!$AE$2:$AE$5547,"Yes") | AW3: 0
A4: 3 | B4: Clyde | C4: Wanett | D4: Wanett Clyde | E4: Associate Professor | F4: NYC College of Technology | G4: Library | H4: WClyde@citytech.cuny.edu | I4: L-539C | J4: https://www.citytech.cuny.edu/faculty/wclyde | L4: FALSE | T4: =COUNTIFS(Items!$H$2:$H$5547,$H4) | U4: =COUNTIFS(Items!$H$2:$H$5547,$H4,Items!$I$2:$I$5547,"Journal article") | V4: =COUNTIFS(Items!$H$2:$H$5547,$H4,Items!$I$2:$I$5547,"Conference paper") | W4: =COUNTIFS(Items!$H$2:$H$5547,$H4,Items!$I$2:$I$5547,"Book") | X4: =COUNTIFS(Items!$H$2:$H$5547,$H4,Items!$I$2:$I$5547,"Book chapter") | Y4: =COUNTIFS(Items!$H$2:$H$5547,$H4,Items!$I$2:$I$5547,"Conference presentation") | Z4: =COUNTIFS(Items!$H$2:$H$5547,$H4,Items!$I$2:$I$5547,"Technical report") | AA4: =COUNTIFS(Items!$H$2:$H$5547,$H4,Items!$I$2:$I$5547,"Paper (venue type unclear)") | AB4: =COUNTIFS(Items!$H$2:$H$5547,$H4,Items!$I$2:$I$5547,"Patent") | AC4: =COUNTIFS(Items!$H$2:$H$5547,$H4,Items!$I$2:$I$5547,"Grant") | AD4: =COUNTIFS(Items!$H$2:$H$5547,$H4,Items!$Q$2:$Q$5547,"<>") | AE4: =COUNTIFS(Items!$H$2:$H$5547,$H4,Items!$S$2:$S$5547,"*Dept bio*") | AF4: =COUNTIFS(Items!$H$2:$H$5547,$H4,Items!$S$2:$S$5547,"*CUNY Academic Works*") | AG4: =COUNTIFS(Items!$H$2:$H$5547,$H4,Items!$S$2:$S$5547,"*ORCID*") | AH4: =COUNTIFS(Items!$H$2:$H$5547,$H4,Items!$S$2:$S$5547,"*Crossref*") | AI4: =COUNTIFS(Items!$H$2:$H$5547,$H4,Items!$S$2:$S$5547,"*NSF*") | AJ4: =COUNTIFS(Items!$H$2:$H$5547,$H4,Items!$S$2:$S$5547,"*Google Scholar*") | AL4: Library | AM4: Full-time | AN4: =COUNTIFS(Items!$H$2:$H$5547,$H4,Items!$I$2:$I$5547,"Preprint") | AO4: =COUNTIFS(Items!$H$2:$H$5547,$H4,Items!$I$2:$I$5547,"Dataset") | AP4: =COUNTIFS(Items!$H$2:$H$5547,$H4,Items!$I$2:$I$5547,"Dissertation") | AQ4: =COUNTIFS(Items!$H$2:$H$5547,$H4,Items!$I$2:$I$5547,"Open educational resource") | AR4: =COUNTIFS(Items!$H$2:$H$5547,$H4,Items!$I$2:$I$5547,"Other") | AS4: =COUNTIFS(Items!$H$2:$H$5547,$H4,Items!$S$2:$S$5547,"*OpenAlex*") | AT4: =COUNTIFS(Items!$H$2:$H$5547,$H4,Items!$S$2:$S$5547,"*NIH*") | AV4: =COUNTIFS(Items!$H$2:$H$5547,$H4,Items!$AE$2:$AE$5547,"Yes") | AW4: 0
A5: 4 | B5: Cooney | C5: Cailean | D5: Cailean Cooney | E5: Associate Professor/OER Librarian | F5: NYC College of Technology | G5: Library | H5: CCooney@citytech.cuny.edu | I5: L-436 | J5: https://www.citytech.cuny.edu/faculty/ccooney | L5: FALSE | T5: =COUNTIFS(Items!$H$2:$H$5547,$H5) | U5: =COUNTIFS(Items!$H$2:$H$5547,$H5,Items!$I$2:$I$5547,"Journal article") | V5: =COUNTIFS(Items!$H$2:$H$5547,$H5,Items!$I$2:$I$5547,"Conference paper") | W5: =COUNTIFS(Items!$H$2:$H$5547,$H5,Items!$I$2:$I$5547,"Book") | X5: =COUNTIFS(Items!$H$2:$H$5547,$H5,Items!$I$2:$I$5547,"Book chapter") | Y5: =COUNTIFS(Items!$H$2:$H$5547,$H5,Items!$I$2:$I$5547,"Conference presentation") | Z5: =COUNTIFS(Items!$H$2:$H$5547,$H5,Items!$I$2:$I$5547,"Technical report") | AA5: =COUNTIFS(Items!$H$2:$H$5547,$H5,Items!$I$2:$I$5547,"Paper (venue type unclear)") | AB5: =COUNTIFS(Items!$H$2:$H$5547,$H5,Items!$I$2:$I$5547,"Patent") | AC5: =COUNTIFS(Items!$H$2:$H$5547,$H5,Items!$I$2:$I$5547,"Grant") | AD5: =COUNTIFS(Items!$H$2:$H$5547,$H5,Items!$Q$2:$Q$5547,"<>") | AE5: =COUNTIFS(Items!$H$2:$H$5547,$H5,Items!$S$2:$S$5547,"*Dept bio*") | AF5: =COUNTIFS(Items!$H$2:$H$5547,$H5,Items!$S$2:$S$5547,"*CUNY Academic Works*") | AG5: =COUNTIFS(Items!$H$2:$H$5547,$H5,Items!$S$2:$S$5547,"*ORCID*") | AH5: =COUNTIFS(Items!$H$2:$H$5547,$H5,Items!$S$2:$S$5547,"*Crossref*") | AI5: =COUNTIFS(Items!$H$2:$H$5547,$H5,Items!$S$2:$S$5547,"*NSF*") | AJ5: =COUNTIFS(Items!$H$2:$H$5547,$H5,Items!$S$2:$S$5547,"*Google Scholar*") | AL5: Library | AM5: Full-time | AN5: =COUNTIFS(Items!$H$2:$H$5547,$H5,Items!$I$2:$I$5547,"Preprint") | AO5: =COUNTIFS(Items!$H$2:$H$5547,$H5,Items!$I$2:$I$5547,"Dataset") | AP5: =COUNTIFS(Items!$H$2:$H$5547,$H5,Items!$I$2:$I$5547,"Dissertation") | AQ5: =COUNTIFS(Items!$H$2:$H$5547,$H5,Items!$I$2:$I$5547,"Open educational resource") | AR5: =COUNTIFS(Items!$H$2:$H$5547,$H5,Items!$I$2:$I$5547,"Other") | AS5: =COUNTIFS(Items!$H$2:$H$5547,$H5,Items!$S$2:$S$5547,"*OpenAlex*") | AT5: =COUNTIFS(Items!$H$2:$H$5547,$H5,Items!$S$2:$S$5547,"*NIH*") | AV5: =COUNTIFS(Items!$H$2:$H$5547,$H5,Items!$AE$2:$AE$5547,"Yes") | AW5: 0
A6: 5 | B6: Hoyer | C6: Jennifer | D6: Jennifer Hoyer | E6: Assistant Professor/Technical Services, Electronic Resources | F6: NYC College of Technology | G6: Library | H6: JHoyer@citytech.cuny.edu | I6: L-539B | J6: https://www.citytech.cuny.edu/faculty/jhoyer | L6: FALSE | T6: =COUNTIFS(Items!$H$2:$H$5547,$H6) | U6: =COUNTIFS(Items!$H$2:$H$5547,$H6,Items!$I$2:$I$5547,"Journal article") | V6: =COUNTIFS(Items!$H$2:$H$5547,$H6,Items!$I$2:$I$5547,"Conference paper") | W6: =COUNTIFS(Items!$H$2:$H$5547,$H6,Items!$I$2:$I$5547,"Book") | X6: =COUNTIFS(Items!$H$2:$H$5547,$H6,Items!$I$2:$I$5547,"Book chapter") | Y6: =COUNTIFS(Items!$H$2:$H$5547,$H6,Items!$I$2:$I$5547,"Conference presentation") | Z6: =COUNTIFS(Items!$H$2:$H$5547,$H6,Items!$I$2:$I$5547,"Technical report") | AA6: =COUNTIFS(Items!$H$2:$H$5547,$H6,Items!$I$2:$I$5547,"Paper (venue type unclear)") | AB6: =COUNTIFS(Items!$H$2:$H$5547,$H6,Items!$I$2:$I$5547,"Patent") | AC6: =COUNTIFS(Items!$H$2:$H$5547,$H6,Items!$I$2:$I$5547,"Grant") | AD6: =COUNTIFS(Items!$H$2:$H$5547,$H6,Items!$Q$2:$Q$5547,"<>") | AE6: =COUNTIFS(Items!$H$2:$H$5547,$H6,Items!$S$2:$S$5547,"*Dept bio*") | AF6: =COUNTIFS(Items!$H$2:$H$5547,$H6,Items!$S$2:$S$5547,"*CUNY Academic Works*") | AG6: =COUNTIFS(Items!$H$2:$H$5547,$H6,Items!$S$2:$S$5547,"*ORCID*") | AH6: =COUNTIFS(Items!$H$2:$H$5547,$H6,Items!$S$2:$S$5547,"*Crossref*") | AI6: =COUNTIFS(Items!$H$2:$H$5547,$H6,Items!$S$2:$S$5547,"*NSF*") | AJ6: =COUNTIFS(Items!$H$2:$H$5547,$H6,Items!$S$2:$S$5547,"*Google Scholar*") | AL6: Library | AM6: Full-time | AN6: =COUNTIFS(Items!$H$2:$H$5547,$H6,Items!$I$2:$I$5547,"Preprint") | AO6: =COUNTIFS(Items!$H$2:$H$5547,$H6,Items!$I$2:$I$5547,"Dataset") | AP6: =COUNTIFS(Items!$H$2:$H$5547,$H6,Items!$I$2:$I$5547,"Dissertation") | AQ6: =COUNTIFS(Items!$H$2:$H$5547,$H6,Items!$I$2:$I$5547,"Open educational resource") | AR6: =COUNTIFS(Items!$H$2:$H$5547,$H6,Items!$I$2:$I$5547,"Other") | AS6: =COUNTIFS(Items!$H$2:$H$5547,$H6,Items!$S$2:$S$5547,"*OpenAlex*") | AT6: =COUNTIFS(Items!$H$2:$H$5547,$H6,Items!$S$2:$S$5547,"*NIH*") | AV6: =COUNTIFS(Items!$H$2:$H$5547,$H6,Items!$AE$2:$AE$5547,"Yes") | AW6: 0
A7: 6 | B7: Karpinski | C7: Kel | D7: Kel Karpinski | E7: Associate Professor | F7: NYC College of Technology | G7: Library | H7: Kel.Karpinski26@citytech.cuny.edu | I7: L-442 | J7: https://www.citytech.cuny.edu/faculty/kel.karpinski26 | L7: FALSE | T7: =COUNTIFS(Items!$H$2:$H$5547,$H7) | U7: =COUNTIFS(Items!$H$2:$H$5547,$H7,Items!$I$2:$I$5547,"Journal article") | V7: =COUNTIFS(Items!$H$2:$H$5547,$H7,Items!$I$2:$I$5547,"Conference paper") | W7: =COUNTIFS(Items!$H$2:$H$5547,$H7,Items!$I$2:$I$5547,"Book") | X7: =COUNTIFS(Items!$H$2:$H$5547,$H7,Items!$I$2:$I$5547,"Book chapter") | Y7: =COUNTIFS(Items!$H$2:$H$5547,$H7,Items!$I$2:$I$5547,"Conference presentation") | Z7: =COUNTIFS(Items!$H$2:$H$5547,$H7,Items!$I$2:$I$5547,"Technical report") | AA7: =COUNTIFS(Items!$H$2:$H$5547,$H7,Items!$I$2:$I$5547,"Paper (venue type unclear)") | AB7: =COUNTIFS(Items!$H$2:$H$5547,$H7,Items!$I$2:$I$5547,"Patent") | AC7: =COUNTIFS(Items!$H$2:$H$5547,$H7,Items!$I$2:$I$5547,"Grant") | AD7: =COUNTIFS(Items!$H$2:$H$5547,$H7,Items!$Q$2:$Q$5547,"<>") | AE7: =COUNTIFS(Items!$H$2:$H$5547,$H7,Items!$S$2:$S$5547,"*Dept bio*") | AF7: =COUNTIFS(Items!$H$2:$H$5547,$H7,Items!$S$2:$S$5547,"*CUNY Academic Works*") | AG7: =COUNTIFS(Items!$H$2:$H$5547,$H7,Items!$S$2:$S$5547,"*ORCID*") | AH7: =COUNTIFS(Items!$H$2:$H$5547,$H7,Items!$S$2:$S$5547,"*Crossref*") | AI7: =COUNTIFS(Items!$H$2:$H$5547,$H7,Items!$S$2:$S$5547,"*NSF*") | AJ7: =COUNTIFS(Items!$H$2:$H$5547,$H7,Items!$S$2:$S$5547,"*Google Scholar*") | AL7: Library | AM7: Full-time | AN7: =COUNTIFS(Items!$H$2:$H$5547,$H7,Items!$I$2:$I$5547,"Preprint") | AO7: =COUNTIFS(Items!$H$2:$H$5547,$H7,Items!$I$2:$I$5547,"Dataset") | AP7: =COUNTIFS(Items!$H$2:$H$5547,$H7,Items!$I$2:$I$5547,"Dissertation") | AQ7: =COUNTIFS(Items!$H$2:$H$5547,$H7,Items!$I$2:$I$5547,"Open educational resource") | AR7: =COUNTIFS(Items!$H$2:$H$5547,$H7,Items!$I$2:$I$5547,"Other") | AS7: =COUNTIFS(Items!$H$2:$H$5547,$H7,Items!$S$2:$S$5547,"*OpenAlex*") | AT7: =COUNTIFS(Items!$H$2:$H$5547,$H7,Items!$S$2:$S$5547,"*NIH*") | AV7: =COUNTIFS(Items!$H$2:$H$5547,$H7,Items!$AE$2:$AE$5547,"Yes") | AW7: 0
A8: 7 | B8: Muchowski | C8: Keith | D8: Keith Muchowski | E8: Associate Professor/Reference Coordinator, Instruction | F8: NYC College of Technology | G8: Library | H8: KMuchowski@citytech.cuny.edu | I8: L-435 | J8: https://www.citytech.cuny.edu/faculty/kmuchowski | L8: FALSE | T8: =COUNTIFS(Items!$H$2:$H$5547,$H8) | U8: =COUNTIFS(Items!$H$2:$H$5547,$H8,Items!$I$2:$I$5547,"Journal article") | V8: =COUNTIFS(Items!$H$2:$H$5547,$H8,Items!$I$2:$I$5547,"Conference paper") | W8: =COUNTIFS(Items!$H$2:$H$5547,$H8,Items!$I$2:$I$5547,"Book") | X8: =COUNTIFS(Items!$H$2:$H$5547,$H8,Items!$I$2:$I$5547,"Book chapter") | Y8: =COUNTIFS(Items!$H$2:$H$5547,$H8,Items!$I$2:$I$5547,"Conference presentation") | Z8: =COUNTIFS(Items!$H$2:$H$5547,$H8,Items!$I$2:$I$5547,"Technical report") | AA8: =COUNTIFS(Items!$H$2:$H$5547,$H8,Items!$I$2:$I$5547,"Paper (venue type unclear)") | AB8: =COUNTIFS(Items!$H$2:$H$5547,$H8,Items!$I$2:$I$5547,"Patent") | AC8: =COUNTIFS(Items!$H$2:$H$5547,$H8,Items!$I$2:$I$5547,"Grant") | AD8: =COUNTIFS(Items!$H$2:$H$5547,$H8,Items!$Q$2:$Q$5547,"<>") | AE8: =COUNTIFS(Items!$H$2:$H$5547,$H8,Items!$S$2:$S$5547,"*Dept bio*") | AF8: =COUNTIFS(Items!$H$2:$H$5547,$H8,Items!$S$2:$S$5547,"*CUNY Academic Works*") | AG8: =COUNTIFS(Items!$H$2:$H$5547,$H8,Items!$S$2:$S$5547,"*ORCID*") | AH8: =COUNTIFS(Items!$H$2:$H$5547,$H8,Items!$S$2:$S$5547,"*Crossref*") | AI8: =COUNTIFS(Items!$H$2:$H$5547,$H8,Items!$S$2:$S$5547,"*NSF*") | AJ8: =COUNTIFS(Items!$H$2:$H$5547,$H8,Items!$S$2:$S$5547,"*Google Scholar*") | AL8: Library | AM8: Full-time | AN8: =COUNTIFS(Items!$H$2:$H$5547,$H8,Items!$I$2:$I$5547,"Preprint") | AO8: =COUNTIFS(Items!$H$2:$H$5547,$H8,Items!$I$2:$I$5547,"Dataset") | AP8: =COUNTIFS(Items!$H$2:$H$5547,$H8,Items!$I$2:$I$5547,"Dissertation") | AQ8: =COUNTIFS(Items!$H$2:$H$5547,$H8,Items!$I$2:$I$5547,"Open educational resource") | AR8: =COUNTIFS(Items!$H$2:$H$5547,$H8,Items!$I$2:$I$5547,"Other") | AS8: =COUNTIFS(Items!$H$2:$H$5547,$H8,Items!$S$2:$S$5547,"*OpenAlex*") | AT8: =COUNTIFS(Items!$H$2:$H$5547,$H8,Items!$S$2:$S$5547,"*NIH*") | AV8: =COUNTIFS(Items!$H$2:$H$5547,$H8,Items!$AE$2:$AE$5547,"Yes") | AW8: 0
A9: 8 | B9: Prince | C9: Nandi | D9: Nandi Prince | E9: Assistant Professor/Instruction, Reference | F9: NYC College of Technology | G9: Library | H9: NPrince@citytech.cuny.edu | I9: L-440 | J9: https://www.citytech.cuny.edu/faculty/nprince | L9: FALSE | T9: =COUNTIFS(Items!$H$2:$H$5547,$H9) | U9: =COUNTIFS(Items!$H$2:$H$5547,$H9,Items!$I$2:$I$5547,"Journal article") | V9: =COUNTIFS(Items!$H$2:$H$5547,$H9,Items!$I$2:$I$5547,"Conference paper") | W9: =COUNTIFS(Items!$H$2:$H$5547,$H9,Items!$I$2:$I$5547,"Book") | X9: =COUNTIFS(Items!$H$2:$H$5547,$H9,Items!$I$2:$I$5547,"Book chapter") | Y9: =COUNTIFS(Items!$H$2:$H$5547,$H9,Items!$I$2:$I$5547,"Conference presentation") | Z9: =COUNTIFS(Items!$H$2:$H$5547,$H9,Items!$I$2:$I$5547,"Technical report") | AA9: =COUNTIFS(Items!$H$2:$H$5547,$H9,Items!$I$2:$I$5547,"Paper (venue type unclear)") | AB9: =COUNTIFS(Items!$H$2:$H$5547,$H9,Items!$I$2:$I$5547,"Patent") | AC9: =COUNTIFS(Items!$H$2:$H$5547,$H9,Items!$I$2:$I$5547,"Grant") | AD9: =COUNTIFS(Items!$H$2:$H$5547,$H9,Items!$Q$2:$Q$5547,"<>") | AE9: =COUNTIFS(Items!$H$2:$H$5547,$H9,Items!$S$2:$S$5547,"*Dept bio*") | AF9: =COUNTIFS(Items!$H$2:$H$5547,$H9,Items!$S$2:$S$5547,"*CUNY Academic Works*") | AG9: =COUNTIFS(Items!$H$2:$H$5547,$H9,Items!$S$2:$S$5547,"*ORCID*") | AH9: =COUNTIFS(Items!$H$2:$H$5547,$H9,Items!$S$2:$S$5547,"*Crossref*") | AI9: =COUNTIFS(Items!$H$2:$H$5547,$H9,Items!$S$2:$S$5547,"*NSF*") | AJ9: =COUNTIFS(Items!$H$2:$H$5547,$H9,Items!$S$2:$S$5547,"*Google Scholar*") | AL9: Library | AM9: Full-time | AN9: =COUNTIFS(Items!$H$2:$H$5547,$H9,Items!$I$2:$I$5547,"Preprint") | AO9: =COUNTIFS(Items!$H$2:$H$5547,$H9,Items!$I$2:$I$5547,"Dataset") | AP9: =COUNTIFS(Items!$H$2:$H$5547,$H9,Items!$I$2:$I$5547,"Dissertation") | AQ9: =COUNTIFS(Items!$H$2:$H$5547,$H9,Items!$I$2:$I$5547,"Open educational resource") | AR9: =COUNTIFS(Items!$H$2:$H$5547,$H9,Items!$I$2:$I$5547,"Other") | AS9: =COUNTIFS(Items!$H$2:$H$5547,$H9,Items!$S$2:$S$5547,"*OpenAlex*") | AT9: =COUNTIFS(Items!$H$2:$H$5547,$H9,Items!$S$2:$S$5547,"*NIH*") | AV9: =COUNTIFS(Items!$H$2:$H$5547,$H9,Items!$AE$2:$AE$5547,"Yes") | AW9: 0
A10: 9 | B10: Rockenbach | C10: Ashley | D10: Ashley Rockenbach | E10: Assistant Professor | F10: NYC College of Technology | G10: Library | H10: AshleyRockenbach95@citytech.cuny.edu | J10: https://www.citytech.cuny.edu/faculty/ashleyrockenbach95 | L10: FALSE | T10: =COUNTIFS(Items!$H$2:$H$5547,$H10) | U10: =COUNTIFS(Items!$H$2:$H$5547,$H10,Items!$I$2:$I$5547,"Journal article") | V10: =COUNTIFS(Items!$H$2:$H$5547,$H10,Items!$I$2:$I$5547,"Conference paper") | W10: =COUNTIFS(Items!$H$2:$H$5547,$H10,Items!$I$2:$I$5547,"Book") | X10: =COUNTIFS(Items!$H$2:$H$5547,$H10,Items!$I$2:$I$5547,"Book chapter") | Y10: =COUNTIFS(Items!$H$2:$H$5547,$H10,Items!$I$2:$I$5547,"Conference presentation") | Z10: =COUNTIFS(Items!$H$2:$H$5547,$H10,Items!$I$2:$I$5547,"Technical report") | AA10: =COUNTIFS(Items!$H$2:$H$5547,$H10,Items!$I$2:$I$5547,"Paper (venue type unclear)") | AB10: =COUNTIFS(Items!$H$2:$H$5547,$H10,Items!$I$2:$I$5547,"Patent") | AC10: =COUNTIFS(Items!$H$2:$H$5547,$H10,Items!$I$2:$I$5547,"Grant") | AD10: =COUNTIFS(Items!$H$2:$H$5547,$H10,Items!$Q$2:$Q$5547,"<>") | AE10: =COUNTIFS(Items!$H$2:$H$5547,$H10,Items!$S$2:$S$5547,"*Dept bio*") | AF10: =COUNTIFS(Items!$H$2:$H$5547,$H10,Items!$S$2:$S$5547,"*CUNY Academic Works*") | AG10: =COUNTIFS(Items!$H$2:$H$5547,$H10,Items!$S$2:$S$5547,"*ORCID*") | AH10: =COUNTIFS(Items!$H$2:$H$5547,$H10,Items!$S$2:$S$5547,"*Crossref*") | AI10: =COUNTIFS(Items!$H$2:$H$5547,$H10,Items!$S$2:$S$5547,"*NSF*") | AJ10: =COUNTIFS(Items!$H$2:$H$5547,$H10,Items!$S$2:$S$5547,"*Google Scholar*") | AL10: Library | AM10: Full-time | AN10: =COUNTIFS(Items!$H$2:$H$5547,$H10,Items!$I$2:$I$5547,"Preprint") | AO10: =COUNTIFS(Items!$H$2:$H$5547,$H10,Items!$I$2:$I$5547,"Dataset") | AP10: =COUNTIFS(Items!$H$2:$H$5547,$H10,Items!$I$2:$I$5547,"Dissertation") | AQ10: =COUNTIFS(Items!$H$2:$H$5547,$H10,Items!$I$2:$I$5547,"Open educational resource") | AR10: =COUNTIFS(Items!$H$2:$H$5547,$H10,Items!$I$2:$I$5547,"Other") | AS10: =COUNTIFS(Items!$H$2:$H$5547,$H10,Items!$S$2:$S$5547,"*OpenAlex*") | AT10: =COUNTIFS(Items!$H$2:$H$5547,$H10,Items!$S$2:$S$5547,"*NIH*") | AV10: =COUNTIFS(Items!$H$2:$H$5547,$H10,Items!$AE$2:$AE$5547,"Yes") | AW10: 0
A11: 10 | B11: Tidal, Jr | C11: Abubakar | D11: Abubakar Tidal, Jr | E11: Chief Librarian and Department Chair | F11: NYC College of Technology | G11: Library | H11: JTidal@citytech.cuny.edu | I11: L-544 | J11: https://www.citytech.cuny.edu/faculty/jtidal | L11: FALSE | T11: =COUNTIFS(Items!$H$2:$H$5547,$H11) | U11: =COUNTIFS(Items!$H$2:$H$5547,$H11,Items!$I$2:$I$5547,"Journal article") | V11: =COUNTIFS(Items!$H$2:$H$5547,$H11,Items!$I$2:$I$5547,"Conference paper") | W11: =COUNTIFS(Items!$H$2:$H$5547,$H11,Items!$I$2:$I$5547,"Book") | X11: =COUNTIFS(Items!$H$2:$H$5547,$H11,Items!$I$2:$I$5547,"Book chapter") | Y11: =COUNTIFS(Items!$H$2:$H$5547,$H11,Items!$I$2:$I$5547,"Conference presentation") | Z11: =COUNTIFS(Items!$H$2:$H$5547,$H11,Items!$I$2:$I$5547,"Technical report") | AA11: =COUNTIFS(Items!$H$2:$H$5547,$H11,Items!$I$2:$I$5547,"Paper (venue type unclear)") | AB11: =COUNTIFS(Items!$H$2:$H$5547,$H11,Items!$I$2:$I$5547,"Patent") | AC11: =COUNTIFS(Items!$H$2:$H$5547,$H11,Items!$I$2:$I$5547,"Grant") | AD11: =COUNTIFS(Items!$H$2:$H$5547,$H11,Items!$Q$2:$Q$5547,"<>") | AE11: =COUNTIFS(Items!$H$2:$H$5547,$H11,Items!$S$2:$S$5547,"*Dept bio*") | AF11: =COUNTIFS(Items!$H$2:$H$5547,$H11,Items!$S$2:$S$5547,"*CUNY Academic Works*") | AG11: =COUNTIFS(Items!$H$2:$H$5547,$H11,Items!$S$2:$S$5547,"*ORCID*") | AH11: =COUNTIFS(Items!$H$2:$H$5547,$H11,Items!$S$2:$S$5547,"*Crossref*") | AI11: =COUNTIFS(Items!$H$2:$H$5547,$H11,Items!$S$2:$S$5547,"*NSF*") | AJ11: =COUNTIFS(Items!$H$2:$H$5547,$H11,Items!$S$2:$S$5547,"*Google Scholar*") | AL11: Library | AM11: Full-time | AN11: =COUNTIFS(Items!$H$2:$H$5547,$H11,Items!$I$2:$I$5547,"Preprint") | AO11: =COUNTIFS(Items!$H$2:$H$5547,$H11,Items!$I$2:$I$5547,"Dataset") | AP11: =COUNTIFS(Items!$H$2:$H$5547,$H11,Items!$I$2:$I$5547,"Dissertation") | AQ11: =COUNTIFS(Items!$H$2:$H$5547,$H11,Items!$I$2:$I$5547,"Open educational resource") | AR11: =COUNTIFS(Items!$H$2:$H$5547,$H11,Items!$I$2:$I$5547,"Other") | AS11: =COUNTIFS(Items!$H$2:$H$5547,$H11,Items!$S$2:$S$5547,"*OpenAlex*") | AT11: =COUNTIFS(Items!$H$2:$H$5547,$H11,Items!$S$2:$S$5547,"*NIH*") | AV11: =COUNTIFS(Items!$H$2:$H$5547,$H11,Items!$AE$2:$AE$5547,"Yes") | AW11: 0
A12: 11 | B12: Bennett | C12: Dionne | D12: Dionne Bennett | E12: Assistant Professor | F12: NYC College of Technology | G12: African American Studies | H12: dionne.bennett14@citytech.cuny.edu | I12: L-643 | J12: https://www.citytech.cuny.edu/faculty/dionne.bennett14 | L12: FALSE | T12: =COUNTIFS(Items!$H$2:$H$5547,$H12) | U12: =COUNTIFS(Items!$H$2:$H$5547,$H12,Items!$I$2:$I$5547,"Journal article") | V12: =COUNTIFS(Items!$H$2:$H$5547,$H12,Items!$I$2:$I$5547,"Conference paper") | W12: =COUNTIFS(Items!$H$2:$H$5547,$H12,Items!$I$2:$I$5547,"Book") | X12: =COUNTIFS(Items!$H$2:$H$5547,$H12,Items!$I$2:$I$5547,"Book chapter") | Y12: =COUNTIFS(Items!$H$2:$H$5547,$H12,Items!$I$2:$I$5547,"Conference presentation") | Z12: =COUNTIFS(Items!$H$2:$H$5547,$H12,Items!$I$2:$I$5547,"Technical report") | AA12: =COUNTIFS(Items!$H$2:$H$5547,$H12,Items!$I$2:$I$5547,"Paper (venue type unclear)") | AB12: =COUNTIFS(Items!$H$2:$H$5547,$H12,Items!$I$2:$I$5547,"Patent") | AC12: =COUNTIFS(Items!$H$2:$H$5547,$H12,Items!$I$2:$I$5547,"Grant") | AD12: =COUNTIFS(Items!$H$2:$H$5547,$H12,Items!$Q$2:$Q$5547,"<>") | AE12: =COUNTIFS(Items!$H$2:$H$5547,$H12,Items!$S$2:$S$5547,"*Dept bio*") | AF12: =COUNTIFS(Items!$H$2:$H$5547,$H12,Items!$S$2:$S$5547,"*CUNY Academic Works*") | AG12: =COUNTIFS(Items!$H$2:$H$5547,$H12,Items!$S$2:$S$5547,"*ORCID*") | AH12: =COUNTIFS(Items!$H$2:$H$5547,$H12,Items!$S$2:$S$5547,"*Crossref*") | AI12: =COUNTIFS(Items!$H$2:$H$5547,$H12,Items!$S$2:$S$5547,"*NSF*") | AJ12: =COUNTIFS(Items!$H$2:$H$5547,$H12,Items!$S$2:$S$5547,"*Google Scholar*") | AL12: School of Arts & Sciences | AM12: Full-time | AN12: =COUNTIFS(Items!$H$2:$H$5547,$H12,Items!$I$2:$I$5547,"Preprint") | AO12: =COUNTIFS(Items!$H$2:$H$5547,$H12,Items!$I$2:$I$5547,"Dataset") | AP12: =COUNTIFS(Items!$H$2:$H$5547,$H12,Items!$I$2:$I$5547,"Dissertation") | AQ12: =COUNTIFS(Items!$H$2:$H$5547,$H12,Items!$I$2:$I$5547,"Open educational resource") | AR12: =COUNTIFS(Items!$H$2:$H$5547,$H12,Items!$I$2:$I$5547,"Other") | AS12: =COUNTIFS(Items!$H$2:$H$5547,$H12,Items!$S$2:$S$5547,"*OpenAlex*") | AT12: =COUNTIFS(Items!$H$2:$H$5547,$H12,Items!$S$2:$S$5547,"*NIH*") | AV12: =COUNTIFS(Items!$H$2:$H$5547,$H12,Items!$AE$2:$AE$5547,"Yes") | AW12: 0
A13: 12 | B13: Biswas | C13: Debarati | D13: Debarati Biswas | E13: Assistant Professor | F13: NYC College of Technology | G13: African American Studies | H13: debarati.biswas57@citytech.cuny.edu | J13: https://www.citytech.cuny.edu/faculty/debarati.biswas57 | L13: FALSE | T13: =COUNTIFS(Items!$H$2:$H$5547,$H13) | U13: =COUNTIFS(Items!$H$2:$H$5547,$H13,Items!$I$2:$I$5547,"Journal article") | V13: =COUNTIFS(Items!$H$2:$H$5547,$H13,Items!$I$2:$I$5547,"Conference paper") | W13: =COUNTIFS(Items!$H$2:$H$5547,$H13,Items!$I$2:$I$5547,"Book") | X13: =COUNTIFS(Items!$H$2:$H$5547,$H13,Items!$I$2:$I$5547,"Book chapter") | Y13: =COUNTIFS(Items!$H$2:$H$5547,$H13,Items!$I$2:$I$5547,"Conference presentation") | Z13: =COUNTIFS(Items!$H$2:$H$5547,$H13,Items!$I$2:$I$5547,"Technical report") | AA13: =COUNTIFS(Items!$H$2:$H$5547,$H13,Items!$I$2:$I$5547,"Paper (venue type unclear)") | AB13: =COUNTIFS(Items!$H$2:$H$5547,$H13,Items!$I$2:$I$5547,"Patent") | AC13: =COUNTIFS(Items!$H$2:$H$5547,$H13,Items!$I$2:$I$5547,"Grant") | AD13: =COUNTIFS(Items!$H$2:$H$5547,$H13,Items!$Q$2:$Q$5547,"<>") | AE13: =COUNTIFS(Items!$H$2:$H$5547,$H13,Items!$S$2:$S$5547,"*Dept bio*") | AF13: =COUNTIFS(Items!$H$2:$H$5547,$H13,Items!$S$2:$S$5547,"*CUNY Academic Works*") | AG13: =COUNTIFS(Items!$H$2:$H$5547,$H13,Items!$S$2:$S$5547,"*ORCID*") | AH13: =COUNTIFS(Items!$H$2:$H$5547,$H13,Items!$S$2:$S$5547,"*Crossref*") | AI13: =COUNTIFS(Items!$H$2:$H$5547,$H13,Items!$S$2:$S$5547,"*NSF*") | AJ13: =COUNTIFS(Items!$H$2:$H$5547,$H13,Items!$S$2:$S$5547,"*Google Scholar*") | AL13: School of Arts & Sciences | AM13: Full-time | AN13: =COUNTIFS(Items!$H$2:$H$5547,$H13,Items!$I$2:$I$5547,"Preprint") | AO13: =COUNTIFS(Items!$H$2:$H$5547,$H13,Items!$I$2:$I$5547,"Dataset") | AP13: =COUNTIFS(Items!$H$2:$H$5547,$H13,Items!$I$2:$I$5547,"Dissertation") | AQ13: =COUNTIFS(Items!$H$2:$H$5547,$H13,Items!$I$2:$I$5547,"Open educational resource") | AR13: =COUNTIFS(Items!$H$2:$H$5547,$H13,Items!$I$2:$I$5547,"Other") | AS13: =COUNTIFS(Items!$H$2:$H$5547,$H13,Items!$S$2:$S$5547,"*OpenAlex*") | AT13: =COUNTIFS(Items!$H$2:$H$5547,$H13,Items!$S$2:$S$5547,"*NIH*") | AV13: =COUNTIFS(Items!$H$2:$H$5547,$H13,Items!$AE$2:$AE$5547,"Yes") | AW13: 0
A14: 13 | B14: Botchway | C14: Karl | D14: Karl Botchway | E14: Associate Professor | F14: NYC College of Technology | G14: African American Studies | H14: karl.botchway07@citytech.cuny.edu | J14: https://www.citytech.cuny.edu/faculty/karl.botchway07 | L14: FALSE | T14: =COUNTIFS(Items!$H$2:$H$5547,$H14) | U14: =COUNTIFS(Items!$H$2:$H$5547,$H14,Items!$I$2:$I$5547,"Journal article") | V14: =COUNTIFS(Items!$H$2:$H$5547,$H14,Items!$I$2:$I$5547,"Conference paper") | W14: =COUNTIFS(Items!$H$2:$H$5547,$H14,Items!$I$2:$I$5547,"Book") | X14: =COUNTIFS(Items!$H$2:$H$5547,$H14,Items!$I$2:$I$5547,"Book chapter") | Y14: =COUNTIFS(Items!$H$2:$H$5547,$H14,Items!$I$2:$I$5547,"Conference presentation") | Z14: =COUNTIFS(Items!$H$2:$H$5547,$H14,Items!$I$2:$I$5547,"Technical report") | AA14: =COUNTIFS(Items!$H$2:$H$5547,$H14,Items!$I$2:$I$5547,"Paper (venue type unclear)") | AB14: =COUNTIFS(Items!$H$2:$H$5547,$H14,Items!$I$2:$I$5547,"Patent") | AC14: =COUNTIFS(Items!$H$2:$H$5547,$H14,Items!$I$2:$I$5547,"Grant") | AD14: =COUNTIFS(Items!$H$2:$H$5547,$H14,Items!$Q$2:$Q$5547,"<>") | AE14: =COUNTIFS(Items!$H$2:$H$5547,$H14,Items!$S$2:$S$5547,"*Dept bio*") | AF14: =COUNTIFS(Items!$H$2:$H$5547,$H14,Items!$S$2:$S$5547,"*CUNY Academic Works*") | AG14: =COUNTIFS(Items!$H$2:$H$5547,$H14,Items!$S$2:$S$5547,"*ORCID*") | AH14: =COUNTIFS(Items!$H$2:$H$5547,$H14,Items!$S$2:$S$5547,"*Crossref*") | AI14: =COUNTIFS(Items!$H$2:$H$5547,$H14,Items!$S$2:$S$5547,"*NSF*") | AJ14: =COUNTIFS(Items!$H$2:$H$5547,$H14,Items!$S$2:$S$5547,"*Google Scholar*") | AL14: School of Arts & Sciences | AM14: Full-time | AN14: =COUNTIFS(Items!$H$2:$H$5547,$H14,Items!$I$2:$I$5547,"Preprint") | AO14: =COUNTIFS(Items!$H$2:$H$5547,$H14,Items!$I$2:$I$5547,"Dataset") | AP14: =COUNTIFS(Items!$H$2:$H$5547,$H14,Items!$I$2:$I$5547,"Dissertation") | AQ14: =COUNTIFS(Items!$H$2:$H$5547,$H14,Items!$I$2:$I$5547,"Open educational resource") | AR14: =COUNTIFS(Items!$H$2:$H$5547,$H14,Items!$I$2:$I$5547,"Other") | AS14: =COUNTIFS(Items!$H$2:$H$5547,$H14,Items!$S$2:$S$5547,"*OpenAlex*") | AT14: =COUNTIFS(Items!$H$2:$H$5547,$H14,Items!$S$2:$S$5547,"*NIH*") | AV14: =COUNTIFS(Items!$H$2:$H$5547,$H14,Items!$AE$2:$AE$5547,"Yes") | AW14: 0
A15: 14 | B15: Effinger-Crichlow | C15: Marta | D15: Marta Effinger-Crichlow | E15: Professor | F15: NYC College of Technology | G15: African American Studies | H15: marta.effinger-crichlow45@citytech.cuny.edu | I15: L-643 | J15: https://www.citytech.cuny.edu/faculty/marta.effinger-crichlow45 | L15: FALSE | T15: =COUNTIFS(Items!$H$2:$H$5547,$H15) | U15: =COUNTIFS(Items!$H$2:$H$5547,$H15,Items!$I$2:$I$5547,"Journal article") | V15: =COUNTIFS(Items!$H$2:$H$5547,$H15,Items!$I$2:$I$5547,"Conference paper") | W15: =COUNTIFS(Items!$H$2:$H$5547,$H15,Items!$I$2:$I$5547,"Book") | X15: =COUNTIFS(Items!$H$2:$H$5547,$H15,Items!$I$2:$I$5547,"Book chapter") | Y15: =COUNTIFS(Items!$H$2:$H$5547,$H15,Items!$I$2:$I$5547,"Conference presentation") | Z15: =COUNTIFS(Items!$H$2:$H$5547,$H15,Items!$I$2:$I$5547,"Technical report") | AA15: =COUNTIFS(Items!$H$2:$H$5547,$H15,Items!$I$2:$I$5547,"Paper (venue type unclear)") | AB15: =COUNTIFS(Items!$H$2:$H$5547,$H15,Items!$I$2:$I$5547,"Patent") | AC15: =COUNTIFS(Items!$H$2:$H$5547,$H15,Items!$I$2:$I$5547,"Grant") | AD15: =COUNTIFS(Items!$H$2:$H$5547,$H15,Items!$Q$2:$Q$5547,"<>") | AE15: =COUNTIFS(Items!$H$2:$H$5547,$H15,Items!$S$2:$S$5547,"*Dept bio*") | AF15: =COUNTIFS(Items!$H$2:$H$5547,$H15,Items!$S$2:$S$5547,"*CUNY Academic Works*") | AG15: =COUNTIFS(Items!$H$2:$H$5547,$H15,Items!$S$2:$S$5547,"*ORCID*") | AH15: =COUNTIFS(Items!$H$2:$H$5547,$H15,Items!$S$2:$S$5547,"*Crossref*") | AI15: =COUNTIFS(Items!$H$2:$H$5547,$H15,Items!$S$2:$S$5547,"*NSF*") | AJ15: =COUNTIFS(Items!$H$2:$H$5547,$H15,Items!$S$2:$S$5547,"*Google Scholar*") | AL15: School of Arts & Sciences | AM15: Full-time | AN15: =COUNTIFS(Items!$H$2:$H$5547,$H15,Items!$I$2:$I$5547,"Preprint") | AO15: =COUNTIFS(Items!$H$2:$H$5547,$H15,Items!$I$2:$I$5547,"Dataset") | AP15: =COUNTIFS(Items!$H$2:$H$5547,$H15,Items!$I$2:$I$5547,"Dissertation") | AQ15: =COUNTIFS(Items!$H$2:$H$5547,$H15,Items!$I$2:$I$5547,"Open educational resource") | AR15: =COUNTIFS(Items!$H$2:$H$5547,$H15,Items!$I$2:$I$5547,"Other") | AS15: =COUNTIFS(Items!$H$2:$H$5547,$H15,Items!$S$2:$S$5547,"*OpenAlex*") | AT15: =COUNTIFS(Items!$H$2:$H$5547,$H15,Items!$S$2:$S$5547,"*NIH*") | AV15: =COUNTIFS(Items!$H$2:$H$5547,$H15,Items!$AE$2:$AE$5547,"Yes") | AW15: 0
A16: 15 | B16: Evangelista | C16: Javiela | D16: Javiela Evangelista | E16: Associate Professor | F16: NYC College of Technology | G16: African American Studies | H16: javiela.evangelista75@citytech.cuny.edu | I16: L-643 | J16: https://www.citytech.cuny.edu/faculty/javiela.evangelista75 | L16: FALSE | T16: =COUNTIFS(Items!$H$2:$H$5547,$H16) | U16: =COUNTIFS(Items!$H$2:$H$5547,$H16,Items!$I$2:$I$5547,"Journal article") | V16: =COUNTIFS(Items!$H$2:$H$5547,$H16,Items!$I$2:$I$5547,"Conference paper") | W16: =COUNTIFS(Items!$H$2:$H$5547,$H16,Items!$I$2:$I$5547,"Book") | X16: =COUNTIFS(Items!$H$2:$H$5547,$H16,Items!$I$2:$I$5547,"Book chapter") | Y16: =COUNTIFS(Items!$H$2:$H$5547,$H16,Items!$I$2:$I$5547,"Conference presentation") | Z16: =COUNTIFS(Items!$H$2:$H$5547,$H16,Items!$I$2:$I$5547,"Technical report") | AA16: =COUNTIFS(Items!$H$2:$H$5547,$H16,Items!$I$2:$I$5547,"Paper (venue type unclear)") | AB16: =COUNTIFS(Items!$H$2:$H$5547,$H16,Items!$I$2:$I$5547,"Patent") | AC16: =COUNTIFS(Items!$H$2:$H$5547,$H16,Items!$I$2:$I$5547,"Grant") | AD16: =COUNTIFS(Items!$H$2:$H$5547,$H16,Items!$Q$2:$Q$5547,"<>") | AE16: =COUNTIFS(Items!$H$2:$H$5547,$H16,Items!$S$2:$S$5547,"*Dept bio*") | AF16: =COUNTIFS(Items!$H$2:$H$5547,$H16,Items!$S$2:$S$5547,"*CUNY Academic Works*") | AG16: =COUNTIFS(Items!$H$2:$H$5547,$H16,Items!$S$2:$S$5547,"*ORCID*") | AH16: =COUNTIFS(Items!$H$2:$H$5547,$H16,Items!$S$2:$S$5547,"*Crossref*") | AI16: =COUNTIFS(Items!$H$2:$H$5547,$H16,Items!$S$2:$S$5547,"*NSF*") | AJ16: =COUNTIFS(Items!$H$2:$H$5547,$H16,Items!$S$2:$S$5547,"*Google Scholar*") | AL16: School of Arts & Sciences | AM16: Full-time | AN16: =COUNTIFS(Items!$H$2:$H$5547,$H16,Items!$I$2:$I$5547,"Preprint") | AO16: =COUNTIFS(Items!$H$2:$H$5547,$H16,Items!$I$2:$I$5547,"Dataset") | AP16: =COUNTIFS(Items!$H$2:$H$5547,$H16,Items!$I$2:$I$5547,"Dissertation") | AQ16: =COUNTIFS(Items!$H$2:$H$5547,$H16,Items!$I$2:$I$5547,"Open educational resource") | AR16: =COUNTIFS(Items!$H$2:$H$5547,$H16,Items!$I$2:$I$5547,"Other") | AS16: =COUNTIFS(Items!$H$2:$H$5547,$H16,Items!$S$2:$S$5547,"*OpenAlex*") | AT16: =COUNTIFS(Items!$H$2:$H$5547,$H16,Items!$S$2:$S$5547,"*NIH*") | AV16: =COUNTIFS(Items!$H$2:$H$5547,$H16,Items!$AE$2:$AE$5547,"Yes") | AW16: 0
A17: 16 | B17: Ferdinand | C17: Renata | D17: Renata Ferdinand | E17: Chair | F17: NYC College of Technology | G17: African American Studies | H17: Renata.Ferdinand92@citytech.cuny.edu | I17: L-634 | J17: https://www.citytech.cuny.edu/faculty/renata.ferdinand92 | L17: FALSE | T17: =COUNTIFS(Items!$H$2:$H$5547,$H17) | U17: =COUNTIFS(Items!$H$2:$H$5547,$H17,Items!$I$2:$I$5547,"Journal article") | V17: =COUNTIFS(Items!$H$2:$H$5547,$H17,Items!$I$2:$I$5547,"Conference paper") | W17: =COUNTIFS(Items!$H$2:$H$5547,$H17,Items!$I$2:$I$5547,"Book") | X17: =COUNTIFS(Items!$H$2:$H$5547,$H17,Items!$I$2:$I$5547,"Book chapter") | Y17: =COUNTIFS(Items!$H$2:$H$5547,$H17,Items!$I$2:$I$5547,"Conference presentation") | Z17: =COUNTIFS(Items!$H$2:$H$5547,$H17,Items!$I$2:$I$5547,"Technical report") | AA17: =COUNTIFS(Items!$H$2:$H$5547,$H17,Items!$I$2:$I$5547,"Paper (venue type unclear)") | AB17: =COUNTIFS(Items!$H$2:$H$5547,$H17,Items!$I$2:$I$5547,"Patent") | AC17: =COUNTIFS(Items!$H$2:$H$5547,$H17,Items!$I$2:$I$5547,"Grant") | AD17: =COUNTIFS(Items!$H$2:$H$5547,$H17,Items!$Q$2:$Q$5547,"<>") | AE17: =COUNTIFS(Items!$H$2:$H$5547,$H17,Items!$S$2:$S$5547,"*Dept bio*") | AF17: =COUNTIFS(Items!$H$2:$H$5547,$H17,Items!$S$2:$S$5547,"*CUNY Academic Works*") | AG17: =COUNTIFS(Items!$H$2:$H$5547,$H17,Items!$S$2:$S$5547,"*ORCID*") | AH17: =COUNTIFS(Items!$H$2:$H$5547,$H17,Items!$S$2:$S$5547,"*Crossref*") | AI17: =COUNTIFS(Items!$H$2:$H$5547,$H17,Items!$S$2:$S$5547,"*NSF*") | AJ17: =COUNTIFS(Items!$H$2:$H$5547,$H17,Items!$S$2:$S$5547,"*Google Scholar*") | AL17: School of Arts & Sciences | AM17: Full-time | AN17: =COUNTIFS(Items!$H$2:$H$5547,$H17,Items!$I$2:$I$5547,"Preprint") | AO17: =COUNTIFS(Items!$H$2:$H$5547,$H17,Items!$I$2:$I$5547,"Dataset") | AP17: =COUNTIFS(Items!$H$2:$H$5547,$H17,Items!$I$2:$I$5547,"Dissertation") | AQ17: =COUNTIFS(Items!$H$2:$H$5547,$H17,Items!$I$2:$I$5547,"Open educational resource") | AR17: =COUNTIFS(Items!$H$2:$H$5547,$H17,Items!$I$2:$I$5547,"Other") | AS17: =COUNTIFS(Items!$H$2:$H$5547,$H17,Items!$S$2:$S$5547,"*OpenAlex*") | AT17: =COUNTIFS(Items!$H$2:$H$5547,$H17,Items!$S$2:$S$5547,"*NIH*") | AV17: =COUNTIFS(Items!$H$2:$H$5547,$H17,Items!$AE$2:$AE$5547,"Yes") | AW17: 0
A18: 17 | B18: Abo-Ali | C18: Ehab | D18: Ehab Abo-Ali | E18: Lecturer - Doctoral Schedule | F18: NYC College of Technology | G18: Biological Sciences | H18: EAboAli@citytech.cuny.edu | J18: https://www.citytech.cuny.edu/faculty/eaboali | L18: FALSE | T18: =COUNTIFS(Items!$H$2:$H$5547,$H18) | U18: =COUNTIFS(Items!$H$2:$H$5547,$H18,Items!$I$2:$I$5547,"Journal article") | V18: =COUNTIFS(Items!$H$2:$H$5547,$H18,Items!$I$2:$I$5547,"Conference paper") | W18: =COUNTIFS(Items!$H$2:$H$5547,$H18,Items!$I$2:$I$5547,"Book") | X18: =COUNTIFS(Items!$H$2:$H$5547,$H18,Items!$I$2:$I$5547,"Book chapter") | Y18: =COUNTIFS(Items!$H$2:$H$5547,$H18,Items!$I$2:$I$5547,"Conference presentation") | Z18: =COUNTIFS(Items!$H$2:$H$5547,$H18,Items!$I$2:$I$5547,"Technical report") | AA18: =COUNTIFS(Items!$H$2:$H$5547,$H18,Items!$I$2:$I$5547,"Paper (venue type unclear)") | AB18: =COUNTIFS(Items!$H$2:$H$5547,$H18,Items!$I$2:$I$5547,"Patent") | AC18: =COUNTIFS(Items!$H$2:$H$5547,$H18,Items!$I$2:$I$5547,"Grant") | AD18: =COUNTIFS(Items!$H$2:$H$5547,$H18,Items!$Q$2:$Q$5547,"<>") | AE18: =COUNTIFS(Items!$H$2:$H$5547,$H18,Items!$S$2:$S$5547,"*Dept bio*") | AF18: =COUNTIFS(Items!$H$2:$H$5547,$H18,Items!$S$2:$S$5547,"*CUNY Academic Works*") | AG18: =COUNTIFS(Items!$H$2:$H$5547,$H18,Items!$S$2:$S$5547,"*ORCID*") | AH18: =COUNTIFS(Items!$H$2:$H$5547,$H18,Items!$S$2:$S$5547,"*Crossref*") | AI18: =COUNTIFS(Items!$H$2:$H$5547,$H18,Items!$S$2:$S$5547,"*NSF*") | AJ18: =COUNTIFS(Items!$H$2:$H$5547,$H18,Items!$S$2:$S$5547,"*Google Scholar*") | AL18: School of Arts & Sciences | AM18: Full-time | AN18: =COUNTIFS(Items!$H$2:$H$5547,$H18,Items!$I$2:$I$5547,"Preprint") | AO18: =COUNTIFS(Items!$H$2:$H$5547,$H18,Items!$I$2:$I$5547,"Dataset") | AP18: =COUNTIFS(Items!$H$2:$H$5547,$H18,Items!$I$2:$I$5547,"Dissertation") | AQ18: =COUNTIFS(Items!$H$2:$H$5547,$H18,Items!$I$2:$I$5547,"Open educational resource") | AR18: =COUNTIFS(Items!$H$2:$H$5547,$H18,Items!$I$2:$I$5547,"Other") | AS18: =COUNTIFS(Items!$H$2:$H$5547,$H18,Items!$S$2:$S$5547,"*OpenAlex*") | AT18: =COUNTIFS(Items!$H$2:$H$5547,$H18,Items!$S$2:$S$5547,"*NIH*") | AV18: =COUNTIFS(Items!$H$2:$H$5547,$H18,Items!$AE$2:$AE$5547,"Yes") | AW18: 0
A19: 18 | B19: Alcendor | C19: Ralph | D19: Ralph Alcendor | E19: Assistant Professor | F19: NYC College of Technology | G19: Biological Sciences | H19: RAlcendor@citytech.cuny.edu | I19: A-302 | J19: https://www.citytech.cuny.edu/faculty/ralcendor | L19: FALSE | T19: =COUNTIFS(Items!$H$2:$H$5547,$H19) | U19: =COUNTIFS(Items!$H$2:$H$5547,$H19,Items!$I$2:$I$5547,"Journal article") | V19: =COUNTIFS(Items!$H$2:$H$5547,$H19,Items!$I$2:$I$5547,"Conference paper") | W19: =COUNTIFS(Items!$H$2:$H$5547,$H19,Items!$I$2:$I$5547,"Book") | X19: =COUNTIFS(Items!$H$2:$H$5547,$H19,Items!$I$2:$I$5547,"Book chapter") | Y19: =COUNTIFS(Items!$H$2:$H$5547,$H19,Items!$I$2:$I$5547,"Conference presentation") | Z19: =COUNTIFS(Items!$H$2:$H$5547,$H19,Items!$I$2:$I$5547,"Technical report") | AA19: =COUNTIFS(Items!$H$2:$H$5547,$H19,Items!$I$2:$I$5547,"Paper (venue type unclear)") | AB19: =COUNTIFS(Items!$H$2:$H$5547,$H19,Items!$I$2:$I$5547,"Patent") | AC19: =COUNTIFS(Items!$H$2:$H$5547,$H19,Items!$I$2:$I$5547,"Grant") | AD19: =COUNTIFS(Items!$H$2:$H$5547,$H19,Items!$Q$2:$Q$5547,"<>") | AE19: =COUNTIFS(Items!$H$2:$H$5547,$H19,Items!$S$2:$S$5547,"*Dept bio*") | AF19: =COUNTIFS(Items!$H$2:$H$5547,$H19,Items!$S$2:$S$5547,"*CUNY Academic Works*") | AG19: =COUNTIFS(Items!$H$2:$H$5547,$H19,Items!$S$2:$S$5547,"*ORCID*") | AH19: =COUNTIFS(Items!$H$2:$H$5547,$H19,Items!$S$2:$S$5547,"*Crossref*") | AI19: =COUNTIFS(Items!$H$2:$H$5547,$H19,Items!$S$2:$S$5547,"*NSF*") | AJ19: =COUNTIFS(Items!$H$2:$H$5547,$H19,Items!$S$2:$S$5547,"*Google Scholar*") | AL19: School of Arts & Sciences | AM19: Full-time | AN19: =COUNTIFS(Items!$H$2:$H$5547,$H19,Items!$I$2:$I$5547,"Preprint") | AO19: =COUNTIFS(Items!$H$2:$H$5547,$H19,Items!$I$2:$I$5547,"Dataset") | AP19: =COUNTIFS(Items!$H$2:$H$5547,$H19,Items!$I$2:$I$5547,"Dissertation") | AQ19: =COUNTIFS(Items!$H$2:$H$5547,$H19,Items!$I$2:$I$5547,"Open educational resource") | AR19: =COUNTIFS(Items!$H$2:$H$5547,$H19,Items!$I$2:$I$5547,"Other") | AS19: =COUNTIFS(Items!$H$2:$H$5547,$H19,Items!$S$2:$S$5547,"*OpenAlex*") | AT19: =COUNTIFS(Items!$H$2:$H$5547,$H19,Items!$S$2:$S$5547,"*NIH*") | AV19: =COUNTIFS(Items!$H$2:$H$5547,$H19,Items!$AE$2:$AE$5547,"Yes") | AW19: 0
A20: 19 | B20: Baek | C20: Yousoon | D20: Yousoon Baek | E20: Assistant Professor | F20: NYC College of Technology | G20: Biological Sciences | H20: YOUSOON.BAEK49@citytech.cuny.edu | J20: https://www.citytech.cuny.edu/faculty/yousoon.baek49 | L20: FALSE | T20: =COUNTIFS(Items!$H$2:$H$5547,$H20) | U20: =COUNTIFS(Items!$H$2:$H$5547,$H20,Items!$I$2:$I$5547,"Journal article") | V20: =COUNTIFS(Items!$H$2:$H$5547,$H20,Items!$I$2:$I$5547,"Conference paper") | W20: =COUNTIFS(Items!$H$2:$H$5547,$H20,Items!$I$2:$I$5547,"Book") | X20: =COUNTIFS(Items!$H$2:$H$5547,$H20,Items!$I$2:$I$5547,"Book chapter") | Y20: =COUNTIFS(Items!$H$2:$H$5547,$H20,Items!$I$2:$I$5547,"Conference presentation") | Z20: =COUNTIFS(Items!$H$2:$H$5547,$H20,Items!$I$2:$I$5547,"Technical report") | AA20: =COUNTIFS(Items!$H$2:$H$5547,$H20,Items!$I$2:$I$5547,"Paper (venue type unclear)") | AB20: =COUNTIFS(Items!$H$2:$H$5547,$H20,Items!$I$2:$I$5547,"Patent") | AC20: =COUNTIFS(Items!$H$2:$H$5547,$H20,Items!$I$2:$I$5547,"Grant") | AD20: =COUNTIFS(Items!$H$2:$H$5547,$H20,Items!$Q$2:$Q$5547,"<>") | AE20: =COUNTIFS(Items!$H$2:$H$5547,$H20,Items!$S$2:$S$5547,"*Dept bio*") | AF20: =COUNTIFS(Items!$H$2:$H$5547,$H20,Items!$S$2:$S$5547,"*CUNY Academic Works*") | AG20: =COUNTIFS(Items!$H$2:$H$5547,$H20,Items!$S$2:$S$5547,"*ORCID*") | AH20: =COUNTIFS(Items!$H$2:$H$5547,$H20,Items!$S$2:$S$5547,"*Crossref*") | AI20: =COUNTIFS(Items!$H$2:$H$5547,$H20,Items!$S$2:$S$5547,"*NSF*") | AJ20: =COUNTIFS(Items!$H$2:$H$5547,$H20,Items!$S$2:$S$5547,"*Google Scholar*") | AL20: School of Arts & Sciences | AM20: Full-time | AN20: =COUNTIFS(Items!$H$2:$H$5547,$H20,Items!$I$2:$I$5547,"Preprint") | AO20: =COUNTIFS(Items!$H$2:$H$5547,$H20,Items!$I$2:$I$5547,"Dataset") | AP20: =COUNTIFS(Items!$H$2:$H$5547,$H20,Items!$I$2:$I$5547,"Dissertation") | AQ20: =COUNTIFS(Items!$H$2:$H$5547,$H20,Items!$I$2:$I$5547,"Open educational resource") | AR20: =COUNTIFS(Items!$H$2:$H$5547,$H20,Items!$I$2:$I$5547,"Other") | AS20: =COUNTIFS(Items!$H$2:$H$5547,$H20,Items!$S$2:$S$5547,"*OpenAlex*") | AT20: =COUNTIFS(Items!$H$2:$H$5547,$H20,Items!$S$2:$S$5547,"*NIH*") | AV20: =COUNTIFS(Items!$H$2:$H$5547,$H20,Items!$AE$2:$AE$5547,"Yes") | AW20: 0
